Workbook

Sheet 검토요약
A1: INNONOW 검토요약 v0.4
A3: 모든 신규 사례·금액은 가상 제안. 원 단위. 먼저 대표 질의 전후 효과와 남는 목표 부족분을 확인하십시오.
A5: 항목 | B5: 값 | C5: 단위·상태 | D5: 읽는 방법·근거
A6: 데이터 묶음 | B6: SC01~SC04 v0.4 수정본 | C6: 2026-10-23 | D6: 개선효과 재설정: ALT41 월3,000대·회피단가15,000원, ALT42 건당120만원. 기존 장면1~3 보존.
A7: 대응 전 연간 관리손익 | B7: =통합손익!K21 -> 3299986680 | C7: 원 | D7: 울산 A제품 a~e 범위. 기준 전망 유지.
A8: 연간 Target | B8: =통합손익!M21 -> 3477290000 | C8: 원 | D8: 자동 변경 없음.
A9: 대응 전 목표 부족 | B9: =통합손익!N21 -> 177303320 | C9: 원 | D9: 기존 부족과 신규 사건의 합계.
A10: 회의 보고 시 개선효과 | B10: =SC04비교!C9 -> 137200000 | C10: 원 | D10: 검증·중복 조정 완료 보고본 REP41-v1.
A11: 대표 질의 후 개선효과 | B11: =SC04비교!D9 -> 127800000 | C11: 원 | D11: DEC41-v2. 긴급구매 효과 시작 8월→9월.
A12: 회의 중 효과 조정 | B12: =SC04비교!E9 -> -9400000 | C12: 원 | D12: 8월 효과 1개월 감소.
A13: 대응안 반영 연간 전망 | B13: =SC04월손익!G18 -> 3427786680 | C13: 원 | D13: 의사결정용 예상. 공식 Forecast 승인 별도.
A14: 남는 목표 부족 | B14: =SC04월손익!H18 -> 49503320 | C14: 원 | D14: 추가 과제 발굴 DIR41로 관리.
A15: 조건부 효과 제외 부족 | B15: =SC04월손익!J18 -> 85103320 | C15: 원 | D15: 긴급구매 조건이 성립하지 않는 경우의 비교.
A16: 정상 연간 반복효과 | B16: =SC04비교!F9 -> 357600000 | C16: 원 | D16: 정액12개월 참고. 일회성비 제외. 2027효과와 합산 금지.
A17: 총괄 예산 한도 | B17: =SC04예산과제!E9 -> 18000000 | C17: 원 | D17: 전환·검증·교육 일회성 범위. 배분8·6·4백만원.
A18: 실행과제 인수 | B18: 3 / 3 | C18: 완료 기대상태 | D18: 전체 책임 인수 별도 완료. 승인2개·조건부1개.
A19: 미충족 조건 | B19: CON41 | C19: OPEN | D19: 생산·구매 공동 기준 마련. 계획 수립 가능, 해당 실행 착수 제한.
A20: 장면5 인계 | B20: HANDOFF41 | C20: 계획 수립 대기 | D20: 2027/7/13 10시 종료. 7/16 18시 상세 계획 제출.
A21: Risk / Forecast / Target | B21: OPEN / REVIEW_PENDING / UNCHANGED | C21: 유지 | D21: 장면 완료와 성과 달성을 구분.
A22: 검토 순서 | B22: 요약 → SC04비교 → SC04회의 → SC04예산과제 | C22: 권장 | D22: 세부 월효과·가정·예외는 개발자와 수치 검토에 활용.

Sheet 설정
A1: 통합 가상 데이터 설정
A3: 노란 값은 이번 데이터 설계의 가상 입력값입니다. 날짜·금액·내부가정 변경 시 계산표가 갱신됩니다.
A5: key | B5: value | C5: 의미 | D5: 기준 및 사용법
A6: effective_date | B6: 46569 | C6: 기본 적용일 | D6: 월초만 지원. 월중 적용은 구현 확장 필요
A7: next_year_factor | B7: 0.97 | C7: 2028 물량 가정 | D7: 2027 동일월 F01 ×97%, 정수 반올림. 2028-01~07 내부가정
A8: rate_attention | B8: 0.05 | C8: 단가 인상률 관심 | D8: 품목별 기존단가 대비
A9: rate_critical | B9: 0.1 | C9: 단가 인상률 중요 | D9: 정확히 경계값 포함
A10: amount_attention | B10: 5000000 | C10: 구매 증가액 관심 | D10: 향후12개월·공급사 요청건 합계·VAT 제외
A11: amount_critical | B11: 10000000 | C11: 구매 증가액 중요 | D11: 손익 감소액과 구분
A12: ceo_threshold | B12: 10000000 | C12: 대표 승인 기준 | D12: 최종 기안 향후12개월 구매 증가액 이상
A13: old_price | B13: 2000 | C13: 기존 공통부품 단가 | D13: C01 외주비에 이미 포함된 부품 P-COM01·원/개
A14: request_price | B14: 2200 | C14: 공급사 요청 단가 | D14: 가상값·10% 인상
A15: internal_offer | B15: 2100 | C15: 내부 협상 제시 단가 | D15: 가상값·실제 합의와 구분
A16: negotiated_price | B16: 2120 | C16: 1차 협상 잠정 단가 | D16: 가상값·6% 인상·대표 승인 시연 유지
A17: proposal_price | B17: 2120 | C17: 상신 단가 | D17: 협상안과 다르면 사유 입력 및 새 분석 필요
A18: approved_price | B18: 2120 | C18: 승인 결과 예정값 | D18: 시연 D09 이후 생성할 기대값. 초기 시드에 승인값 적재 금지
A19: negotiation_due | B19: 2027-06-21 18:00:00 KST | C19: 외부협상 기한 | D19: 구매담당 수동 입력. 건별 변경 가능·내부 SLA와 별도
A20: selected_price_version | B20: PV-APP01 | C20: 장면3 최종 비교안 | D20: 승인 결과 기준 기대 데이터. 초기화 시 아직 존재하지 않음
A21: fixed_monthly | B21: 370000000 | C21: 2028 월 고정비 가정 | D21: 2027 월 기준 유지. 원가·판매단가도 C01 유지
A22: purchase_lag | B22: 0 | C22: 구매·생산·납품 시차 | D22: 기발주·재고 없음. 구매 증가와 공헌이익 감소가 같은 단순화
A23: analysis_period_end | B23: =EDATE(B6,12) -> 46935 | C23: 향후12개월 종료 경계 | D23: 종료일 미포함. 2027-07-01~2028-06-30
A24: remaining_year_end | B24: =DATE(YEAR(B6)+1,1,1) -> 46753 | C24: 당해연도 종료 경계 | D24: 종료일 미포함
A25: expected_model_months | B25: 60 | C25: 12개월 필수 원가·물량 행수 | D25: 5모델 ×12개월. 중복키·누락값 별도 검사

Sheet 단가안비교
A1: 요청부터 승인까지 구매 증가액 비교
A3: 동일 F02·EXT28-v1 물량. H: 2027 잔여기간, I: 적용일부터12개월. 승인선은 최종 기안안으로 확정하며 다른 안의 값은 사전 미리보기입니다.
A5: price_version | B5: 종류 | C5: 기존가 | D5: 단가 | E5: 인상률 | F5: 잔여구매량 | G5: 12개월구매량 | H5: 잔여구매증가 | I5: 12개월구매증가 | J5: 비율위험 | K5: 금액위험 | L5: 종합위험 | M5: 승인선미리보기 | N5: 요청대비부담감소 | O5: 12개월CM영향
A6: PV-REQ01 | B6: 요청안 | C6: =단가버전!E6 -> 2000 | D6: =단가버전!F6 -> 2200 | E6: =IF(C6>0,(D6-C6)/C6,"미산출") -> 0.1 | F6: =IF(SUMPRODUCT(월별계산!$O$6:$O$100,월별계산!$U$6:$U$100)<>SUM(월별계산!$O$6:$O$100),"미산출",SUMPRODUCT(월별계산!$J$6:$J$100,월별계산!$O$6:$O$100)) -> 78036 | G6: =IF(SUMPRODUCT(월별계산!$N$6:$N$100,월별계산!$U$6:$U$100)<>SUM(월별계산!$N$6:$N$100),"미산출",SUMPRODUCT(월별계산!$J$6:$J$100,월별계산!$N$6:$N$100)) -> 156812 | H6: =IF(ISNUMBER(F6),F6*(D6-C6),"미산출") -> 15607200 | I6: =IF(AND(ISNUMBER(G6),SUM(월별계산!$N$6:$N$100)=설정!$B$25),G6*(D6-C6),"미산출") -> 31362400 | J6: =IF(NOT(ISNUMBER(E6)),"미산출",IF(E6>=설정!$B$9,"중요",IF(E6>=설정!$B$8,"관심","정상"))) -> 중요 | K6: =IF(NOT(ISNUMBER(I6)),"미산출",IF(I6>=설정!$B$11,"중요",IF(I6>=설정!$B$10,"관심","정상"))) -> 중요 | L6: =IF(OR(J6="미산출",K6="미산출"),"미산출",IF(OR(J6="중요",K6="중요"),"중요",IF(OR(J6="관심",K6="관심"),"관심","정상"))) -> 중요 | M6: =IF(NOT(ISNUMBER(I6)),"판정 보류",IF(I6>=설정!$B$12,"대표 대상","대표 비대상")) -> 대표 대상 | N6: =IF(AND(ISNUMBER($I$6),ISNUMBER(I6)),$I$6-I6,"미산출") -> 0 | O6: =IF(ISNUMBER(I6),-I6,"미산출") -> -31362400
A7: PV-OFFER01 | B7: 내부제시안 | C7: =단가버전!E7 -> 2000 | D7: =단가버전!F7 -> 2100 | E7: =IF(C7>0,(D7-C7)/C7,"미산출") -> 0.05 | F7: =IF(SUMPRODUCT(월별계산!$O$6:$O$100,월별계산!$U$6:$U$100)<>SUM(월별계산!$O$6:$O$100),"미산출",SUMPRODUCT(월별계산!$J$6:$J$100,월별계산!$O$6:$O$100)) -> 78036 | G7: =IF(SUMPRODUCT(월별계산!$N$6:$N$100,월별계산!$U$6:$U$100)<>SUM(월별계산!$N$6:$N$100),"미산출",SUMPRODUCT(월별계산!$J$6:$J$100,월별계산!$N$6:$N$100)) -> 156812 | H7: =IF(ISNUMBER(F7),F7*(D7-C7),"미산출") -> 7803600 | I7: =IF(AND(ISNUMBER(G7),SUM(월별계산!$N$6:$N$100)=설정!$B$25),G7*(D7-C7),"미산출") -> 15681200 | J7: =IF(NOT(ISNUMBER(E7)),"미산출",IF(E7>=설정!$B$9,"중요",IF(E7>=설정!$B$8,"관심","정상"))) -> 관심 | K7: =IF(NOT(ISNUMBER(I7)),"미산출",IF(I7>=설정!$B$11,"중요",IF(I7>=설정!$B$10,"관심","정상"))) -> 중요 | L7: =IF(OR(J7="미산출",K7="미산출"),"미산출",IF(OR(J7="중요",K7="중요"),"중요",IF(OR(J7="관심",K7="관심"),"관심","정상"))) -> 중요 | M7: =IF(NOT(ISNUMBER(I7)),"판정 보류",IF(I7>=설정!$B$12,"대표 대상","대표 비대상")) -> 대표 대상 | N7: =IF(AND(ISNUMBER($I$6),ISNUMBER(I7)),$I$6-I7,"미산출") -> 15681200 | O7: =IF(ISNUMBER(I7),-I7,"미산출") -> -15681200
A8: PV-NEG01 | B8: 1차협상안 | C8: =단가버전!E8 -> 2000 | D8: =단가버전!F8 -> 2120 | E8: =IF(C8>0,(D8-C8)/C8,"미산출") -> 0.06 | F8: =IF(SUMPRODUCT(월별계산!$O$6:$O$100,월별계산!$U$6:$U$100)<>SUM(월별계산!$O$6:$O$100),"미산출",SUMPRODUCT(월별계산!$J$6:$J$100,월별계산!$O$6:$O$100)) -> 78036 | G8: =IF(SUMPRODUCT(월별계산!$N$6:$N$100,월별계산!$U$6:$U$100)<>SUM(월별계산!$N$6:$N$100),"미산출",SUMPRODUCT(월별계산!$J$6:$J$100,월별계산!$N$6:$N$100)) -> 156812 | H8: =IF(ISNUMBER(F8),F8*(D8-C8),"미산출") -> 9364320 | I8: =IF(AND(ISNUMBER(G8),SUM(월별계산!$N$6:$N$100)=설정!$B$25),G8*(D8-C8),"미산출") -> 18817440 | J8: =IF(NOT(ISNUMBER(E8)),"미산출",IF(E8>=설정!$B$9,"중요",IF(E8>=설정!$B$8,"관심","정상"))) -> 관심 | K8: =IF(NOT(ISNUMBER(I8)),"미산출",IF(I8>=설정!$B$11,"중요",IF(I8>=설정!$B$10,"관심","정상"))) -> 중요 | L8: =IF(OR(J8="미산출",K8="미산출"),"미산출",IF(OR(J8="중요",K8="중요"),"중요",IF(OR(J8="관심",K8="관심"),"관심","정상"))) -> 중요 | M8: =IF(NOT(ISNUMBER(I8)),"판정 보류",IF(I8>=설정!$B$12,"대표 대상","대표 비대상")) -> 대표 대상 | N8: =IF(AND(ISNUMBER($I$6),ISNUMBER(I8)),$I$6-I8,"미산출") -> 12544960 | O8: =IF(ISNUMBER(I8),-I8,"미산출") -> -18817440
A9: PV-PROP01 | B9: 기안안 | C9: =단가버전!E9 -> 2000 | D9: =단가버전!F9 -> 2120 | E9: =IF(C9>0,(D9-C9)/C9,"미산출") -> 0.06 | F9: =IF(SUMPRODUCT(월별계산!$O$6:$O$100,월별계산!$U$6:$U$100)<>SUM(월별계산!$O$6:$O$100),"미산출",SUMPRODUCT(월별계산!$J$6:$J$100,월별계산!$O$6:$O$100)) -> 78036 | G9: =IF(SUMPRODUCT(월별계산!$N$6:$N$100,월별계산!$U$6:$U$100)<>SUM(월별계산!$N$6:$N$100),"미산출",SUMPRODUCT(월별계산!$J$6:$J$100,월별계산!$N$6:$N$100)) -> 156812 | H9: =IF(ISNUMBER(F9),F9*(D9-C9),"미산출") -> 9364320 | I9: =IF(AND(ISNUMBER(G9),SUM(월별계산!$N$6:$N$100)=설정!$B$25),G9*(D9-C9),"미산출") -> 18817440 | J9: =IF(NOT(ISNUMBER(E9)),"미산출",IF(E9>=설정!$B$9,"중요",IF(E9>=설정!$B$8,"관심","정상"))) -> 관심 | K9: =IF(NOT(ISNUMBER(I9)),"미산출",IF(I9>=설정!$B$11,"중요",IF(I9>=설정!$B$10,"관심","정상"))) -> 중요 | L9: =IF(OR(J9="미산출",K9="미산출"),"미산출",IF(OR(J9="중요",K9="중요"),"중요",IF(OR(J9="관심",K9="관심"),"관심","정상"))) -> 중요 | M9: =IF(NOT(ISNUMBER(I9)),"판정 보류",IF(I9>=설정!$B$12,"대표 대상","대표 비대상")) -> 대표 대상 | N9: =IF(AND(ISNUMBER($I$6),ISNUMBER(I9)),$I$6-I9,"미산출") -> 12544960 | O9: =IF(ISNUMBER(I9),-I9,"미산출") -> -18817440
A10: PV-APP01 | B10: 승인안 | C10: =단가버전!E10 -> 2000 | D10: =단가버전!F10 -> 2120 | E10: =IF(C10>0,(D10-C10)/C10,"미산출") -> 0.06 | F10: =IF(SUMPRODUCT(월별계산!$O$6:$O$100,월별계산!$U$6:$U$100)<>SUM(월별계산!$O$6:$O$100),"미산출",SUMPRODUCT(월별계산!$J$6:$J$100,월별계산!$O$6:$O$100)) -> 78036 | G10: =IF(SUMPRODUCT(월별계산!$N$6:$N$100,월별계산!$U$6:$U$100)<>SUM(월별계산!$N$6:$N$100),"미산출",SUMPRODUCT(월별계산!$J$6:$J$100,월별계산!$N$6:$N$100)) -> 156812 | H10: =IF(ISNUMBER(F10),F10*(D10-C10),"미산출") -> 9364320 | I10: =IF(AND(ISNUMBER(G10),SUM(월별계산!$N$6:$N$100)=설정!$B$25),G10*(D10-C10),"미산출") -> 18817440 | J10: =IF(NOT(ISNUMBER(E10)),"미산출",IF(E10>=설정!$B$9,"중요",IF(E10>=설정!$B$8,"관심","정상"))) -> 관심 | K10: =IF(NOT(ISNUMBER(I10)),"미산출",IF(I10>=설정!$B$11,"중요",IF(I10>=설정!$B$10,"관심","정상"))) -> 중요 | L10: =IF(OR(J10="미산출",K10="미산출"),"미산출",IF(OR(J10="중요",K10="중요"),"중요",IF(OR(J10="관심",K10="관심"),"관심","정상"))) -> 중요 | M10: =IF(NOT(ISNUMBER(I10)),"판정 보류",IF(I10>=설정!$B$12,"대표 대상","대표 비대상")) -> 대표 대상 | N10: =IF(AND(ISNUMBER($I$6),ISNUMBER(I10)),$I$6-I10,"미산출") -> 12544960 | O10: =IF(ISNUMBER(I10),-I10,"미산출") -> -18817440

Sheet 통합손익
A1: 장면 1·2 통합 관리손익
A3: 모든 금액 원. 관리손익=공헌이익−공장고정비. 본사비·금융비·세금 제외. 향후12개월 Target은 미설정이며 당해연도 Target을 혼용하지 않습니다.
A5: 기간 | B5: 시작일 | C5: 종료경계 | D5: 구분 | E5: F02매출 | F5: 공장고정비 | G5: F01기준손익 | H5: 물량반영손익 | I5: 장면1물량영향 | J5: 장면2원가영향 | K5: 통합손익 | L5: 전체변동 | M5: Target손익 | N5: Target부족 | O5: 브리지차이
A6: 2027-01 | B6: 46388 | C6: 46419 | D6: 월 | E6: =SUMIFS(월별계산!$S$6:$S$100,월별계산!$B$6:$B$100,">="&B6,월별계산!$B$6:$B$100,"<"&C6) -> 5989630000 | F6: =SUMIFS(월고정비!$B$6:$B$24,월고정비!$A$6:$A$24,">="&B6,월고정비!$A$6:$A$24,"<"&C6) -> 370000000 | G6: =SUMIFS(월별계산!$K$6:$K$100,월별계산!$B$6:$B$100,">="&B6,월별계산!$B$6:$B$100,"<"&C6)-F6 -> 309349000 | H6: =SUMIFS(월별계산!$L$6:$L$100,월별계산!$B$6:$B$100,">="&B6,월별계산!$B$6:$B$100,"<"&C6)-F6 -> 309349000 | I6: =H6-G6 -> 0 | J6: =-SUMIFS(월별계산!$P$6:$P$100,월별계산!$B$6:$B$100,">="&B6,월별계산!$B$6:$B$100,"<"&C6) -> 0 | K6: =H6+J6 -> 309349000 | L6: =K6-G6 -> 0 | M6: =SUMIFS(월별계산!$R$6:$R$100,월별계산!$B$6:$B$100,">="&B6,월별계산!$B$6:$B$100,"<"&C6)-F6 -> 310340000 | N6: =M6-K6 -> 991000 | O6: =K6-(G6+I6+J6) -> 0
A7: 2027-02 | B7: 46419 | C7: 46447 | D7: 월 | E7: =SUMIFS(월별계산!$S$6:$S$100,월별계산!$B$6:$B$100,">="&B7,월별계산!$B$6:$B$100,"<"&C7) -> 5257980000 | F7: =SUMIFS(월고정비!$B$6:$B$24,월고정비!$A$6:$A$24,">="&B7,월고정비!$A$6:$A$24,"<"&C7) -> 370000000 | G7: =SUMIFS(월별계산!$K$6:$K$100,월별계산!$B$6:$B$100,">="&B7,월별계산!$B$6:$B$100,"<"&C7)-F7 -> 226547000 | H7: =SUMIFS(월별계산!$L$6:$L$100,월별계산!$B$6:$B$100,">="&B7,월별계산!$B$6:$B$100,"<"&C7)-F7 -> 226547000 | I7: =H7-G7 -> 0 | J7: =-SUMIFS(월별계산!$P$6:$P$100,월별계산!$B$6:$B$100,">="&B7,월별계산!$B$6:$B$100,"<"&C7) -> 0 | K7: =H7+J7 -> 226547000 | L7: =K7-G7 -> 0 | M7: =SUMIFS(월별계산!$R$6:$R$100,월별계산!$B$6:$B$100,">="&B7,월별계산!$B$6:$B$100,"<"&C7)-F7 -> 230300000 | N7: =M7-K7 -> 3753000 | O7: =K7-(G7+I7+J7) -> 0
A8: 2027-03 | B8: 46447 | C8: 46478 | D8: 월 | E8: =SUMIFS(월별계산!$S$6:$S$100,월별계산!$B$6:$B$100,">="&B8,월별계산!$B$6:$B$100,"<"&C8) -> 6102990000 | F8: =SUMIFS(월고정비!$B$6:$B$24,월고정비!$A$6:$A$24,">="&B8,월고정비!$A$6:$A$24,"<"&C8) -> 370000000 | G8: =SUMIFS(월별계산!$K$6:$K$100,월별계산!$B$6:$B$100,">="&B8,월별계산!$B$6:$B$100,"<"&C8)-F8 -> 322633000 | H8: =SUMIFS(월별계산!$L$6:$L$100,월별계산!$B$6:$B$100,">="&B8,월별계산!$B$6:$B$100,"<"&C8)-F8 -> 322633000 | I8: =H8-G8 -> 0 | J8: =-SUMIFS(월별계산!$P$6:$P$100,월별계산!$B$6:$B$100,">="&B8,월별계산!$B$6:$B$100,"<"&C8) -> 0 | K8: =H8+J8 -> 322633000 | L8: =K8-G8 -> 0 | M8: =SUMIFS(월별계산!$R$6:$R$100,월별계산!$B$6:$B$100,">="&B8,월별계산!$B$6:$B$100,"<"&C8)-F8 -> 330350000 | N8: =M8-K8 -> 7717000 | O8: =K8-(G8+I8+J8) -> 0
A9: 2027-04 | B9: 46478 | C9: 46508 | D9: 월 | E9: =SUMIFS(월별계산!$S$6:$S$100,월별계산!$B$6:$B$100,">="&B9,월별계산!$B$6:$B$100,"<"&C9) -> 5782200000 | F9: =SUMIFS(월고정비!$B$6:$B$24,월고정비!$A$6:$A$24,">="&B9,월고정비!$A$6:$A$24,"<"&C9) -> 370000000 | G9: =SUMIFS(월별계산!$K$6:$K$100,월별계산!$B$6:$B$100,">="&B9,월별계산!$B$6:$B$100,"<"&C9)-F9 -> 286430000 | H9: =SUMIFS(월별계산!$L$6:$L$100,월별계산!$B$6:$B$100,">="&B9,월별계산!$B$6:$B$100,"<"&C9)-F9 -> 286430000 | I9: =H9-G9 -> 0 | J9: =-SUMIFS(월별계산!$P$6:$P$100,월별계산!$B$6:$B$100,">="&B9,월별계산!$B$6:$B$100,"<"&C9) -> 0 | K9: =H9+J9 -> 286430000 | L9: =K9-G9 -> 0 | M9: =SUMIFS(월별계산!$R$6:$R$100,월별계산!$B$6:$B$100,">="&B9,월별계산!$B$6:$B$100,"<"&C9)-F9 -> 297000000 | N9: =M9-K9 -> 10570000 | O9: =K9-(G9+I9+J9) -> 0
A10: 2027-05 | B10: 46508 | C10: 46539 | D10: 월 | E10: =SUMIFS(월별계산!$S$6:$S$100,월별계산!$B$6:$B$100,">="&B10,월별계산!$B$6:$B$100,"<"&C10) -> 5637110000 | F10: =SUMIFS(월고정비!$B$6:$B$24,월고정비!$A$6:$A$24,">="&B10,월고정비!$A$6:$A$24,"<"&C10) -> 370000000 | G10: =SUMIFS(월별계산!$K$6:$K$100,월별계산!$B$6:$B$100,">="&B10,월별계산!$B$6:$B$100,"<"&C10)-F10 -> 270161000 | H10: =SUMIFS(월별계산!$L$6:$L$100,월별계산!$B$6:$B$100,">="&B10,월별계산!$B$6:$B$100,"<"&C10)-F10 -> 270161000 | I10: =H10-G10 -> 0 | J10: =-SUMIFS(월별계산!$P$6:$P$100,월별계산!$B$6:$B$100,">="&B10,월별계산!$B$6:$B$100,"<"&C10) -> 0 | K10: =H10+J10 -> 270161000 | L10: =K10-G10 -> 0 | M10: =SUMIFS(월별계산!$R$6:$R$100,월별계산!$B$6:$B$100,">="&B10,월별계산!$B$6:$B$100,"<"&C10)-F10 -> 283660000 | N10: =M10-K10 -> 13499000 | O10: =K10-(G10+I10+J10) -> 0
A11: 2027-06 | B11: 46539 | C11: 46569 | D11: 월 | E11: =SUMIFS(월별계산!$S$6:$S$100,월별계산!$B$6:$B$100,">="&B11,월별계산!$B$6:$B$100,"<"&C11) -> 5722200000 | F11: =SUMIFS(월고정비!$B$6:$B$24,월고정비!$A$6:$A$24,">="&B11,월고정비!$A$6:$A$24,"<"&C11) -> 370000000 | G11: =SUMIFS(월별계산!$K$6:$K$100,월별계산!$B$6:$B$100,">="&B11,월별계산!$B$6:$B$100,"<"&C11)-F11 -> 280030000 | H11: =SUMIFS(월별계산!$L$6:$L$100,월별계산!$B$6:$B$100,">="&B11,월별계산!$B$6:$B$100,"<"&C11)-F11 -> 280030000 | I11: =H11-G11 -> 0 | J11: =-SUMIFS(월별계산!$P$6:$P$100,월별계산!$B$6:$B$100,">="&B11,월별계산!$B$6:$B$100,"<"&C11) -> 0 | K11: =H11+J11 -> 280030000 | L11: =K11-G11 -> 0 | M11: =SUMIFS(월별계산!$R$6:$R$100,월별계산!$B$6:$B$100,">="&B11,월별계산!$B$6:$B$100,"<"&C11)-F11 -> 297000000 | N11: =M11-K11 -> 16970000 | O11: =K11-(G11+I11+J11) -> 0
A12: 2027-07 | B12: 46569 | C12: 46600 | D12: 월 | E12: =SUMIFS(월별계산!$S$6:$S$100,월별계산!$B$6:$B$100,">="&B12,월별계산!$B$6:$B$100,"<"&C12) -> 5596200000 | F12: =SUMIFS(월고정비!$B$6:$B$24,월고정비!$A$6:$A$24,">="&B12,월고정비!$A$6:$A$24,"<"&C12) -> 370000000 | G12: =SUMIFS(월별계산!$K$6:$K$100,월별계산!$B$6:$B$100,">="&B12,월별계산!$B$6:$B$100,"<"&C12)-F12 -> 280030000 | H12: =SUMIFS(월별계산!$L$6:$L$100,월별계산!$B$6:$B$100,">="&B12,월별계산!$B$6:$B$100,"<"&C12)-F12 -> 266030000 | I12: =H12-G12 -> -14000000 | J12: =-SUMIFS(월별계산!$P$6:$P$100,월별계산!$B$6:$B$100,">="&B12,월별계산!$B$6:$B$100,"<"&C12) -> -1512000 | K12: =H12+J12 -> 264518000 | L12: =K12-G12 -> -15512000 | M12: =SUMIFS(월별계산!$R$6:$R$100,월별계산!$B$6:$B$100,">="&B12,월별계산!$B$6:$B$100,"<"&C12)-F12 -> 297000000 | N12: =M12-K12 -> 32482000 | O12: =K12-(G12+I12+J12) -> 0
A13: 2027-08 | B13: 46600 | C13: 46631 | D13: 월 | E13: =SUMIFS(월별계산!$S$6:$S$100,월별계산!$B$6:$B$100,">="&B13,월별계산!$B$6:$B$100,"<"&C13) -> 5264410000 | F13: =SUMIFS(월고정비!$B$6:$B$24,월고정비!$A$6:$A$24,">="&B13,월고정비!$A$6:$A$24,"<"&C13) -> 370000000 | G13: =SUMIFS(월별계산!$K$6:$K$100,월별계산!$B$6:$B$100,">="&B13,월별계산!$B$6:$B$100,"<"&C13)-F13 -> 228026000 | H13: =SUMIFS(월별계산!$L$6:$L$100,월별계산!$B$6:$B$100,">="&B13,월별계산!$B$6:$B$100,"<"&C13)-F13 -> 228026000 | I13: =H13-G13 -> 0 | J13: =-SUMIFS(월별계산!$P$6:$P$100,월별계산!$B$6:$B$100,">="&B13,월별계산!$B$6:$B$100,"<"&C13) -> -1468320 | K13: =H13+J13 -> 226557680 | L13: =K13-G13 -> -1468320 | M13: =SUMIFS(월별계산!$R$6:$R$100,월별계산!$B$6:$B$100,">="&B13,월별계산!$B$6:$B$100,"<"&C13)-F13 -> 243640000 | N13: =M13-K13 -> 17082320 | O13: =K13-(G13+I13+J13) -> 0
A14: 2027-09 | B14: 46631 | C14: 46661 | D14: 월 | E14: =SUMIFS(월별계산!$S$6:$S$100,월별계산!$B$6:$B$100,">="&B14,월별계산!$B$6:$B$100,"<"&C14) -> 5893910000 | F14: =SUMIFS(월고정비!$B$6:$B$24,월고정비!$A$6:$A$24,">="&B14,월고정비!$A$6:$A$24,"<"&C14) -> 370000000 | G14: =SUMIFS(월별계산!$K$6:$K$100,월별계산!$B$6:$B$100,">="&B14,월별계산!$B$6:$B$100,"<"&C14)-F14 -> 299536000 | H14: =SUMIFS(월별계산!$L$6:$L$100,월별계산!$B$6:$B$100,">="&B14,월별계산!$B$6:$B$100,"<"&C14)-F14 -> 299536000 | I14: =H14-G14 -> 0 | J14: =-SUMIFS(월별계산!$P$6:$P$100,월별계산!$B$6:$B$100,">="&B14,월별계산!$B$6:$B$100,"<"&C14) -> -1643880 | K14: =H14+J14 -> 297892120 | L14: =K14-G14 -> -1643880 | M14: =SUMIFS(월별계산!$R$6:$R$100,월별계산!$B$6:$B$100,">="&B14,월별계산!$B$6:$B$100,"<"&C14)-F14 -> 317010000 | N14: =M14-K14 -> 19117880 | O14: =K14-(G14+I14+J14) -> 0
A15: 2027-10 | B15: 46661 | C15: 46692 | D15: 월 | E15: =SUMIFS(월별계산!$S$6:$S$100,월별계산!$B$6:$B$100,">="&B15,월별계산!$B$6:$B$100,"<"&C15) -> 5836630000 | F15: =SUMIFS(월고정비!$B$6:$B$24,월고정비!$A$6:$A$24,">="&B15,월고정비!$A$6:$A$24,"<"&C15) -> 370000000 | G15: =SUMIFS(월별계산!$K$6:$K$100,월별계산!$B$6:$B$100,">="&B15,월별계산!$B$6:$B$100,"<"&C15)-F15 -> 293029000 | H15: =SUMIFS(월별계산!$L$6:$L$100,월별계산!$B$6:$B$100,">="&B15,월별계산!$B$6:$B$100,"<"&C15)-F15 -> 293029000 | I15: =H15-G15 -> 0 | J15: =-SUMIFS(월별계산!$P$6:$P$100,월별계산!$B$6:$B$100,">="&B15,월별계산!$B$6:$B$100,"<"&C15) -> -1627920 | K15: =H15+J15 -> 291401080 | L15: =K15-G15 -> -1627920 | M15: =SUMIFS(월별계산!$R$6:$R$100,월별계산!$B$6:$B$100,">="&B15,월별계산!$B$6:$B$100,"<"&C15)-F15 -> 310340000 | N15: =M15-K15 -> 18938920 | O15: =K15-(G15+I15+J15) -> 0
A16: 2027-11 | B16: 46692 | C16: 46722 | D16: 월 | E16: =SUMIFS(월별계산!$S$6:$S$100,월별계산!$B$6:$B$100,">="&B16,월별계산!$B$6:$B$100,"<"&C16) -> 5722200000 | F16: =SUMIFS(월고정비!$B$6:$B$24,월고정비!$A$6:$A$24,">="&B16,월고정비!$A$6:$A$24,"<"&C16) -> 370000000 | G16: =SUMIFS(월별계산!$K$6:$K$100,월별계산!$B$6:$B$100,">="&B16,월별계산!$B$6:$B$100,"<"&C16)-F16 -> 280030000 | H16: =SUMIFS(월별계산!$L$6:$L$100,월별계산!$B$6:$B$100,">="&B16,월별계산!$B$6:$B$100,"<"&C16)-F16 -> 280030000 | I16: =H16-G16 -> 0 | J16: =-SUMIFS(월별계산!$P$6:$P$100,월별계산!$B$6:$B$100,">="&B16,월별계산!$B$6:$B$100,"<"&C16) -> -1596000 | K16: =H16+J16 -> 278434000 | L16: =K16-G16 -> -1596000 | M16: =SUMIFS(월별계산!$R$6:$R$100,월별계산!$B$6:$B$100,">="&B16,월별계산!$B$6:$B$100,"<"&C16)-F16 -> 297000000 | N16: =M16-K16 -> 18566000 | O16: =K16-(G16+I16+J16) -> 0
A17: 2027-12 | B17: 46722 | C17: 46753 | D17: 월 | E17: =SUMIFS(월별계산!$S$6:$S$100,월별계산!$B$6:$B$100,">="&B17,월별계산!$B$6:$B$100,"<"&C17) -> 5436270000 | F17: =SUMIFS(월고정비!$B$6:$B$24,월고정비!$A$6:$A$24,">="&B17,월고정비!$A$6:$A$24,"<"&C17) -> 370000000 | G17: =SUMIFS(월별계산!$K$6:$K$100,월별계산!$B$6:$B$100,">="&B17,월별계산!$B$6:$B$100,"<"&C17)-F17 -> 247550000 | H17: =SUMIFS(월별계산!$L$6:$L$100,월별계산!$B$6:$B$100,">="&B17,월별계산!$B$6:$B$100,"<"&C17)-F17 -> 247550000 | I17: =H17-G17 -> 0 | J17: =-SUMIFS(월별계산!$P$6:$P$100,월별계산!$B$6:$B$100,">="&B17,월별계산!$B$6:$B$100,"<"&C17) -> -1516200 | K17: =H17+J17 -> 246033800 | L17: =K17-G17 -> -1516200 | M17: =SUMIFS(월별계산!$R$6:$R$100,월별계산!$B$6:$B$100,">="&B17,월별계산!$B$6:$B$100,"<"&C17)-F17 -> 263650000 | N17: =M17-K17 -> 17616200 | O17: =K17-(G17+I17+J17) -> 0
... A19: 2027 Q4 | B19: 46661 | C19: 46753 | D19: 분기 | E19: =SUMIFS(월별계산!$S$6:$S$100,월별계산!$B$6:$B$100,">="&B19,월별계산!$B$6:$B$100,"<"&C19) -> 16995100000 | F19: =SUMIFS(월고정비!$B$6:$B$24,월고정비!$A$6:$A$24,">="&B19,월고정비!$A$6:$A$24,"<"&C19) -> 1110000000 | G19: =SUMIFS(월별계산!$K$6:$K$100,월별계산!$B$6:$B$100,">="&B19,월별계산!$B$6:$B$100,"<"&C19)-F19 -> 820609000 | H19: =SUMIFS(월별계산!$L$6:$L$100,월별계산!$B$6:$B$100,">="&B19,월별계산!$B$6:$B$100,"<"&C19)-F19 -> 820609000 | I19: =H19-G19 -> 0 | J19: =-SUMIFS(월별계산!$P$6:$P$100,월별계산!$B$6:$B$100,">="&B19,월별계산!$B$6:$B$100,"<"&C19) -> -4740120 | K19: =H19+J19 -> 815868880 | L19: =K19-G19 -> -4740120 | M19: =SUMIFS(월별계산!$R$6:$R$100,월별계산!$B$6:$B$100,">="&B19,월별계산!$B$6:$B$100,"<"&C19)-F19 -> 870990000 | N19: =M19-K19 -> 55121120 | O19: =K19-(G19+I19+J19) -> 0
A20: 2027 잔여 | B20: =설정!B6 -> 46569 | C20: 46753 | D20: 잔여 | E20: =SUMIFS(월별계산!$S$6:$S$100,월별계산!$B$6:$B$100,">="&B20,월별계산!$B$6:$B$100,"<"&C20) -> 33749620000 | F20: =SUMIFS(월고정비!$B$6:$B$24,월고정비!$A$6:$A$24,">="&B20,월고정비!$A$6:$A$24,"<"&C20) -> 2220000000 | G20: =SUMIFS(월별계산!$K$6:$K$100,월별계산!$B$6:$B$100,">="&B20,월별계산!$B$6:$B$100,"<"&C20)-F20 -> 1628201000 | H20: =SUMIFS(월별계산!$L$6:$L$100,월별계산!$B$6:$B$100,">="&B20,월별계산!$B$6:$B$100,"<"&C20)-F20 -> 1614201000 | I20: =H20-G20 -> -14000000 | J20: =-SUMIFS(월별계산!$P$6:$P$100,월별계산!$B$6:$B$100,">="&B20,월별계산!$B$6:$B$100,"<"&C20) -> -9364320 | K20: =H20+J20 -> 1604836680 | L20: =K20-G20 -> -23364320 | M20: =SUMIFS(월별계산!$R$6:$R$100,월별계산!$B$6:$B$100,">="&B20,월별계산!$B$6:$B$100,"<"&C20)-F20 -> 1728640000 | N20: =M20-K20 -> 123803320 | O20: =K20-(G20+I20+J20) -> 0
A21: 2027 연간 | B21: 46388 | C21: 46753 | D21: 연간 | E21: =SUMIFS(월별계산!$S$6:$S$100,월별계산!$B$6:$B$100,">="&B21,월별계산!$B$6:$B$100,"<"&C21) -> 68241730000 | F21: =SUMIFS(월고정비!$B$6:$B$24,월고정비!$A$6:$A$24,">="&B21,월고정비!$A$6:$A$24,"<"&C21) -> 4440000000 | G21: =SUMIFS(월별계산!$K$6:$K$100,월별계산!$B$6:$B$100,">="&B21,월별계산!$B$6:$B$100,"<"&C21)-F21 -> 3323351000 | H21: =SUMIFS(월별계산!$L$6:$L$100,월별계산!$B$6:$B$100,">="&B21,월별계산!$B$6:$B$100,"<"&C21)-F21 -> 3309351000 | I21: =H21-G21 -> -14000000 | J21: =-SUMIFS(월별계산!$P$6:$P$100,월별계산!$B$6:$B$100,">="&B21,월별계산!$B$6:$B$100,"<"&C21) -> -9364320 | K21: =H21+J21 -> 3299986680 | L21: =K21-G21 -> -23364320 | M21: =SUMIFS(월별계산!$R$6:$R$100,월별계산!$B$6:$B$100,">="&B21,월별계산!$B$6:$B$100,"<"&C21)-F21 -> 3477290000 | N21: =M21-K21 -> 177303320 | O21: =K21-(G21+I21+J21) -> 0
A22: 향후12개월 | B22: =설정!B6 -> 46569 | C22: =설정!B23 -> 46935 | D22: 12개월 | E22: =SUMIFS(월별계산!$S$6:$S$100,월별계산!$B$6:$B$100,">="&B22,월별계산!$B$6:$B$100,"<"&C22) -> 67207730000 | F22: =SUMIFS(월고정비!$B$6:$B$24,월고정비!$A$6:$A$24,">="&B22,월고정비!$A$6:$A$24,"<"&C22) -> 4440000000 | G22: =SUMIFS(월별계산!$K$6:$K$100,월별계산!$B$6:$B$100,">="&B22,월별계산!$B$6:$B$100,"<"&C22)-F22 -> 3205981000 | H22: =SUMIFS(월별계산!$L$6:$L$100,월별계산!$B$6:$B$100,">="&B22,월별계산!$B$6:$B$100,"<"&C22)-F22 -> 3191981000 | I22: =H22-G22 -> -14000000 | J22: =-SUMIFS(월별계산!$P$6:$P$100,월별계산!$B$6:$B$100,">="&B22,월별계산!$B$6:$B$100,"<"&C22) -> -18817440 | K22: =H22+J22 -> 3173163560 | L22: =K22-G22 -> -32817440 | O22: =K22-(G22+I22+J22) -> 0

Sheet 월별계산
A1: 월별·모델별 손익 및 구매수량
A3: 금액 원, 수량 개/대분. 가격 인상은 적용일 이후에만 반영합니다. 2028년 비교안은 모두 같은 내부가정·원가·고정비 범위를 사용합니다.
A5: row_key | B5: period | C5: model_id | D5: F01_qty | E5: F02_qty | F5: 판매단가 | G5: C01변동비 | H5: 기준단위CM | I5: 부품소요량 | J5: 부품구매량 | K5: F01_CM | L5: F02_CM | M5: 물량순영향 | N5: 12개월포함 | O5: 당해잔여포함 | P5: 승인안원가증가 | Q5: 통합_CM | R5: Target_CM | S5: F02매출 | T5: 승인안외주비 | U5: 원천유효
A6: =물량원가기준!A6 -> 2027-01|A-a | B6: =물량원가기준!B6 -> 46388 | C6: =물량원가기준!C6 -> A-a | D6: =물량원가기준!E6 -> 4080 | E6: =물량원가기준!F6 -> 4080 | F6: =물량원가기준!G6 -> 300000 | G6: =SUM(물량원가기준!H6:J6) -> 270000 | H6: =F6-G6 -> 30000 | I6: =부품모델매핑!D6 -> 1 | J6: =IF(ISNUMBER(물량원가기준!F6),E6*I6,"미산출") -> 4080 | K6: =D6*H6 -> 122400000 | L6: =E6*H6 -> 122400000 | M6: =L6-K6 -> 0 | N6: =IF(AND(B6>=설정!$B$6,B6<설정!$B$23),1,0) -> 0 | O6: =IF(AND(B6>=설정!$B$6,B6<설정!$B$24),1,0) -> 0 | P6: =IF(B6>=설정!$B$6,J6*(설정!$B$18-설정!$B$13),0) -> 0 | Q6: =L6-P6 -> 122400000 | R6: =IF(물량원가기준!D6="","",물량원가기준!D6*H6) -> 122400000 | S6: =E6*F6 -> 1224000000 | T6: =물량원가기준!I6+IF(B6>=설정!$B$6,I6*(설정!$B$18-설정!$B$13),0) -> 75000 | U6: =IF(OR(COUNT(물량원가기준!E6:J6)<>6,COUNTIFS(물량원가기준!$A$6:$A$100,A6)<>1),0,1) -> 1
A7: =물량원가기준!A7 -> 2027-01|A-b | B7: =물량원가기준!B7 -> 46388 | C7: =물량원가기준!C7 -> A-b | D7: =물량원가기준!E7 -> 10200 | E7: =물량원가기준!F7 -> 10200 | F7: =물량원가기준!G7 -> 180000 | G7: =SUM(물량원가기준!H7:J7) -> 160000 | H7: =F7-G7 -> 20000 | I7: =부품모델매핑!D7 -> 1 | J7: =IF(ISNUMBER(물량원가기준!F7),E7*I7,"미산출") -> 10200 | K7: =D7*H7 -> 204000000 | L7: =E7*H7 -> 204000000 | M7: =L7-K7 -> 0 | N7: =IF(AND(B7>=설정!$B$6,B7<설정!$B$23),1,0) -> 0 | O7: =IF(AND(B7>=설정!$B$6,B7<설정!$B$24),1,0) -> 0 | P7: =IF(B7>=설정!$B$6,J7*(설정!$B$18-설정!$B$13),0) -> 0 | Q7: =L7-P7 -> 204000000 | R7: =IF(물량원가기준!D7="","",물량원가기준!D7*H7) -> 204000000 | S7: =E7*F7 -> 1836000000 | T7: =물량원가기준!I7+IF(B7>=설정!$B$6,I7*(설정!$B$18-설정!$B$13),0) -> 95000 | U7: =IF(OR(COUNT(물량원가기준!E7:J7)<>6,COUNTIFS(물량원가기준!$A$6:$A$100,A7)<>1),0,1) -> 1
A8: =물량원가기준!A8 -> 2027-01|A-c | B8: =물량원가기준!B8 -> 46388 | C8: =물량원가기준!C8 -> A-c | D8: =물량원가기준!E8 -> 6059 | E8: =물량원가기준!F8 -> 6059 | F8: =물량원가기준!G8 -> 230000 | G8: =SUM(물량원가기준!H8:J8) -> 202000 | H8: =F8-G8 -> 28000 | I8: =부품모델매핑!D8 -> 0 | J8: =IF(ISNUMBER(물량원가기준!F8),E8*I8,"미산출") -> 0 | K8: =D8*H8 -> 169652000 | L8: =E8*H8 -> 169652000 | M8: =L8-K8 -> 0 | N8: =IF(AND(B8>=설정!$B$6,B8<설정!$B$23),1,0) -> 0 | O8: =IF(AND(B8>=설정!$B$6,B8<설정!$B$24),1,0) -> 0 | P8: =IF(B8>=설정!$B$6,J8*(설정!$B$18-설정!$B$13),0) -> 0 | Q8: =L8-P8 -> 169652000 | R8: =IF(물량원가기준!D8="","",물량원가기준!D8*H8) -> 171360000 | S8: =E8*F8 -> 1393570000 | T8: =물량원가기준!I8+IF(B8>=설정!$B$6,I8*(설정!$B$18-설정!$B$13),0) -> 60000 | U8: =IF(OR(COUNT(물량원가기준!E8:J8)<>6,COUNTIFS(물량원가기준!$A$6:$A$100,A8)<>1),0,1) -> 1
A9: =물량원가기준!A9 -> 2027-01|A-d | B9: =물량원가기준!B9 -> 46388 | C9: =물량원가기준!C9 -> A-d | D9: =물량원가기준!E9 -> 5151 | E9: =물량원가기준!F9 -> 5151 | F9: =물량원가기준!G9 -> 210000 | G9: =SUM(물량원가기준!H9:J9) -> 185000 | H9: =F9-G9 -> 25000 | I9: =부품모델매핑!D9 -> 0 | J9: =IF(ISNUMBER(물량원가기준!F9),E9*I9,"미산출") -> 0 | K9: =D9*H9 -> 128775000 | L9: =E9*H9 -> 128775000 | M9: =L9-K9 -> 0 | N9: =IF(AND(B9>=설정!$B$6,B9<설정!$B$23),1,0) -> 0 | O9: =IF(AND(B9>=설정!$B$6,B9<설정!$B$24),1,0) -> 0 | P9: =IF(B9>=설정!$B$6,J9*(설정!$B$18-설정!$B$13),0) -> 0 | Q9: =L9-P9 -> 128775000 | R9: =IF(물량원가기준!D9="","",물량원가기준!D9*H9) -> 127500000 | S9: =E9*F9 -> 1081710000 | T9: =물량원가기준!I9+IF(B9>=설정!$B$6,I9*(설정!$B$18-설정!$B$13),0) -> 65000 | U9: =IF(OR(COUNT(물량원가기준!E9:J9)<>6,COUNTIFS(물량원가기준!$A$6:$A$100,A9)<>1),0,1) -> 1
A10: =물량원가기준!A10 -> 2027-01|A-e | B10: =물량원가기준!B10 -> 46388 | C10: =물량원가기준!C10 -> A-e | D10: =물량원가기준!E10 -> 3029 | E10: =물량원가기준!F10 -> 3029 | F10: =물량원가기준!G10 -> 150000 | G10: =SUM(물량원가기준!H10:J10) -> 132000 | H10: =F10-G10 -> 18000 | I10: =부품모델매핑!D10 -> 0 | J10: =IF(ISNUMBER(물량원가기준!F10),E10*I10,"미산출") -> 0 | K10: =D10*H10 -> 54522000 | L10: =E10*H10 -> 54522000 | M10: =L10-K10 -> 0 | N10: =IF(AND(B10>=설정!$B$6,B10<설정!$B$23),1,0) -> 0 | O10: =IF(AND(B10>=설정!$B$6,B10<설정!$B$24),1,0) -> 0 | P10: =IF(B10>=설정!$B$6,J10*(설정!$B$18-설정!$B$13),0) -> 0 | Q10: =L10-P10 -> 54522000 | R10: =IF(물량원가기준!D10="","",물량원가기준!D10*H10) -> 55080000 | S10: =E10*F10 -> 454350000 | T10: =물량원가기준!I10+IF(B10>=설정!$B$6,I10*(설정!$B$18-설정!$B$13),0) -> 50000 | U10: =IF(OR(COUNT(물량원가기준!E10:J10)<>6,COUNTIFS(물량원가기준!$A$6:$A$100,A10)<>1),0,1) -> 1
A11: =물량원가기준!A11 -> 2027-02|A-a | B11: =물량원가기준!B11 -> 46419 | C11: =물량원가기준!C11 -> A-a | D11: =물량원가기준!E11 -> 3564 | E11: =물량원가기준!F11 -> 3564 | F11: =물량원가기준!G11 -> 300000 | G11: =SUM(물량원가기준!H11:J11) -> 270000 | H11: =F11-G11 -> 30000 | I11: =부품모델매핑!D6 -> 1 | J11: =IF(ISNUMBER(물량원가기준!F11),E11*I11,"미산출") -> 3564 | K11: =D11*H11 -> 106920000 | L11: =E11*H11 -> 106920000 | M11: =L11-K11 -> 0 | N11: =IF(AND(B11>=설정!$B$6,B11<설정!$B$23),1,0) -> 0 | O11: =IF(AND(B11>=설정!$B$6,B11<설정!$B$24),1,0) -> 0 | P11: =IF(B11>=설정!$B$6,J11*(설정!$B$18-설정!$B$13),0) -> 0 | Q11: =L11-P11 -> 106920000 | R11: =IF(물량원가기준!D11="","",물량원가기준!D11*H11) -> 108000000 | S11: =E11*F11 -> 1069200000 | T11: =물량원가기준!I11+IF(B11>=설정!$B$6,I11*(설정!$B$18-설정!$B$13),0) -> 75000 | U11: =IF(OR(COUNT(물량원가기준!E11:J11)<>6,COUNTIFS(물량원가기준!$A$6:$A$100,A11)<>1),0,1) -> 1
A12: =물량원가기준!A12 -> 2027-02|A-b | B12: =물량원가기준!B12 -> 46419 | C12: =물량원가기준!C12 -> A-b | D12: =물량원가기준!E12 -> 8910 | E12: =물량원가기준!F12 -> 8910 | F12: =물량원가기준!G12 -> 180000 | G12: =SUM(물량원가기준!H12:J12) -> 160000 | H12: =F12-G12 -> 20000 | I12: =부품모델매핑!D7 -> 1 | J12: =IF(ISNUMBER(물량원가기준!F12),E12*I12,"미산출") -> 8910 | K12: =D12*H12 -> 178200000 | L12: =E12*H12 -> 178200000 | M12: =L12-K12 -> 0 | N12: =IF(AND(B12>=설정!$B$6,B12<설정!$B$23),1,0) -> 0 | O12: =IF(AND(B12>=설정!$B$6,B12<설정!$B$24),1,0) -> 0 | P12: =IF(B12>=설정!$B$6,J12*(설정!$B$18-설정!$B$13),0) -> 0 | Q12: =L12-P12 -> 178200000 | R12: =IF(물량원가기준!D12="","",물량원가기준!D12*H12) -> 180000000 | S12: =E12*F12 -> 1603800000 | T12: =물량원가기준!I12+IF(B12>=설정!$B$6,I12*(설정!$B$18-설정!$B$13),0) -> 95000 | U12: =IF(OR(COUNT(물량원가기준!E12:J12)<>6,COUNTIFS(물량원가기준!$A$6:$A$100,A12)<>1),0,1) -> 1
A13: =물량원가기준!A13 -> 2027-02|A-c | B13: =물량원가기준!B13 -> 46419 | C13: =물량원가기준!C13 -> A-c | D13: =물량원가기준!E13 -> 5346 | E13: =물량원가기준!F13 -> 5346 | F13: =물량원가기준!G13 -> 230000 | G13: =SUM(물량원가기준!H13:J13) -> 202000 | H13: =F13-G13 -> 28000 | I13: =부품모델매핑!D8 -> 0 | J13: =IF(ISNUMBER(물량원가기준!F13),E13*I13,"미산출") -> 0 | K13: =D13*H13 -> 149688000 | L13: =E13*H13 -> 149688000 | M13: =L13-K13 -> 0 | N13: =IF(AND(B13>=설정!$B$6,B13<설정!$B$23),1,0) -> 0 | O13: =IF(AND(B13>=설정!$B$6,B13<설정!$B$24),1,0) -> 0 | P13: =IF(B13>=설정!$B$6,J13*(설정!$B$18-설정!$B$13),0) -> 0 | Q13: =L13-P13 -> 149688000 | R13: =IF(물량원가기준!D13="","",물량원가기준!D13*H13) -> 151200000 | S13: =E13*F13 -> 1229580000 | T13: =물량원가기준!I13+IF(B13>=설정!$B$6,I13*(설정!$B$18-설정!$B$13),0) -> 60000 | U13: =IF(OR(COUNT(물량원가기준!E13:J13)<>6,COUNTIFS(물량원가기준!$A$6:$A$100,A13)<>1),0,1) -> 1
A14: =물량원가기준!A14 -> 2027-02|A-d | B14: =물량원가기준!B14 -> 46419 | C14: =물량원가기준!C14 -> A-d | D14: =물량원가기준!E14 -> 4545 | E14: =물량원가기준!F14 -> 4545 | F14: =물량원가기준!G14 -> 210000 | G14: =SUM(물량원가기준!H14:J14) -> 185000 | H14: =F14-G14 -> 25000 | I14: =부품모델매핑!D9 -> 0 | J14: =IF(ISNUMBER(물량원가기준!F14),E14*I14,"미산출") -> 0 | K14: =D14*H14 -> 113625000 | L14: =E14*H14 -> 113625000 | M14: =L14-K14 -> 0 | N14: =IF(AND(B14>=설정!$B$6,B14<설정!$B$23),1,0) -> 0 | O14: =IF(AND(B14>=설정!$B$6,B14<설정!$B$24),1,0) -> 0 | P14: =IF(B14>=설정!$B$6,J14*(설정!$B$18-설정!$B$13),0) -> 0 | Q14: =L14-P14 -> 113625000 | R14: =IF(물량원가기준!D14="","",물량원가기준!D14*H14) -> 112500000 | S14: =E14*F14 -> 954450000 | T14: =물량원가기준!I14+IF(B14>=설정!$B$6,I14*(설정!$B$18-설정!$B$13),0) -> 65000 | U14: =IF(OR(COUNT(물량원가기준!E14:J14)<>6,COUNTIFS(물량원가기준!$A$6:$A$100,A14)<>1),0,1) -> 1
A15: =물량원가기준!A15 -> 2027-02|A-e | B15: =물량원가기준!B15 -> 46419 | C15: =물량원가기준!C15 -> A-e | D15: =물량원가기준!E15 -> 2673 | E15: =물량원가기준!F15 -> 2673 | F15: =물량원가기준!G15 -> 150000 | G15: =SUM(물량원가기준!H15:J15) -> 132000 | H15: =F15-G15 -> 18000 | I15: =부품모델매핑!D10 -> 0 | J15: =IF(ISNUMBER(물량원가기준!F15),E15*I15,"미산출") -> 0 | K15: =D15*H15 -> 48114000 | L15: =E15*H15 -> 48114000 | M15: =L15-K15 -> 0 | N15: =IF(AND(B15>=설정!$B$6,B15<설정!$B$23),1,0) -> 0 | O15: =IF(AND(B15>=설정!$B$6,B15<설정!$B$24),1,0) -> 0 | P15: =IF(B15>=설정!$B$6,J15*(설정!$B$18-설정!$B$13),0) -> 0 | Q15: =L15-P15 -> 48114000 | R15: =IF(물량원가기준!D15="","",물량원가기준!D15*H15) -> 48600000 | S15: =E15*F15 -> 400950000 | T15: =물량원가기준!I15+IF(B15>=설정!$B$6,I15*(설정!$B$18-설정!$B$13),0) -> 50000 | U15: =IF(OR(COUNT(물량원가기준!E15:J15)<>6,COUNTIFS(물량원가기준!$A$6:$A$100,A15)<>1),0,1) -> 1
A16: =물량원가기준!A16 -> 2027-03|A-a | B16: =물량원가기준!B16 -> 46447 | C16: =물량원가기준!C16 -> A-a | D16: =물량원가기준!E16 -> 4116 | E16: =물량원가기준!F16 -> 4116 | F16: =물량원가기준!G16 -> 300000 | G16: =SUM(물량원가기준!H16:J16) -> 270000 | H16: =F16-G16 -> 30000 | I16: =부품모델매핑!D6 -> 1 | J16: =IF(ISNUMBER(물량원가기준!F16),E16*I16,"미산출") -> 4116 | K16: =D16*H16 -> 123480000 | L16: =E16*H16 -> 123480000 | M16: =L16-K16 -> 0 | N16: =IF(AND(B16>=설정!$B$6,B16<설정!$B$23),1,0) -> 0 | O16: =IF(AND(B16>=설정!$B$6,B16<설정!$B$24),1,0) -> 0 | P16: =IF(B16>=설정!$B$6,J16*(설정!$B$18-설정!$B$13),0) -> 0 | Q16: =L16-P16 -> 123480000 | R16: =IF(물량원가기준!D16="","",물량원가기준!D16*H16) -> 126000000 | S16: =E16*F16 -> 1234800000 | T16: =물량원가기준!I16+IF(B16>=설정!$B$6,I16*(설정!$B$18-설정!$B$13),0) -> 75000 | U16: =IF(OR(COUNT(물량원가기준!E16:J16)<>6,COUNTIFS(물량원가기준!$A$6:$A$100,A16)<>1),0,1) -> 1
A17: =물량원가기준!A17 -> 2027-03|A-b | B17: =물량원가기준!B17 -> 46447 | C17: =물량원가기준!C17 -> A-b | D17: =물량원가기준!E17 -> 10290 | E17: =물량원가기준!F17 -> 10290 | F17: =물량원가기준!G17 -> 180000 | G17: =SUM(물량원가기준!H17:J17) -> 160000 | H17: =F17-G17 -> 20000 | I17: =부품모델매핑!D7 -> 1 | J17: =IF(ISNUMBER(물량원가기준!F17),E17*I17,"미산출") -> 10290 | K17: =D17*H17 -> 205800000 | L17: =E17*H17 -> 205800000 | M17: =L17-K17 -> 0 | N17: =IF(AND(B17>=설정!$B$6,B17<설정!$B$23),1,0) -> 0 | O17: =IF(AND(B17>=설정!$B$6,B17<설정!$B$24),1,0) -> 0 | P17: =IF(B17>=설정!$B$6,J17*(설정!$B$18-설정!$B$13),0) -> 0 | Q17: =L17-P17 -> 205800000 | R17: =IF(물량원가기준!D17="","",물량원가기준!D17*H17) -> 210000000 | S17: =E17*F17 -> 1852200000 | T17: =물량원가기준!I17+IF(B17>=설정!$B$6,I17*(설정!$B$18-설정!$B$13),0) -> 95000 | U17: =IF(OR(COUNT(물량원가기준!E17:J17)<>6,COUNTIFS(물량원가기준!$A$6:$A$100,A17)<>1),0,1) -> 1
A18: =물량원가기준!A18 -> 2027-03|A-c | B18: =물량원가기준!B18 -> 46447 | C18: =물량원가기준!C18 -> A-c | D18: =물량원가기준!E18 -> 6237 | E18: =물량원가기준!F18 -> 6237 | F18: =물량원가기준!G18 -> 230000 | G18: =SUM(물량원가기준!H18:J18) -> 202000 | H18: =F18-G18 -> 28000 | I18: =부품모델매핑!D8 -> 0 | J18: =IF(ISNUMBER(물량원가기준!F18),E18*I18,"미산출") -> 0 | K18: =D18*H18 -> 174636000 | L18: =E18*H18 -> 174636000 | M18: =L18-K18 -> 0 | N18: =IF(AND(B18>=설정!$B$6,B18<설정!$B$23),1,0) -> 0 | O18: =IF(AND(B18>=설정!$B$6,B18<설정!$B$24),1,0) -> 0 | P18: =IF(B18>=설정!$B$6,J18*(설정!$B$18-설정!$B$13),0) -> 0 | Q18: =L18-P18 -> 174636000 | R18: =IF(물량원가기준!D18="","",물량원가기준!D18*H18) -> 176400000 | S18: =E18*F18 -> 1434510000 | T18: =물량원가기준!I18+IF(B18>=설정!$B$6,I18*(설정!$B$18-설정!$B$13),0) -> 60000 | U18: =IF(OR(COUNT(물량원가기준!E18:J18)<>6,COUNTIFS(물량원가기준!$A$6:$A$100,A18)<>1),0,1) -> 1
A19: =물량원가기준!A19 -> 2027-03|A-d | B19: =물량원가기준!B19 -> 46447 | C19: =물량원가기준!C19 -> A-d | D19: =물량원가기준!E19 -> 5303 | E19: =물량원가기준!F19 -> 5303 | F19: =물량원가기준!G19 -> 210000 | G19: =SUM(물량원가기준!H19:J19) -> 185000 | H19: =F19-G19 -> 25000 | I19: =부품모델매핑!D9 -> 0 | J19: =IF(ISNUMBER(물량원가기준!F19),E19*I19,"미산출") -> 0 | K19: =D19*H19 -> 132575000 | L19: =E19*H19 -> 132575000 | M19: =L19-K19 -> 0 | N19: =IF(AND(B19>=설정!$B$6,B19<설정!$B$23),1,0) -> 0 | O19: =IF(AND(B19>=설정!$B$6,B19<설정!$B$24),1,0) -> 0 | P19: =IF(B19>=설정!$B$6,J19*(설정!$B$18-설정!$B$13),0) -> 0 | Q19: =L19-P19 -> 132575000 | R19: =IF(물량원가기준!D19="","",물량원가기준!D19*H19) -> 131250000 | S19: =E19*F19 -> 1113630000 | T19: =물량원가기준!I19+IF(B19>=설정!$B$6,I19*(설정!$B$18-설정!$B$13),0) -> 65000 | U19: =IF(OR(COUNT(물량원가기준!E19:J19)<>6,COUNTIFS(물량원가기준!$A$6:$A$100,A19)<>1),0,1) -> 1
A20: =물량원가기준!A20 -> 2027-03|A-e | B20: =물량원가기준!B20 -> 46447 | C20: =물량원가기준!C20 -> A-e | D20: =물량원가기준!E20 -> 3119 | E20: =물량원가기준!F20 -> 3119 | F20: =물량원가기준!G20 -> 150000 | G20: =SUM(물량원가기준!H20:J20) -> 132000 | H20: =F20-G20 -> 18000 | I20: =부품모델매핑!D10 -> 0 | J20: =IF(ISNUMBER(물량원가기준!F20),E20*I20,"미산출") -> 0 | K20: =D20*H20 -> 56142000 | L20: =E20*H20 -> 56142000 | M20: =L20-K20 -> 0 | N20: =IF(AND(B20>=설정!$B$6,B20<설정!$B$23),1,0) -> 0 | O20: =IF(AND(B20>=설정!$B$6,B20<설정!$B$24),1,0) -> 0 | P20: =IF(B20>=설정!$B$6,J20*(설정!$B$18-설정!$B$13),0) -> 0 | Q20: =L20-P20 -> 56142000 | R20: =IF(물량원가기준!D20="","",물량원가기준!D20*H20) -> 56700000 | S20: =E20*F20 -> 467850000 | T20: =물량원가기준!I20+IF(B20>=설정!$B$6,I20*(설정!$B$18-설정!$B$13),0) -> 50000 | U20: =IF(OR(COUNT(물량원가기준!E20:J20)<>6,COUNTIFS(물량원가기준!$A$6:$A$100,A20)<>1),0,1) -> 1
A21: =물량원가기준!A21 -> 2027-04|A-a | B21: =물량원가기준!B21 -> 46478 | C21: =물량원가기준!C21 -> A-a | D21: =물량원가기준!E21 -> 3880 | E21: =물량원가기준!F21 -> 3880 | F21: =물량원가기준!G21 -> 300000 | G21: =SUM(물량원가기준!H21:J21) -> 270000 | H21: =F21-G21 -> 30000 | I21: =부품모델매핑!D6 -> 1 | J21: =IF(ISNUMBER(물량원가기준!F21),E21*I21,"미산출") -> 3880 | K21: =D21*H21 -> 116400000 | L21: =E21*H21 -> 116400000 | M21: =L21-K21 -> 0 | N21: =IF(AND(B21>=설정!$B$6,B21<설정!$B$23),1,0) -> 0 | O21: =IF(AND(B21>=설정!$B$6,B21<설정!$B$24),1,0) -> 0 | P21: =IF(B21>=설정!$B$6,J21*(설정!$B$18-설정!$B$13),0) -> 0 | Q21: =L21-P21 -> 116400000 | R21: =IF(물량원가기준!D21="","",물량원가기준!D21*H21) -> 120000000 | S21: =E21*F21 -> 1164000000 | T21: =물량원가기준!I21+IF(B21>=설정!$B$6,I21*(설정!$B$18-설정!$B$13),0) -> 75000 | U21: =IF(OR(COUNT(물량원가기준!E21:J21)<>6,COUNTIFS(물량원가기준!$A$6:$A$100,A21)<>1),0,1) -> 1
A22: =물량원가기준!A22 -> 2027-04|A-b | B22: =물량원가기준!B22 -> 46478 | C22: =물량원가기준!C22 -> A-b | D22: =물량원가기준!E22 -> 9700 | E22: =물량원가기준!F22 -> 9700 | F22: =물량원가기준!G22 -> 180000 | G22: =SUM(물량원가기준!H22:J22) -> 160000 | H22: =F22-G22 -> 20000 | I22: =부품모델매핑!D7 -> 1 | J22: =IF(ISNUMBER(물량원가기준!F22),E22*I22,"미산출") -> 9700 | K22: =D22*H22 -> 194000000 | L22: =E22*H22 -> 194000000 | M22: =L22-K22 -> 0 | N22: =IF(AND(B22>=설정!$B$6,B22<설정!$B$23),1,0) -> 0 | O22: =IF(AND(B22>=설정!$B$6,B22<설정!$B$24),1,0) -> 0 | P22: =IF(B22>=설정!$B$6,J22*(설정!$B$18-설정!$B$13),0) -> 0 | Q22: =L22-P22 -> 194000000 | R22: =IF(물량원가기준!D22="","",물량원가기준!D22*H22) -> 200000000 | S22: =E22*F22 -> 1746000000 | T22: =물량원가기준!I22+IF(B22>=설정!$B$6,I22*(설정!$B$18-설정!$B$13),0) -> 95000 | U22: =IF(OR(COUNT(물량원가기준!E22:J22)<>6,COUNTIFS(물량원가기준!$A$6:$A$100,A22)<>1),0,1) -> 1
A23: =물량원가기준!A23 -> 2027-04|A-c | B23: =물량원가기준!B23 -> 46478 | C23: =물량원가기준!C23 -> A-c | D23: =물량원가기준!E23 -> 5940 | E23: =물량원가기준!F23 -> 5940 | F23: =물량원가기준!G23 -> 230000 | G23: =SUM(물량원가기준!H23:J23) -> 202000 | H23: =F23-G23 -> 28000 | I23: =부품모델매핑!D8 -> 0 | J23: =IF(ISNUMBER(물량원가기준!F23),E23*I23,"미산출") -> 0 | K23: =D23*H23 -> 166320000 | L23: =E23*H23 -> 166320000 | M23: =L23-K23 -> 0 | N23: =IF(AND(B23>=설정!$B$6,B23<설정!$B$23),1,0) -> 0 | O23: =IF(AND(B23>=설정!$B$6,B23<설정!$B$24),1,0) -> 0 | P23: =IF(B23>=설정!$B$6,J23*(설정!$B$18-설정!$B$13),0) -> 0 | Q23: =L23-P23 -> 166320000 | R23: =IF(물량원가기준!D23="","",물량원가기준!D23*H23) -> 168000000 | S23: =E23*F23 -> 1366200000 | T23: =물량원가기준!I23+IF(B23>=설정!$B$6,I23*(설정!$B$18-설정!$B$13),0) -> 60000 | U23: =IF(OR(COUNT(물량원가기준!E23:J23)<>6,COUNTIFS(물량원가기준!$A$6:$A$100,A23)<>1),0,1) -> 1
A24: =물량원가기준!A24 -> 2027-04|A-d | B24: =물량원가기준!B24 -> 46478 | C24: =물량원가기준!C24 -> A-d | D24: =물량원가기준!E24 -> 5050 | E24: =물량원가기준!F24 -> 5050 | F24: =물량원가기준!G24 -> 210000 | G24: =SUM(물량원가기준!H24:J24) -> 185000 | H24: =F24-G24 -> 25000 | I24: =부품모델매핑!D9 -> 0 | J24: =IF(ISNUMBER(물량원가기준!F24),E24*I24,"미산출") -> 0 | K24: =D24*H24 -> 126250000 | L24: =E24*H24 -> 126250000 | M24: =L24-K24 -> 0 | N24: =IF(AND(B24>=설정!$B$6,B24<설정!$B$23),1,0) -> 0 | O24: =IF(AND(B24>=설정!$B$6,B24<설정!$B$24),1,0) -> 0 | P24: =IF(B24>=설정!$B$6,J24*(설정!$B$18-설정!$B$13),0) -> 0 | Q24: =L24-P24 -> 126250000 | R24: =IF(물량원가기준!D24="","",물량원가기준!D24*H24) -> 125000000 | S24: =E24*F24 -> 1060500000 | T24: =물량원가기준!I24+IF(B24>=설정!$B$6,I24*(설정!$B$18-설정!$B$13),0) -> 65000 | U24: =IF(OR(COUNT(물량원가기준!E24:J24)<>6,COUNTIFS(물량원가기준!$A$6:$A$100,A24)<>1),0,1) -> 1
A25: =물량원가기준!A25 -> 2027-04|A-e | B25: =물량원가기준!B25 -> 46478 | C25: =물량원가기준!C25 -> A-e | D25: =물량원가기준!E25 -> 2970 | E25: =물량원가기준!F25 -> 2970 | F25: =물량원가기준!G25 -> 150000 | G25: =SUM(물량원가기준!H25:J25) -> 132000 | H25: =F25-G25 -> 18000 | I25: =부품모델매핑!D10 -> 0 | J25: =IF(ISNUMBER(물량원가기준!F25),E25*I25,"미산출") -> 0 | K25: =D25*H25 -> 53460000 | L25: =E25*H25 -> 53460000 | M25: =L25-K25 -> 0 | N25: =IF(AND(B25>=설정!$B$6,B25<설정!$B$23),1,0) -> 0 | O25: =IF(AND(B25>=설정!$B$6,B25<설정!$B$24),1,0) -> 0 | P25: =IF(B25>=설정!$B$6,J25*(설정!$B$18-설정!$B$13),0) -> 0 | Q25: =L25-P25 -> 53460000 | R25: =IF(물량원가기준!D25="","",물량원가기준!D25*H25) -> 54000000 | S25: =E25*F25 -> 445500000 | T25: =물량원가기준!I25+IF(B25>=설정!$B$6,I25*(설정!$B$18-설정!$B$13),0) -> 50000 | U25: =IF(OR(COUNT(물량원가기준!E25:J25)<>6,COUNTIFS(물량원가기준!$A$6:$A$100,A25)<>1),0,1) -> 1
A26: =물량원가기준!A26 -> 2027-05|A-a | B26: =물량원가기준!B26 -> 46508 | C26: =물량원가기준!C26 -> A-a | D26: =물량원가기준!E26 -> 3763 | E26: =물량원가기준!F26 -> 3763 | F26: =물량원가기준!G26 -> 300000 | G26: =SUM(물량원가기준!H26:J26) -> 270000 | H26: =F26-G26 -> 30000 | I26: =부품모델매핑!D6 -> 1 | J26: =IF(ISNUMBER(물량원가기준!F26),E26*I26,"미산출") -> 3763 | K26: =D26*H26 -> 112890000 | L26: =E26*H26 -> 112890000 | M26: =L26-K26 -> 0 | N26: =IF(AND(B26>=설정!$B$6,B26<설정!$B$23),1,0) -> 0 | O26: =IF(AND(B26>=설정!$B$6,B26<설정!$B$24),1,0) -> 0 | P26: =IF(B26>=설정!$B$6,J26*(설정!$B$18-설정!$B$13),0) -> 0 | Q26: =L26-P26 -> 112890000 | R26: =IF(물량원가기준!D26="","",물량원가기준!D26*H26) -> 117600000 | S26: =E26*F26 -> 1128900000 | T26: =물량원가기준!I26+IF(B26>=설정!$B$6,I26*(설정!$B$18-설정!$B$13),0) -> 75000 | U26: =IF(OR(COUNT(물량원가기준!E26:J26)<>6,COUNTIFS(물량원가기준!$A$6:$A$100,A26)<>1),0,1) -> 1
A27: =물량원가기준!A27 -> 2027-05|A-b | B27: =물량원가기준!B27 -> 46508 | C27: =물량원가기준!C27 -> A-b | D27: =물량원가기준!E27 -> 9408 | E27: =물량원가기준!F27 -> 9408 | F27: =물량원가기준!G27 -> 180000 | G27: =SUM(물량원가기준!H27:J27) -> 160000 | H27: =F27-G27 -> 20000 | I27: =부품모델매핑!D7 -> 1 | J27: =IF(ISNUMBER(물량원가기준!F27),E27*I27,"미산출") -> 9408 | K27: =D27*H27 -> 188160000 | L27: =E27*H27 -> 188160000 | M27: =L27-K27 -> 0 | N27: =IF(AND(B27>=설정!$B$6,B27<설정!$B$23),1,0) -> 0 | O27: =IF(AND(B27>=설정!$B$6,B27<설정!$B$24),1,0) -> 0 | P27: =IF(B27>=설정!$B$6,J27*(설정!$B$18-설정!$B$13),0) -> 0 | Q27: =L27-P27 -> 188160000 | R27: =IF(물량원가기준!D27="","",물량원가기준!D27*H27) -> 196000000 | S27: =E27*F27 -> 1693440000 | T27: =물량원가기준!I27+IF(B27>=설정!$B$6,I27*(설정!$B$18-설정!$B$13),0) -> 95000 | U27: =IF(OR(COUNT(물량원가기준!E27:J27)<>6,COUNTIFS(물량원가기준!$A$6:$A$100,A27)<>1),0,1) -> 1
A28: =물량원가기준!A28 -> 2027-05|A-c | B28: =물량원가기준!B28 -> 46508 | C28: =물량원가기준!C28 -> A-c | D28: =물량원가기준!E28 -> 5821 | E28: =물량원가기준!F28 -> 5821 | F28: =물량원가기준!G28 -> 230000 | G28: =SUM(물량원가기준!H28:J28) -> 202000 | H28: =F28-G28 -> 28000 | I28: =부품모델매핑!D8 -> 0 | J28: =IF(ISNUMBER(물량원가기준!F28),E28*I28,"미산출") -> 0 | K28: =D28*H28 -> 162988000 | L28: =E28*H28 -> 162988000 | M28: =L28-K28 -> 0 | N28: =IF(AND(B28>=설정!$B$6,B28<설정!$B$23),1,0) -> 0 | O28: =IF(AND(B28>=설정!$B$6,B28<설정!$B$24),1,0) -> 0 | P28: =IF(B28>=설정!$B$6,J28*(설정!$B$18-설정!$B$13),0) -> 0 | Q28: =L28-P28 -> 162988000 | R28: =IF(물량원가기준!D28="","",물량원가기준!D28*H28) -> 164640000 | S28: =E28*F28 -> 1338830000 | T28: =물량원가기준!I28+IF(B28>=설정!$B$6,I28*(설정!$B$18-설정!$B$13),0) -> 60000 | U28: =IF(OR(COUNT(물량원가기준!E28:J28)<>6,COUNTIFS(물량원가기준!$A$6:$A$100,A28)<>1),0,1) -> 1
A29: =물량원가기준!A29 -> 2027-05|A-d | B29: =물량원가기준!B29 -> 46508 | C29: =물량원가기준!C29 -> A-d | D29: =물량원가기준!E29 -> 4949 | E29: =물량원가기준!F29 -> 4949 | F29: =물량원가기준!G29 -> 210000 | G29: =SUM(물량원가기준!H29:J29) -> 185000 | H29: =F29-G29 -> 25000 | I29: =부품모델매핑!D9 -> 0 | J29: =IF(ISNUMBER(물량원가기준!F29),E29*I29,"미산출") -> 0 | K29: =D29*H29 -> 123725000 | L29: =E29*H29 -> 123725000 | M29: =L29-K29 -> 0 | N29: =IF(AND(B29>=설정!$B$6,B29<설정!$B$23),1,0) -> 0 | O29: =IF(AND(B29>=설정!$B$6,B29<설정!$B$24),1,0) -> 0 | P29: =IF(B29>=설정!$B$6,J29*(설정!$B$18-설정!$B$13),0) -> 0 | Q29: =L29-P29 -> 123725000 | R29: =IF(물량원가기준!D29="","",물량원가기준!D29*H29) -> 122500000 | S29: =E29*F29 -> 1039290000 | T29: =물량원가기준!I29+IF(B29>=설정!$B$6,I29*(설정!$B$18-설정!$B$13),0) -> 65000 | U29: =IF(OR(COUNT(물량원가기준!E29:J29)<>6,COUNTIFS(물량원가기준!$A$6:$A$100,A29)<>1),0,1) -> 1
A30: =물량원가기준!A30 -> 2027-05|A-e | B30: =물량원가기준!B30 -> 46508 | C30: =물량원가기준!C30 -> A-e | D30: =물량원가기준!E30 -> 2911 | E30: =물량원가기준!F30 -> 2911 | F30: =물량원가기준!G30 -> 150000 | G30: =SUM(물량원가기준!H30:J30) -> 132000 | H30: =F30-G30 -> 18000 | I30: =부품모델매핑!D10 -> 0 | J30: =IF(ISNUMBER(물량원가기준!F30),E30*I30,"미산출") -> 0 | K30: =D30*H30 -> 52398000 | L30: =E30*H30 -> 52398000 | M30: =L30-K30 -> 0 | N30: =IF(AND(B30>=설정!$B$6,B30<설정!$B$23),1,0) -> 0 | O30: =IF(AND(B30>=설정!$B$6,B30<설정!$B$24),1,0) -> 0 | P30: =IF(B30>=설정!$B$6,J30*(설정!$B$18-설정!$B$13),0) -> 0 | Q30: =L30-P30 -> 52398000 | R30: =IF(물량원가기준!D30="","",물량원가기준!D30*H30) -> 52920000 | S30: =E30*F30 -> 436650000 | T30: =물량원가기준!I30+IF(B30>=설정!$B$6,I30*(설정!$B$18-설정!$B$13),0) -> 50000 | U30: =IF(OR(COUNT(물량원가기준!E30:J30)<>6,COUNTIFS(물량원가기준!$A$6:$A$100,A30)<>1),0,1) -> 1
A31: =물량원가기준!A31 -> 2027-06|A-a | B31: =물량원가기준!B31 -> 46539 | C31: =물량원가기준!C31 -> A-a | D31: =물량원가기준!E31 -> 3800 | E31: =물량원가기준!F31 -> 3800 | F31: =물량원가기준!G31 -> 300000 | G31: =SUM(물량원가기준!H31:J31) -> 270000 | H31: =F31-G31 -> 30000 | I31: =부품모델매핑!D6 -> 1 | J31: =IF(ISNUMBER(물량원가기준!F31),E31*I31,"미산출") -> 3800 | K31: =D31*H31 -> 114000000 | L31: =E31*H31 -> 114000000 | M31: =L31-K31 -> 0 | N31: =IF(AND(B31>=설정!$B$6,B31<설정!$B$23),1,0) -> 0 | O31: =IF(AND(B31>=설정!$B$6,B31<설정!$B$24),1,0) -> 0 | P31: =IF(B31>=설정!$B$6,J31*(설정!$B$18-설정!$B$13),0) -> 0 | Q31: =L31-P31 -> 114000000 | R31: =IF(물량원가기준!D31="","",물량원가기준!D31*H31) -> 120000000 | S31: =E31*F31 -> 1140000000 | T31: =물량원가기준!I31+IF(B31>=설정!$B$6,I31*(설정!$B$18-설정!$B$13),0) -> 75000 | U31: =IF(OR(COUNT(물량원가기준!E31:J31)<>6,COUNTIFS(물량원가기준!$A$6:$A$100,A31)<>1),0,1) -> 1
A32: =물량원가기준!A32 -> 2027-06|A-b | B32: =물량원가기준!B32 -> 46539 | C32: =물량원가기준!C32 -> A-b | D32: =물량원가기준!E32 -> 9500 | E32: =물량원가기준!F32 -> 9500 | F32: =물량원가기준!G32 -> 180000 | G32: =SUM(물량원가기준!H32:J32) -> 160000 | H32: =F32-G32 -> 20000 | I32: =부품모델매핑!D7 -> 1 | J32: =IF(ISNUMBER(물량원가기준!F32),E32*I32,"미산출") -> 9500 | K32: =D32*H32 -> 190000000 | L32: =E32*H32 -> 190000000 | M32: =L32-K32 -> 0 | N32: =IF(AND(B32>=설정!$B$6,B32<설정!$B$23),1,0) -> 0 | O32: =IF(AND(B32>=설정!$B$6,B32<설정!$B$24),1,0) -> 0 | P32: =IF(B32>=설정!$B$6,J32*(설정!$B$18-설정!$B$13),0) -> 0 | Q32: =L32-P32 -> 190000000 | R32: =IF(물량원가기준!D32="","",물량원가기준!D32*H32) -> 200000000 | S32: =E32*F32 -> 1710000000 | T32: =물량원가기준!I32+IF(B32>=설정!$B$6,I32*(설정!$B$18-설정!$B$13),0) -> 95000 | U32: =IF(OR(COUNT(물량원가기준!E32:J32)<>6,COUNTIFS(물량원가기준!$A$6:$A$100,A32)<>1),0,1) -> 1
A33: =물량원가기준!A33 -> 2027-06|A-c | B33: =물량원가기준!B33 -> 46539 | C33: =물량원가기준!C33 -> A-c | D33: =물량원가기준!E33 -> 5940 | E33: =물량원가기준!F33 -> 5940 | F33: =물량원가기준!G33 -> 230000 | G33: =SUM(물량원가기준!H33:J33) -> 202000 | H33: =F33-G33 -> 28000 | I33: =부품모델매핑!D8 -> 0 | J33: =IF(ISNUMBER(물량원가기준!F33),E33*I33,"미산출") -> 0 | K33: =D33*H33 -> 166320000 | L33: =E33*H33 -> 166320000 | M33: =L33-K33 -> 0 | N33: =IF(AND(B33>=설정!$B$6,B33<설정!$B$23),1,0) -> 0 | O33: =IF(AND(B33>=설정!$B$6,B33<설정!$B$24),1,0) -> 0 | P33: =IF(B33>=설정!$B$6,J33*(설정!$B$18-설정!$B$13),0) -> 0 | Q33: =L33-P33 -> 166320000 | R33: =IF(물량원가기준!D33="","",물량원가기준!D33*H33) -> 168000000 | S33: =E33*F33 -> 1366200000 | T33: =물량원가기준!I33+IF(B33>=설정!$B$6,I33*(설정!$B$18-설정!$B$13),0) -> 60000 | U33: =IF(OR(COUNT(물량원가기준!E33:J33)<>6,COUNTIFS(물량원가기준!$A$6:$A$100,A33)<>1),0,1) -> 1
A34: =물량원가기준!A34 -> 2027-06|A-d | B34: =물량원가기준!B34 -> 46539 | C34: =물량원가기준!C34 -> A-d | D34: =물량원가기준!E34 -> 5050 | E34: =물량원가기준!F34 -> 5050 | F34: =물량원가기준!G34 -> 210000 | G34: =SUM(물량원가기준!H34:J34) -> 185000 | H34: =F34-G34 -> 25000 | I34: =부품모델매핑!D9 -> 0 | J34: =IF(ISNUMBER(물량원가기준!F34),E34*I34,"미산출") -> 0 | K34: =D34*H34 -> 126250000 | L34: =E34*H34 -> 126250000 | M34: =L34-K34 -> 0 | N34: =IF(AND(B34>=설정!$B$6,B34<설정!$B$23),1,0) -> 0 | O34: =IF(AND(B34>=설정!$B$6,B34<설정!$B$24),1,0) -> 0 | P34: =IF(B34>=설정!$B$6,J34*(설정!$B$18-설정!$B$13),0) -> 0 | Q34: =L34-P34 -> 126250000 | R34: =IF(물량원가기준!D34="","",물량원가기준!D34*H34) -> 125000000 | S34: =E34*F34 -> 1060500000 | T34: =물량원가기준!I34+IF(B34>=설정!$B$6,I34*(설정!$B$18-설정!$B$13),0) -> 65000 | U34: =IF(OR(COUNT(물량원가기준!E34:J34)<>6,COUNTIFS(물량원가기준!$A$6:$A$100,A34)<>1),0,1) -> 1
A35: =물량원가기준!A35 -> 2027-06|A-e | B35: =물량원가기준!B35 -> 46539 | C35: =물량원가기준!C35 -> A-e | D35: =물량원가기준!E35 -> 2970 | E35: =물량원가기준!F35 -> 2970 | F35: =물량원가기준!G35 -> 150000 | G35: =SUM(물량원가기준!H35:J35) -> 132000 | H35: =F35-G35 -> 18000 | I35: =부품모델매핑!D10 -> 0 | J35: =IF(ISNUMBER(물량원가기준!F35),E35*I35,"미산출") -> 0 | K35: =D35*H35 -> 53460000 | L35: =E35*H35 -> 53460000 | M35: =L35-K35 -> 0 | N35: =IF(AND(B35>=설정!$B$6,B35<설정!$B$23),1,0) -> 0 | O35: =IF(AND(B35>=설정!$B$6,B35<설정!$B$24),1,0) -> 0 | P35: =IF(B35>=설정!$B$6,J35*(설정!$B$18-설정!$B$13),0) -> 0 | Q35: =L35-P35 -> 53460000 | R35: =IF(물량원가기준!D35="","",물량원가기준!D35*H35) -> 54000000 | S35: =E35*F35 -> 445500000 | T35: =물량원가기준!I35+IF(B35>=설정!$B$6,I35*(설정!$B$18-설정!$B$13),0) -> 50000 | U35: =IF(OR(COUNT(물량원가기준!E35:J35)<>6,COUNTIFS(물량원가기준!$A$6:$A$100,A35)<>1),0,1) -> 1
A36: =물량원가기준!A36 -> 2027-07|A-a | B36: =물량원가기준!B36 -> 46569 | C36: =물량원가기준!C36 -> A-a | D36: =물량원가기준!E36 -> 3800 | E36: =물량원가기준!F36 -> 3800 | F36: =물량원가기준!G36 -> 300000 | G36: =SUM(물량원가기준!H36:J36) -> 270000 | H36: =F36-G36 -> 30000 | I36: =부품모델매핑!D6 -> 1 | J36: =IF(ISNUMBER(물량원가기준!F36),E36*I36,"미산출") -> 3800 | K36: =D36*H36 -> 114000000 | L36: =E36*H36 -> 114000000 | M36: =L36-K36 -> 0 | N36: =IF(AND(B36>=설정!$B$6,B36<설정!$B$23),1,0) -> 1 | O36: =IF(AND(B36>=설정!$B$6,B36<설정!$B$24),1,0) -> 1 | P36: =IF(B36>=설정!$B$6,J36*(설정!$B$18-설정!$B$13),0) -> 456000 | Q36: =L36-P36 -> 113544000 | R36: =IF(물량원가기준!D36="","",물량원가기준!D36*H36) -> 120000000 | S36: =E36*F36 -> 1140000000 | T36: =물량원가기준!I36+IF(B36>=설정!$B$6,I36*(설정!$B$18-설정!$B$13),0) -> 75120 | U36: =IF(OR(COUNT(물량원가기준!E36:J36)<>6,COUNTIFS(물량원가기준!$A$6:$A$100,A36)<>1),0,1) -> 1
A37: =물량원가기준!A37 -> 2027-07|A-b | B37: =물량원가기준!B37 -> 46569 | C37: =물량원가기준!C37 -> A-b | D37: =물량원가기준!E37 -> 9500 | E37: =물량원가기준!F37 -> 8800 | F37: =물량원가기준!G37 -> 180000 | G37: =SUM(물량원가기준!H37:J37) -> 160000 | H37: =F37-G37 -> 20000 | I37: =부품모델매핑!D7 -> 1 | J37: =IF(ISNUMBER(물량원가기준!F37),E37*I37,"미산출") -> 8800 | K37: =D37*H37 -> 190000000 | L37: =E37*H37 -> 176000000 | M37: =L37-K37 -> -14000000 | N37: =IF(AND(B37>=설정!$B$6,B37<설정!$B$23),1,0) -> 1 | O37: =IF(AND(B37>=설정!$B$6,B37<설정!$B$24),1,0) -> 1 | P37: =IF(B37>=설정!$B$6,J37*(설정!$B$18-설정!$B$13),0) -> 1056000 | Q37: =L37-P37 -> 174944000 | R37: =IF(물량원가기준!D37="","",물량원가기준!D37*H37) -> 200000000 | S37: =E37*F37 -> 1584000000 | T37: =물량원가기준!I37+IF(B37>=설정!$B$6,I37*(설정!$B$18-설정!$B$13),0) -> 95120 | U37: =IF(OR(COUNT(물량원가기준!E37:J37)<>6,COUNTIFS(물량원가기준!$A$6:$A$100,A37)<>1),0,1) -> 1
A38: =물량원가기준!A38 -> 2027-07|A-c | B38: =물량원가기준!B38 -> 46569 | C38: =물량원가기준!C38 -> A-c | D38: =물량원가기준!E38 -> 5940 | E38: =물량원가기준!F38 -> 5940 | F38: =물량원가기준!G38 -> 230000 | G38: =SUM(물량원가기준!H38:J38) -> 202000 | H38: =F38-G38 -> 28000 | I38: =부품모델매핑!D8 -> 0 | J38: =IF(ISNUMBER(물량원가기준!F38),E38*I38,"미산출") -> 0 | K38: =D38*H38 -> 166320000 | L38: =E38*H38 -> 166320000 | M38: =L38-K38 -> 0 | N38: =IF(AND(B38>=설정!$B$6,B38<설정!$B$23),1,0) -> 1 | O38: =IF(AND(B38>=설정!$B$6,B38<설정!$B$24),1,0) -> 1 | P38: =IF(B38>=설정!$B$6,J38*(설정!$B$18-설정!$B$13),0) -> 0 | Q38: =L38-P38 -> 166320000 | R38: =IF(물량원가기준!D38="","",물량원가기준!D38*H38) -> 168000000 | S38: =E38*F38 -> 1366200000 | T38: =물량원가기준!I38+IF(B38>=설정!$B$6,I38*(설정!$B$18-설정!$B$13),0) -> 60000 | U38: =IF(OR(COUNT(물량원가기준!E38:J38)<>6,COUNTIFS(물량원가기준!$A$6:$A$100,A38)<>1),0,1) -> 1
A39: =물량원가기준!A39 -> 2027-07|A-d | B39: =물량원가기준!B39 -> 46569 | C39: =물량원가기준!C39 -> A-d | D39: =물량원가기준!E39 -> 5050 | E39: =물량원가기준!F39 -> 5050 | F39: =물량원가기준!G39 -> 210000 | G39: =SUM(물량원가기준!H39:J39) -> 185000 | H39: =F39-G39 -> 25000 | I39: =부품모델매핑!D9 -> 0 | J39: =IF(ISNUMBER(물량원가기준!F39),E39*I39,"미산출") -> 0 | K39: =D39*H39 -> 126250000 | L39: =E39*H39 -> 126250000 | M39: =L39-K39 -> 0 | N39: =IF(AND(B39>=설정!$B$6,B39<설정!$B$23),1,0) -> 1 | O39: =IF(AND(B39>=설정!$B$6,B39<설정!$B$24),1,0) -> 1 | P39: =IF(B39>=설정!$B$6,J39*(설정!$B$18-설정!$B$13),0) -> 0 | Q39: =L39-P39 -> 126250000 | R39: =IF(물량원가기준!D39="","",물량원가기준!D39*H39) -> 125000000 | S39: =E39*F39 -> 1060500000 | T39: =물량원가기준!I39+IF(B39>=설정!$B$6,I39*(설정!$B$18-설정!$B$13),0) -> 65000 | U39: =IF(OR(COUNT(물량원가기준!E39:J39)<>6,COUNTIFS(물량원가기준!$A$6:$A$100,A39)<>1),0,1) -> 1
A40: =물량원가기준!A40 -> 2027-07|A-e | B40: =물량원가기준!B40 -> 46569 | C40: =물량원가기준!C40 -> A-e | D40: =물량원가기준!E40 -> 2970 | E40: =물량원가기준!F40 -> 2970 | F40: =물량원가기준!G40 -> 150000 | G40: =SUM(물량원가기준!H40:J40) -> 132000 | H40: =F40-G40 -> 18000 | I40: =부품모델매핑!D10 -> 0 | J40: =IF(ISNUMBER(물량원가기준!F40),E40*I40,"미산출") -> 0 | K40: =D40*H40 -> 53460000 | L40: =E40*H40 -> 53460000 | M40: =L40-K40 -> 0 | N40: =IF(AND(B40>=설정!$B$6,B40<설정!$B$23),1,0) -> 1 | O40: =IF(AND(B40>=설정!$B$6,B40<설정!$B$24),1,0) -> 1 | P40: =IF(B40>=설정!$B$6,J40*(설정!$B$18-설정!$B$13),0) -> 0 | Q40: =L40-P40 -> 53460000 | R40: =IF(물량원가기준!D40="","",물량원가기준!D40*H40) -> 54000000 | S40: =E40*F40 -> 445500000 | T40: =물량원가기준!I40+IF(B40>=설정!$B$6,I40*(설정!$B$18-설정!$B$13),0) -> 50000 | U40: =IF(OR(COUNT(물량원가기준!E40:J40)<>6,COUNTIFS(물량원가기준!$A$6:$A$100,A40)<>1),0,1) -> 1
A41: =물량원가기준!A41 -> 2027-08|A-a | B41: =물량원가기준!B41 -> 46600 | C41: =물량원가기준!C41 -> A-a | D41: =물량원가기준!E41 -> 3496 | E41: =물량원가기준!F41 -> 3496 | F41: =물량원가기준!G41 -> 300000 | G41: =SUM(물량원가기준!H41:J41) -> 270000 | H41: =F41-G41 -> 30000 | I41: =부품모델매핑!D6 -> 1 | J41: =IF(ISNUMBER(물량원가기준!F41),E41*I41,"미산출") -> 3496 | K41: =D41*H41 -> 104880000 | L41: =E41*H41 -> 104880000 | M41: =L41-K41 -> 0 | N41: =IF(AND(B41>=설정!$B$6,B41<설정!$B$23),1,0) -> 1 | O41: =IF(AND(B41>=설정!$B$6,B41<설정!$B$24),1,0) -> 1 | P41: =IF(B41>=설정!$B$6,J41*(설정!$B$18-설정!$B$13),0) -> 419520 | Q41: =L41-P41 -> 104460480 | R41: =IF(물량원가기준!D41="","",물량원가기준!D41*H41) -> 110400000 | S41: =E41*F41 -> 1048800000 | T41: =물량원가기준!I41+IF(B41>=설정!$B$6,I41*(설정!$B$18-설정!$B$13),0) -> 75120 | U41: =IF(OR(COUNT(물량원가기준!E41:J41)<>6,COUNTIFS(물량원가기준!$A$6:$A$100,A41)<>1),0,1) -> 1
A42: =물량원가기준!A42 -> 2027-08|A-b | B42: =물량원가기준!B42 -> 46600 | C42: =물량원가기준!C42 -> A-b | D42: =물량원가기준!E42 -> 8740 | E42: =물량원가기준!F42 -> 8740 | F42: =물량원가기준!G42 -> 180000 | G42: =SUM(물량원가기준!H42:J42) -> 160000 | H42: =F42-G42 -> 20000 | I42: =부품모델매핑!D7 -> 1 | J42: =IF(ISNUMBER(물량원가기준!F42),E42*I42,"미산출") -> 8740 | K42: =D42*H42 -> 174800000 | L42: =E42*H42 -> 174800000 | M42: =L42-K42 -> 0 | N42: =IF(AND(B42>=설정!$B$6,B42<설정!$B$23),1,0) -> 1 | O42: =IF(AND(B42>=설정!$B$6,B42<설정!$B$24),1,0) -> 1 | P42: =IF(B42>=설정!$B$6,J42*(설정!$B$18-설정!$B$13),0) -> 1048800 | Q42: =L42-P42 -> 173751200 | R42: =IF(물량원가기준!D42="","",물량원가기준!D42*H42) -> 184000000 | S42: =E42*F42 -> 1573200000 | T42: =물량원가기준!I42+IF(B42>=설정!$B$6,I42*(설정!$B$18-설정!$B$13),0) -> 95120 | U42: =IF(OR(COUNT(물량원가기준!E42:J42)<>6,COUNTIFS(물량원가기준!$A$6:$A$100,A42)<>1),0,1) -> 1
A43: =물량원가기준!A43 -> 2027-08|A-c | B43: =물량원가기준!B43 -> 46600 | C43: =물량원가기준!C43 -> A-c | D43: =물량원가기준!E43 -> 5465 | E43: =물량원가기준!F43 -> 5465 | F43: =물량원가기준!G43 -> 230000 | G43: =SUM(물량원가기준!H43:J43) -> 202000 | H43: =F43-G43 -> 28000 | I43: =부품모델매핑!D8 -> 0 | J43: =IF(ISNUMBER(물량원가기준!F43),E43*I43,"미산출") -> 0 | K43: =D43*H43 -> 153020000 | L43: =E43*H43 -> 153020000 | M43: =L43-K43 -> 0 | N43: =IF(AND(B43>=설정!$B$6,B43<설정!$B$23),1,0) -> 1 | O43: =IF(AND(B43>=설정!$B$6,B43<설정!$B$24),1,0) -> 1 | P43: =IF(B43>=설정!$B$6,J43*(설정!$B$18-설정!$B$13),0) -> 0 | Q43: =L43-P43 -> 153020000 | R43: =IF(물량원가기준!D43="","",물량원가기준!D43*H43) -> 154560000 | S43: =E43*F43 -> 1256950000 | T43: =물량원가기준!I43+IF(B43>=설정!$B$6,I43*(설정!$B$18-설정!$B$13),0) -> 60000 | U43: =IF(OR(COUNT(물량원가기준!E43:J43)<>6,COUNTIFS(물량원가기준!$A$6:$A$100,A43)<>1),0,1) -> 1
A44: =물량원가기준!A44 -> 2027-08|A-d | B44: =물량원가기준!B44 -> 46600 | C44: =물량원가기준!C44 -> A-d | D44: =물량원가기준!E44 -> 4646 | E44: =물량원가기준!F44 -> 4646 | F44: =물량원가기준!G44 -> 210000 | G44: =SUM(물량원가기준!H44:J44) -> 185000 | H44: =F44-G44 -> 25000 | I44: =부품모델매핑!D9 -> 0 | J44: =IF(ISNUMBER(물량원가기준!F44),E44*I44,"미산출") -> 0 | K44: =D44*H44 -> 116150000 | L44: =E44*H44 -> 116150000 | M44: =L44-K44 -> 0 | N44: =IF(AND(B44>=설정!$B$6,B44<설정!$B$23),1,0) -> 1 | O44: =IF(AND(B44>=설정!$B$6,B44<설정!$B$24),1,0) -> 1 | P44: =IF(B44>=설정!$B$6,J44*(설정!$B$18-설정!$B$13),0) -> 0 | Q44: =L44-P44 -> 116150000 | R44: =IF(물량원가기준!D44="","",물량원가기준!D44*H44) -> 115000000 | S44: =E44*F44 -> 975660000 | T44: =물량원가기준!I44+IF(B44>=설정!$B$6,I44*(설정!$B$18-설정!$B$13),0) -> 65000 | U44: =IF(OR(COUNT(물량원가기준!E44:J44)<>6,COUNTIFS(물량원가기준!$A$6:$A$100,A44)<>1),0,1) -> 1
A45: =물량원가기준!A45 -> 2027-08|A-e | B45: =물량원가기준!B45 -> 46600 | C45: =물량원가기준!C45 -> A-e | D45: =물량원가기준!E45 -> 2732 | E45: =물량원가기준!F45 -> 2732 | F45: =물량원가기준!G45 -> 150000 | G45: =SUM(물량원가기준!H45:J45) -> 132000 | H45: =F45-G45 -> 18000 | I45: =부품모델매핑!D10 -> 0 | J45: =IF(ISNUMBER(물량원가기준!F45),E45*I45,"미산출") -> 0 | K45: =D45*H45 -> 49176000 | L45: =E45*H45 -> 49176000 | M45: =L45-K45 -> 0 | N45: =IF(AND(B45>=설정!$B$6,B45<설정!$B$23),1,0) -> 1 | O45: =IF(AND(B45>=설정!$B$6,B45<설정!$B$24),1,0) -> 1 | P45: =IF(B45>=설정!$B$6,J45*(설정!$B$18-설정!$B$13),0) -> 0 | Q45: =L45-P45 -> 49176000 | R45: =IF(물량원가기준!D45="","",물량원가기준!D45*H45) -> 49680000 | S45: =E45*F45 -> 409800000 | T45: =물량원가기준!I45+IF(B45>=설정!$B$6,I45*(설정!$B$18-설정!$B$13),0) -> 50000 | U45: =IF(OR(COUNT(물량원가기준!E45:J45)<>6,COUNTIFS(물량원가기준!$A$6:$A$100,A45)<>1),0,1) -> 1
A46: =물량원가기준!A46 -> 2027-09|A-a | B46: =물량원가기준!B46 -> 46631 | C46: =물량원가기준!C46 -> A-a | D46: =물량원가기준!E46 -> 3914 | E46: =물량원가기준!F46 -> 3914 | F46: =물량원가기준!G46 -> 300000 | G46: =SUM(물량원가기준!H46:J46) -> 270000 | H46: =F46-G46 -> 30000 | I46: =부품모델매핑!D6 -> 1 | J46: =IF(ISNUMBER(물량원가기준!F46),E46*I46,"미산출") -> 3914 | K46: =D46*H46 -> 117420000 | L46: =E46*H46 -> 117420000 | M46: =L46-K46 -> 0 | N46: =IF(AND(B46>=설정!$B$6,B46<설정!$B$23),1,0) -> 1 | O46: =IF(AND(B46>=설정!$B$6,B46<설정!$B$24),1,0) -> 1 | P46: =IF(B46>=설정!$B$6,J46*(설정!$B$18-설정!$B$13),0) -> 469680 | Q46: =L46-P46 -> 116950320 | R46: =IF(물량원가기준!D46="","",물량원가기준!D46*H46) -> 123600000 | S46: =E46*F46 -> 1174200000 | T46: =물량원가기준!I46+IF(B46>=설정!$B$6,I46*(설정!$B$18-설정!$B$13),0) -> 75120 | U46: =IF(OR(COUNT(물량원가기준!E46:J46)<>6,COUNTIFS(물량원가기준!$A$6:$A$100,A46)<>1),0,1) -> 1
A47: =물량원가기준!A47 -> 2027-09|A-b | B47: =물량원가기준!B47 -> 46631 | C47: =물량원가기준!C47 -> A-b | D47: =물량원가기준!E47 -> 9785 | E47: =물량원가기준!F47 -> 9785 | F47: =물량원가기준!G47 -> 180000 | G47: =SUM(물량원가기준!H47:J47) -> 160000 | H47: =F47-G47 -> 20000 | I47: =부품모델매핑!D7 -> 1 | J47: =IF(ISNUMBER(물량원가기준!F47),E47*I47,"미산출") -> 9785 | K47: =D47*H47 -> 195700000 | L47: =E47*H47 -> 195700000 | M47: =L47-K47 -> 0 | N47: =IF(AND(B47>=설정!$B$6,B47<설정!$B$23),1,0) -> 1 | O47: =IF(AND(B47>=설정!$B$6,B47<설정!$B$24),1,0) -> 1 | P47: =IF(B47>=설정!$B$6,J47*(설정!$B$18-설정!$B$13),0) -> 1174200 | Q47: =L47-P47 -> 194525800 | R47: =IF(물량원가기준!D47="","",물량원가기준!D47*H47) -> 206000000 | S47: =E47*F47 -> 1761300000 | T47: =물량원가기준!I47+IF(B47>=설정!$B$6,I47*(설정!$B$18-설정!$B$13),0) -> 95120 | U47: =IF(OR(COUNT(물량원가기준!E47:J47)<>6,COUNTIFS(물량원가기준!$A$6:$A$100,A47)<>1),0,1) -> 1
A48: =물량원가기준!A48 -> 2027-09|A-c | B48: =물량원가기준!B48 -> 46631 | C48: =물량원가기준!C48 -> A-c | D48: =물량원가기준!E48 -> 6118 | E48: =물량원가기준!F48 -> 6118 | F48: =물량원가기준!G48 -> 230000 | G48: =SUM(물량원가기준!H48:J48) -> 202000 | H48: =F48-G48 -> 28000 | I48: =부품모델매핑!D8 -> 0 | J48: =IF(ISNUMBER(물량원가기준!F48),E48*I48,"미산출") -> 0 | K48: =D48*H48 -> 171304000 | L48: =E48*H48 -> 171304000 | M48: =L48-K48 -> 0 | N48: =IF(AND(B48>=설정!$B$6,B48<설정!$B$23),1,0) -> 1 | O48: =IF(AND(B48>=설정!$B$6,B48<설정!$B$24),1,0) -> 1 | P48: =IF(B48>=설정!$B$6,J48*(설정!$B$18-설정!$B$13),0) -> 0 | Q48: =L48-P48 -> 171304000 | R48: =IF(물량원가기준!D48="","",물량원가기준!D48*H48) -> 173040000 | S48: =E48*F48 -> 1407140000 | T48: =물량원가기준!I48+IF(B48>=설정!$B$6,I48*(설정!$B$18-설정!$B$13),0) -> 60000 | U48: =IF(OR(COUNT(물량원가기준!E48:J48)<>6,COUNTIFS(물량원가기준!$A$6:$A$100,A48)<>1),0,1) -> 1
A49: =물량원가기준!A49 -> 2027-09|A-d | B49: =물량원가기준!B49 -> 46631 | C49: =물량원가기준!C49 -> A-d | D49: =물량원가기준!E49 -> 5202 | E49: =물량원가기준!F49 -> 5202 | F49: =물량원가기준!G49 -> 210000 | G49: =SUM(물량원가기준!H49:J49) -> 185000 | H49: =F49-G49 -> 25000 | I49: =부품모델매핑!D9 -> 0 | J49: =IF(ISNUMBER(물량원가기준!F49),E49*I49,"미산출") -> 0 | K49: =D49*H49 -> 130050000 | L49: =E49*H49 -> 130050000 | M49: =L49-K49 -> 0 | N49: =IF(AND(B49>=설정!$B$6,B49<설정!$B$23),1,0) -> 1 | O49: =IF(AND(B49>=설정!$B$6,B49<설정!$B$24),1,0) -> 1 | P49: =IF(B49>=설정!$B$6,J49*(설정!$B$18-설정!$B$13),0) -> 0 | Q49: =L49-P49 -> 130050000 | R49: =IF(물량원가기준!D49="","",물량원가기준!D49*H49) -> 128750000 | S49: =E49*F49 -> 1092420000 | T49: =물량원가기준!I49+IF(B49>=설정!$B$6,I49*(설정!$B$18-설정!$B$13),0) -> 65000 | U49: =IF(OR(COUNT(물량원가기준!E49:J49)<>6,COUNTIFS(물량원가기준!$A$6:$A$100,A49)<>1),0,1) -> 1
A50: =물량원가기준!A50 -> 2027-09|A-e | B50: =물량원가기준!B50 -> 46631 | C50: =물량원가기준!C50 -> A-e | D50: =물량원가기준!E50 -> 3059 | E50: =물량원가기준!F50 -> 3059 | F50: =물량원가기준!G50 -> 150000 | G50: =SUM(물량원가기준!H50:J50) -> 132000 | H50: =F50-G50 -> 18000 | I50: =부품모델매핑!D10 -> 0 | J50: =IF(ISNUMBER(물량원가기준!F50),E50*I50,"미산출") -> 0 | K50: =D50*H50 -> 55062000 | L50: =E50*H50 -> 55062000 | M50: =L50-K50 -> 0 | N50: =IF(AND(B50>=설정!$B$6,B50<설정!$B$23),1,0) -> 1 | O50: =IF(AND(B50>=설정!$B$6,B50<설정!$B$24),1,0) -> 1 | P50: =IF(B50>=설정!$B$6,J50*(설정!$B$18-설정!$B$13),0) -> 0 | Q50: =L50-P50 -> 55062000 | R50: =IF(물량원가기준!D50="","",물량원가기준!D50*H50) -> 55620000 | S50: =E50*F50 -> 458850000 | T50: =물량원가기준!I50+IF(B50>=설정!$B$6,I50*(설정!$B$18-설정!$B$13),0) -> 50000 | U50: =IF(OR(COUNT(물량원가기준!E50:J50)<>6,COUNTIFS(물량원가기준!$A$6:$A$100,A50)<>1),0,1) -> 1
A51: =물량원가기준!A51 -> 2027-10|A-a | B51: =물량원가기준!B51 -> 46661 | C51: =물량원가기준!C51 -> A-a | D51: =물량원가기준!E51 -> 3876 | E51: =물량원가기준!F51 -> 3876 | F51: =물량원가기준!G51 -> 300000 | G51: =SUM(물량원가기준!H51:J51) -> 270000 | H51: =F51-G51 -> 30000 | I51: =부품모델매핑!D6 -> 1 | J51: =IF(ISNUMBER(물량원가기준!F51),E51*I51,"미산출") -> 3876 | K51: =D51*H51 -> 116280000 | L51: =E51*H51 -> 116280000 | M51: =L51-K51 -> 0 | N51: =IF(AND(B51>=설정!$B$6,B51<설정!$B$23),1,0) -> 1 | O51: =IF(AND(B51>=설정!$B$6,B51<설정!$B$24),1,0) -> 1 | P51: =IF(B51>=설정!$B$6,J51*(설정!$B$18-설정!$B$13),0) -> 465120 | Q51: =L51-P51 -> 115814880 | R51: =IF(물량원가기준!D51="","",물량원가기준!D51*H51) -> 122400000 | S51: =E51*F51 -> 1162800000 | T51: =물량원가기준!I51+IF(B51>=설정!$B$6,I51*(설정!$B$18-설정!$B$13),0) -> 75120 | U51: =IF(OR(COUNT(물량원가기준!E51:J51)<>6,COUNTIFS(물량원가기준!$A$6:$A$100,A51)<>1),0,1) -> 1
A52: =물량원가기준!A52 -> 2027-10|A-b | B52: =물량원가기준!B52 -> 46661 | C52: =물량원가기준!C52 -> A-b | D52: =물량원가기준!E52 -> 9690 | E52: =물량원가기준!F52 -> 9690 | F52: =물량원가기준!G52 -> 180000 | G52: =SUM(물량원가기준!H52:J52) -> 160000 | H52: =F52-G52 -> 20000 | I52: =부품모델매핑!D7 -> 1 | J52: =IF(ISNUMBER(물량원가기준!F52),E52*I52,"미산출") -> 9690 | K52: =D52*H52 -> 193800000 | L52: =E52*H52 -> 193800000 | M52: =L52-K52 -> 0 | N52: =IF(AND(B52>=설정!$B$6,B52<설정!$B$23),1,0) -> 1 | O52: =IF(AND(B52>=설정!$B$6,B52<설정!$B$24),1,0) -> 1 | P52: =IF(B52>=설정!$B$6,J52*(설정!$B$18-설정!$B$13),0) -> 1162800 | Q52: =L52-P52 -> 192637200 | R52: =IF(물량원가기준!D52="","",물량원가기준!D52*H52) -> 204000000 | S52: =E52*F52 -> 1744200000 | T52: =물량원가기준!I52+IF(B52>=설정!$B$6,I52*(설정!$B$18-설정!$B$13),0) -> 95120 | U52: =IF(OR(COUNT(물량원가기준!E52:J52)<>6,COUNTIFS(물량원가기준!$A$6:$A$100,A52)<>1),0,1) -> 1
A53: =물량원가기준!A53 -> 2027-10|A-c | B53: =물량원가기준!B53 -> 46661 | C53: =물량원가기준!C53 -> A-c | D53: =물량원가기준!E53 -> 6059 | E53: =물량원가기준!F53 -> 6059 | F53: =물량원가기준!G53 -> 230000 | G53: =SUM(물량원가기준!H53:J53) -> 202000 | H53: =F53-G53 -> 28000 | I53: =부품모델매핑!D8 -> 0 | J53: =IF(ISNUMBER(물량원가기준!F53),E53*I53,"미산출") -> 0 | K53: =D53*H53 -> 169652000 | L53: =E53*H53 -> 169652000 | M53: =L53-K53 -> 0 | N53: =IF(AND(B53>=설정!$B$6,B53<설정!$B$23),1,0) -> 1 | O53: =IF(AND(B53>=설정!$B$6,B53<설정!$B$24),1,0) -> 1 | P53: =IF(B53>=설정!$B$6,J53*(설정!$B$18-설정!$B$13),0) -> 0 | Q53: =L53-P53 -> 169652000 | R53: =IF(물량원가기준!D53="","",물량원가기준!D53*H53) -> 171360000 | S53: =E53*F53 -> 1393570000 | T53: =물량원가기준!I53+IF(B53>=설정!$B$6,I53*(설정!$B$18-설정!$B$13),0) -> 60000 | U53: =IF(OR(COUNT(물량원가기준!E53:J53)<>6,COUNTIFS(물량원가기준!$A$6:$A$100,A53)<>1),0,1) -> 1
A54: =물량원가기준!A54 -> 2027-10|A-d | B54: =물량원가기준!B54 -> 46661 | C54: =물량원가기준!C54 -> A-d | D54: =물량원가기준!E54 -> 5151 | E54: =물량원가기준!F54 -> 5151 | F54: =물량원가기준!G54 -> 210000 | G54: =SUM(물량원가기준!H54:J54) -> 185000 | H54: =F54-G54 -> 25000 | I54: =부품모델매핑!D9 -> 0 | J54: =IF(ISNUMBER(물량원가기준!F54),E54*I54,"미산출") -> 0 | K54: =D54*H54 -> 128775000 | L54: =E54*H54 -> 128775000 | M54: =L54-K54 -> 0 | N54: =IF(AND(B54>=설정!$B$6,B54<설정!$B$23),1,0) -> 1 | O54: =IF(AND(B54>=설정!$B$6,B54<설정!$B$24),1,0) -> 1 | P54: =IF(B54>=설정!$B$6,J54*(설정!$B$18-설정!$B$13),0) -> 0 | Q54: =L54-P54 -> 128775000 | R54: =IF(물량원가기준!D54="","",물량원가기준!D54*H54) -> 127500000 | S54: =E54*F54 -> 1081710000 | T54: =물량원가기준!I54+IF(B54>=설정!$B$6,I54*(설정!$B$18-설정!$B$13),0) -> 65000 | U54: =IF(OR(COUNT(물량원가기준!E54:J54)<>6,COUNTIFS(물량원가기준!$A$6:$A$100,A54)<>1),0,1) -> 1
A55: =물량원가기준!A55 -> 2027-10|A-e | B55: =물량원가기준!B55 -> 46661 | C55: =물량원가기준!C55 -> A-e | D55: =물량원가기준!E55 -> 3029 | E55: =물량원가기준!F55 -> 3029 | F55: =물량원가기준!G55 -> 150000 | G55: =SUM(물량원가기준!H55:J55) -> 132000 | H55: =F55-G55 -> 18000 | I55: =부품모델매핑!D10 -> 0 | J55: =IF(ISNUMBER(물량원가기준!F55),E55*I55,"미산출") -> 0 | K55: =D55*H55 -> 54522000 | L55: =E55*H55 -> 54522000 | M55: =L55-K55 -> 0 | N55: =IF(AND(B55>=설정!$B$6,B55<설정!$B$23),1,0) -> 1 | O55: =IF(AND(B55>=설정!$B$6,B55<설정!$B$24),1,0) -> 1 | P55: =IF(B55>=설정!$B$6,J55*(설정!$B$18-설정!$B$13),0) -> 0 | Q55: =L55-P55 -> 54522000 | R55: =IF(물량원가기준!D55="","",물량원가기준!D55*H55) -> 55080000 | S55: =E55*F55 -> 454350000 | T55: =물량원가기준!I55+IF(B55>=설정!$B$6,I55*(설정!$B$18-설정!$B$13),0) -> 50000 | U55: =IF(OR(COUNT(물량원가기준!E55:J55)<>6,COUNTIFS(물량원가기준!$A$6:$A$100,A55)<>1),0,1) -> 1
A56: =물량원가기준!A56 -> 2027-11|A-a | B56: =물량원가기준!B56 -> 46692 | C56: =물량원가기준!C56 -> A-a | D56: =물량원가기준!E56 -> 3800 | E56: =물량원가기준!F56 -> 3800 | F56: =물량원가기준!G56 -> 300000 | G56: =SUM(물량원가기준!H56:J56) -> 270000 | H56: =F56-G56 -> 30000 | I56: =부품모델매핑!D6 -> 1 | J56: =IF(ISNUMBER(물량원가기준!F56),E56*I56,"미산출") -> 3800 | K56: =D56*H56 -> 114000000 | L56: =E56*H56 -> 114000000 | M56: =L56-K56 -> 0 | N56: =IF(AND(B56>=설정!$B$6,B56<설정!$B$23),1,0) -> 1 | O56: =IF(AND(B56>=설정!$B$6,B56<설정!$B$24),1,0) -> 1 | P56: =IF(B56>=설정!$B$6,J56*(설정!$B$18-설정!$B$13),0) -> 456000 | Q56: =L56-P56 -> 113544000 | R56: =IF(물량원가기준!D56="","",물량원가기준!D56*H56) -> 120000000 | S56: =E56*F56 -> 1140000000 | T56: =물량원가기준!I56+IF(B56>=설정!$B$6,I56*(설정!$B$18-설정!$B$13),0) -> 75120 | U56: =IF(OR(COUNT(물량원가기준!E56:J56)<>6,COUNTIFS(물량원가기준!$A$6:$A$100,A56)<>1),0,1) -> 1
A57: =물량원가기준!A57 -> 2027-11|A-b | B57: =물량원가기준!B57 -> 46692 | C57: =물량원가기준!C57 -> A-b | D57: =물량원가기준!E57 -> 9500 | E57: =물량원가기준!F57 -> 9500 | F57: =물량원가기준!G57 -> 180000 | G57: =SUM(물량원가기준!H57:J57) -> 160000 | H57: =F57-G57 -> 20000 | I57: =부품모델매핑!D7 -> 1 | J57: =IF(ISNUMBER(물량원가기준!F57),E57*I57,"미산출") -> 9500 | K57: =D57*H57 -> 190000000 | L57: =E57*H57 -> 190000000 | M57: =L57-K57 -> 0 | N57: =IF(AND(B57>=설정!$B$6,B57<설정!$B$23),1,0) -> 1 | O57: =IF(AND(B57>=설정!$B$6,B57<설정!$B$24),1,0) -> 1 | P57: =IF(B57>=설정!$B$6,J57*(설정!$B$18-설정!$B$13),0) -> 1140000 | Q57: =L57-P57 -> 188860000 | R57: =IF(물량원가기준!D57="","",물량원가기준!D57*H57) -> 200000000 | S57: =E57*F57 -> 1710000000 | T57: =물량원가기준!I57+IF(B57>=설정!$B$6,I57*(설정!$B$18-설정!$B$13),0) -> 95120 | U57: =IF(OR(COUNT(물량원가기준!E57:J57)<>6,COUNTIFS(물량원가기준!$A$6:$A$100,A57)<>1),0,1) -> 1
A58: =물량원가기준!A58 -> 2027-11|A-c | B58: =물량원가기준!B58 -> 46692 | C58: =물량원가기준!C58 -> A-c | D58: =물량원가기준!E58 -> 5940 | E58: =물량원가기준!F58 -> 5940 | F58: =물량원가기준!G58 -> 230000 | G58: =SUM(물량원가기준!H58:J58) -> 202000 | H58: =F58-G58 -> 28000 | I58: =부품모델매핑!D8 -> 0 | J58: =IF(ISNUMBER(물량원가기준!F58),E58*I58,"미산출") -> 0 | K58: =D58*H58 -> 166320000 | L58: =E58*H58 -> 166320000 | M58: =L58-K58 -> 0 | N58: =IF(AND(B58>=설정!$B$6,B58<설정!$B$23),1,0) -> 1 | O58: =IF(AND(B58>=설정!$B$6,B58<설정!$B$24),1,0) -> 1 | P58: =IF(B58>=설정!$B$6,J58*(설정!$B$18-설정!$B$13),0) -> 0 | Q58: =L58-P58 -> 166320000 | R58: =IF(물량원가기준!D58="","",물량원가기준!D58*H58) -> 168000000 | S58: =E58*F58 -> 1366200000 | T58: =물량원가기준!I58+IF(B58>=설정!$B$6,I58*(설정!$B$18-설정!$B$13),0) -> 60000 | U58: =IF(OR(COUNT(물량원가기준!E58:J58)<>6,COUNTIFS(물량원가기준!$A$6:$A$100,A58)<>1),0,1) -> 1
A59: =물량원가기준!A59 -> 2027-11|A-d | B59: =물량원가기준!B59 -> 46692 | C59: =물량원가기준!C59 -> A-d | D59: =물량원가기준!E59 -> 5050 | E59: =물량원가기준!F59 -> 5050 | F59: =물량원가기준!G59 -> 210000 | G59: =SUM(물량원가기준!H59:J59) -> 185000 | H59: =F59-G59 -> 25000 | I59: =부품모델매핑!D9 -> 0 | J59: =IF(ISNUMBER(물량원가기준!F59),E59*I59,"미산출") -> 0 | K59: =D59*H59 -> 126250000 | L59: =E59*H59 -> 126250000 | M59: =L59-K59 -> 0 | N59: =IF(AND(B59>=설정!$B$6,B59<설정!$B$23),1,0) -> 1 | O59: =IF(AND(B59>=설정!$B$6,B59<설정!$B$24),1,0) -> 1 | P59: =IF(B59>=설정!$B$6,J59*(설정!$B$18-설정!$B$13),0) -> 0 | Q59: =L59-P59 -> 126250000 | R59: =IF(물량원가기준!D59="","",물량원가기준!D59*H59) -> 125000000 | S59: =E59*F59 -> 1060500000 | T59: =물량원가기준!I59+IF(B59>=설정!$B$6,I59*(설정!$B$18-설정!$B$13),0) -> 65000 | U59: =IF(OR(COUNT(물량원가기준!E59:J59)<>6,COUNTIFS(물량원가기준!$A$6:$A$100,A59)<>1),0,1) -> 1
A60: =물량원가기준!A60 -> 2027-11|A-e | B60: =물량원가기준!B60 -> 46692 | C60: =물량원가기준!C60 -> A-e | D60: =물량원가기준!E60 -> 2970 | E60: =물량원가기준!F60 -> 2970 | F60: =물량원가기준!G60 -> 150000 | G60: =SUM(물량원가기준!H60:J60) -> 132000 | H60: =F60-G60 -> 18000 | I60: =부품모델매핑!D10 -> 0 | J60: =IF(ISNUMBER(물량원가기준!F60),E60*I60,"미산출") -> 0 | K60: =D60*H60 -> 53460000 | L60: =E60*H60 -> 53460000 | M60: =L60-K60 -> 0 | N60: =IF(AND(B60>=설정!$B$6,B60<설정!$B$23),1,0) -> 1 | O60: =IF(AND(B60>=설정!$B$6,B60<설정!$B$24),1,0) -> 1 | P60: =IF(B60>=설정!$B$6,J60*(설정!$B$18-설정!$B$13),0) -> 0 | Q60: =L60-P60 -> 53460000 | R60: =IF(물량원가기준!D60="","",물량원가기준!D60*H60) -> 54000000 | S60: =E60*F60 -> 445500000 | T60: =물량원가기준!I60+IF(B60>=설정!$B$6,I60*(설정!$B$18-설정!$B$13),0) -> 50000 | U60: =IF(OR(COUNT(물량원가기준!E60:J60)<>6,COUNTIFS(물량원가기준!$A$6:$A$100,A60)<>1),0,1) -> 1
A61: =물량원가기준!A61 -> 2027-12|A-a | B61: =물량원가기준!B61 -> 46722 | C61: =물량원가기준!C61 -> A-a | D61: =물량원가기준!E61 -> 3610 | E61: =물량원가기준!F61 -> 3610 | F61: =물량원가기준!G61 -> 300000 | G61: =SUM(물량원가기준!H61:J61) -> 270000 | H61: =F61-G61 -> 30000 | I61: =부품모델매핑!D6 -> 1 | J61: =IF(ISNUMBER(물량원가기준!F61),E61*I61,"미산출") -> 3610 | K61: =D61*H61 -> 108300000 | L61: =E61*H61 -> 108300000 | M61: =L61-K61 -> 0 | N61: =IF(AND(B61>=설정!$B$6,B61<설정!$B$23),1,0) -> 1 | O61: =IF(AND(B61>=설정!$B$6,B61<설정!$B$24),1,0) -> 1 | P61: =IF(B61>=설정!$B$6,J61*(설정!$B$18-설정!$B$13),0) -> 433200 | Q61: =L61-P61 -> 107866800 | R61: =IF(물량원가기준!D61="","",물량원가기준!D61*H61) -> 114000000 | S61: =E61*F61 -> 1083000000 | T61: =물량원가기준!I61+IF(B61>=설정!$B$6,I61*(설정!$B$18-설정!$B$13),0) -> 75120 | U61: =IF(OR(COUNT(물량원가기준!E61:J61)<>6,COUNTIFS(물량원가기준!$A$6:$A$100,A61)<>1),0,1) -> 1
A62: =물량원가기준!A62 -> 2027-12|A-b | B62: =물량원가기준!B62 -> 46722 | C62: =물량원가기준!C62 -> A-b | D62: =물량원가기준!E62 -> 9025 | E62: =물량원가기준!F62 -> 9025 | F62: =물량원가기준!G62 -> 180000 | G62: =SUM(물량원가기준!H62:J62) -> 160000 | H62: =F62-G62 -> 20000 | I62: =부품모델매핑!D7 -> 1 | J62: =IF(ISNUMBER(물량원가기준!F62),E62*I62,"미산출") -> 9025 | K62: =D62*H62 -> 180500000 | L62: =E62*H62 -> 180500000 | M62: =L62-K62 -> 0 | N62: =IF(AND(B62>=설정!$B$6,B62<설정!$B$23),1,0) -> 1 | O62: =IF(AND(B62>=설정!$B$6,B62<설정!$B$24),1,0) -> 1 | P62: =IF(B62>=설정!$B$6,J62*(설정!$B$18-설정!$B$13),0) -> 1083000 | Q62: =L62-P62 -> 179417000 | R62: =IF(물량원가기준!D62="","",물량원가기준!D62*H62) -> 190000000 | S62: =E62*F62 -> 1624500000 | T62: =물량원가기준!I62+IF(B62>=설정!$B$6,I62*(설정!$B$18-설정!$B$13),0) -> 95120 | U62: =IF(OR(COUNT(물량원가기준!E62:J62)<>6,COUNTIFS(물량원가기준!$A$6:$A$100,A62)<>1),0,1) -> 1
A63: =물량원가기준!A63 -> 2027-12|A-c | B63: =물량원가기준!B63 -> 46722 | C63: =물량원가기준!C63 -> A-c | D63: =물량원가기준!E63 -> 5643 | E63: =물량원가기준!F63 -> 5643 | F63: =물량원가기준!G63 -> 230000 | G63: =SUM(물량원가기준!H63:J63) -> 202000 | H63: =F63-G63 -> 28000 | I63: =부품모델매핑!D8 -> 0 | J63: =IF(ISNUMBER(물량원가기준!F63),E63*I63,"미산출") -> 0 | K63: =D63*H63 -> 158004000 | L63: =E63*H63 -> 158004000 | M63: =L63-K63 -> 0 | N63: =IF(AND(B63>=설정!$B$6,B63<설정!$B$23),1,0) -> 1 | O63: =IF(AND(B63>=설정!$B$6,B63<설정!$B$24),1,0) -> 1 | P63: =IF(B63>=설정!$B$6,J63*(설정!$B$18-설정!$B$13),0) -> 0 | Q63: =L63-P63 -> 158004000 | R63: =IF(물량원가기준!D63="","",물량원가기준!D63*H63) -> 159600000 | S63: =E63*F63 -> 1297890000 | T63: =물량원가기준!I63+IF(B63>=설정!$B$6,I63*(설정!$B$18-설정!$B$13),0) -> 60000 | U63: =IF(OR(COUNT(물량원가기준!E63:J63)<>6,COUNTIFS(물량원가기준!$A$6:$A$100,A63)<>1),0,1) -> 1
A64: =물량원가기준!A64 -> 2027-12|A-d | B64: =물량원가기준!B64 -> 46722 | C64: =물량원가기준!C64 -> A-d | D64: =물량원가기준!E64 -> 4798 | E64: =물량원가기준!F64 -> 4798 | F64: =물량원가기준!G64 -> 210000 | G64: =SUM(물량원가기준!H64:J64) -> 185000 | H64: =F64-G64 -> 25000 | I64: =부품모델매핑!D9 -> 0 | J64: =IF(ISNUMBER(물량원가기준!F64),E64*I64,"미산출") -> 0 | K64: =D64*H64 -> 119950000 | L64: =E64*H64 -> 119950000 | M64: =L64-K64 -> 0 | N64: =IF(AND(B64>=설정!$B$6,B64<설정!$B$23),1,0) -> 1 | O64: =IF(AND(B64>=설정!$B$6,B64<설정!$B$24),1,0) -> 1 | P64: =IF(B64>=설정!$B$6,J64*(설정!$B$18-설정!$B$13),0) -> 0 | Q64: =L64-P64 -> 119950000 | R64: =IF(물량원가기준!D64="","",물량원가기준!D64*H64) -> 118750000 | S64: =E64*F64 -> 1007580000 | T64: =물량원가기준!I64+IF(B64>=설정!$B$6,I64*(설정!$B$18-설정!$B$13),0) -> 65000 | U64: =IF(OR(COUNT(물량원가기준!E64:J64)<>6,COUNTIFS(물량원가기준!$A$6:$A$100,A64)<>1),0,1) -> 1
A65: =물량원가기준!A65 -> 2027-12|A-e | B65: =물량원가기준!B65 -> 46722 | C65: =물량원가기준!C65 -> A-e | D65: =물량원가기준!E65 -> 2822 | E65: =물량원가기준!F65 -> 2822 | F65: =물량원가기준!G65 -> 150000 | G65: =SUM(물량원가기준!H65:J65) -> 132000 | H65: =F65-G65 -> 18000 | I65: =부품모델매핑!D10 -> 0 | J65: =IF(ISNUMBER(물량원가기준!F65),E65*I65,"미산출") -> 0 | K65: =D65*H65 -> 50796000 | L65: =E65*H65 -> 50796000 | M65: =L65-K65 -> 0 | N65: =IF(AND(B65>=설정!$B$6,B65<설정!$B$23),1,0) -> 1 | O65: =IF(AND(B65>=설정!$B$6,B65<설정!$B$24),1,0) -> 1 | P65: =IF(B65>=설정!$B$6,J65*(설정!$B$18-설정!$B$13),0) -> 0 | Q65: =L65-P65 -> 50796000 | R65: =IF(물량원가기준!D65="","",물량원가기준!D65*H65) -> 51300000 | S65: =E65*F65 -> 423300000 | T65: =물량원가기준!I65+IF(B65>=설정!$B$6,I65*(설정!$B$18-설정!$B$13),0) -> 50000 | U65: =IF(OR(COUNT(물량원가기준!E65:J65)<>6,COUNTIFS(물량원가기준!$A$6:$A$100,A65)<>1),0,1) -> 1
A66: =물량원가기준!A66 -> 2028-01|A-a | B66: =물량원가기준!B66 -> 46753 | C66: =물량원가기준!C66 -> A-a | D66: =물량원가기준!E66 -> 3958 | E66: =물량원가기준!F66 -> 3958 | F66: =물량원가기준!G66 -> 300000 | G66: =SUM(물량원가기준!H66:J66) -> 270000 | H66: =F66-G66 -> 30000 | I66: =부품모델매핑!D6 -> 1 | J66: =IF(ISNUMBER(물량원가기준!F66),E66*I66,"미산출") -> 3958 | K66: =D66*H66 -> 118740000 | L66: =E66*H66 -> 118740000 | M66: =L66-K66 -> 0 | N66: =IF(AND(B66>=설정!$B$6,B66<설정!$B$23),1,0) -> 1 | O66: =IF(AND(B66>=설정!$B$6,B66<설정!$B$24),1,0) -> 0 | P66: =IF(B66>=설정!$B$6,J66*(설정!$B$18-설정!$B$13),0) -> 474960 | Q66: =L66-P66 -> 118265040 | R66: =IF(물량원가기준!D66="","",물량원가기준!D66*H66) | S66: =E66*F66 -> 1187400000 | T66: =물량원가기준!I66+IF(B66>=설정!$B$6,I66*(설정!$B$18-설정!$B$13),0) -> 75120 | U66: =IF(OR(COUNT(물량원가기준!E66:J66)<>6,COUNTIFS(물량원가기준!$A$6:$A$100,A66)<>1),0,1) -> 1
A67: =물량원가기준!A67 -> 2028-01|A-b | B67: =물량원가기준!B67 -> 46753 | C67: =물량원가기준!C67 -> A-b | D67: =물량원가기준!E67 -> 9894 | E67: =물량원가기준!F67 -> 9894 | F67: =물량원가기준!G67 -> 180000 | G67: =SUM(물량원가기준!H67:J67) -> 160000 | H67: =F67-G67 -> 20000 | I67: =부품모델매핑!D7 -> 1 | J67: =IF(ISNUMBER(물량원가기준!F67),E67*I67,"미산출") -> 9894 | K67: =D67*H67 -> 197880000 | L67: =E67*H67 -> 197880000 | M67: =L67-K67 -> 0 | N67: =IF(AND(B67>=설정!$B$6,B67<설정!$B$23),1,0) -> 1 | O67: =IF(AND(B67>=설정!$B$6,B67<설정!$B$24),1,0) -> 0 | P67: =IF(B67>=설정!$B$6,J67*(설정!$B$18-설정!$B$13),0) -> 1187280 | Q67: =L67-P67 -> 196692720 | R67: =IF(물량원가기준!D67="","",물량원가기준!D67*H67) | S67: =E67*F67 -> 1780920000 | T67: =물량원가기준!I67+IF(B67>=설정!$B$6,I67*(설정!$B$18-설정!$B$13),0) -> 95120 | U67: =IF(OR(COUNT(물량원가기준!E67:J67)<>6,COUNTIFS(물량원가기준!$A$6:$A$100,A67)<>1),0,1) -> 1
A68: =물량원가기준!A68 -> 2028-01|A-c | B68: =물량원가기준!B68 -> 46753 | C68: =물량원가기준!C68 -> A-c | D68: =물량원가기준!E68 -> 5877 | E68: =물량원가기준!F68 -> 5877 | F68: =물량원가기준!G68 -> 230000 | G68: =SUM(물량원가기준!H68:J68) -> 202000 | H68: =F68-G68 -> 28000 | I68: =부품모델매핑!D8 -> 0 | J68: =IF(ISNUMBER(물량원가기준!F68),E68*I68,"미산출") -> 0 | K68: =D68*H68 -> 164556000 | L68: =E68*H68 -> 164556000 | M68: =L68-K68 -> 0 | N68: =IF(AND(B68>=설정!$B$6,B68<설정!$B$23),1,0) -> 1 | O68: =IF(AND(B68>=설정!$B$6,B68<설정!$B$24),1,0) -> 0 | P68: =IF(B68>=설정!$B$6,J68*(설정!$B$18-설정!$B$13),0) -> 0 | Q68: =L68-P68 -> 164556000 | R68: =IF(물량원가기준!D68="","",물량원가기준!D68*H68) | S68: =E68*F68 -> 1351710000 | T68: =물량원가기준!I68+IF(B68>=설정!$B$6,I68*(설정!$B$18-설정!$B$13),0) -> 60000 | U68: =IF(OR(COUNT(물량원가기준!E68:J68)<>6,COUNTIFS(물량원가기준!$A$6:$A$100,A68)<>1),0,1) -> 1
A69: =물량원가기준!A69 -> 2028-01|A-d | B69: =물량원가기준!B69 -> 46753 | C69: =물량원가기준!C69 -> A-d | D69: =물량원가기준!E69 -> 4996 | E69: =물량원가기준!F69 -> 4996 | F69: =물량원가기준!G69 -> 210000 | G69: =SUM(물량원가기준!H69:J69) -> 185000 | H69: =F69-G69 -> 25000 | I69: =부품모델매핑!D9 -> 0 | J69: =IF(ISNUMBER(물량원가기준!F69),E69*I69,"미산출") -> 0 | K69: =D69*H69 -> 124900000 | L69: =E69*H69 -> 124900000 | M69: =L69-K69 -> 0 | N69: =IF(AND(B69>=설정!$B$6,B69<설정!$B$23),1,0) -> 1 | O69: =IF(AND(B69>=설정!$B$6,B69<설정!$B$24),1,0) -> 0 | P69: =IF(B69>=설정!$B$6,J69*(설정!$B$18-설정!$B$13),0) -> 0 | Q69: =L69-P69 -> 124900000 | R69: =IF(물량원가기준!D69="","",물량원가기준!D69*H69) | S69: =E69*F69 -> 1049160000 | T69: =물량원가기준!I69+IF(B69>=설정!$B$6,I69*(설정!$B$18-설정!$B$13),0) -> 65000 | U69: =IF(OR(COUNT(물량원가기준!E69:J69)<>6,COUNTIFS(물량원가기준!$A$6:$A$100,A69)<>1),0,1) -> 1
A70: =물량원가기준!A70 -> 2028-01|A-e | B70: =물량원가기준!B70 -> 46753 | C70: =물량원가기준!C70 -> A-e | D70: =물량원가기준!E70 -> 2938 | E70: =물량원가기준!F70 -> 2938 | F70: =물량원가기준!G70 -> 150000 | G70: =SUM(물량원가기준!H70:J70) -> 132000 | H70: =F70-G70 -> 18000 | I70: =부품모델매핑!D10 -> 0 | J70: =IF(ISNUMBER(물량원가기준!F70),E70*I70,"미산출") -> 0 | K70: =D70*H70 -> 52884000 | L70: =E70*H70 -> 52884000 | M70: =L70-K70 -> 0 | N70: =IF(AND(B70>=설정!$B$6,B70<설정!$B$23),1,0) -> 1 | O70: =IF(AND(B70>=설정!$B$6,B70<설정!$B$24),1,0) -> 0 | P70: =IF(B70>=설정!$B$6,J70*(설정!$B$18-설정!$B$13),0) -> 0 | Q70: =L70-P70 -> 52884000 | R70: =IF(물량원가기준!D70="","",물량원가기준!D70*H70) | S70: =E70*F70 -> 440700000 | T70: =물량원가기준!I70+IF(B70>=설정!$B$6,I70*(설정!$B$18-설정!$B$13),0) -> 50000 | U70: =IF(OR(COUNT(물량원가기준!E70:J70)<>6,COUNTIFS(물량원가기준!$A$6:$A$100,A70)<>1),0,1) -> 1
A71: =물량원가기준!A71 -> 2028-02|A-a | B71: =물량원가기준!B71 -> 46784 | C71: =물량원가기준!C71 -> A-a | D71: =물량원가기준!E71 -> 3457 | E71: =물량원가기준!F71 -> 3457 | F71: =물량원가기준!G71 -> 300000 | G71: =SUM(물량원가기준!H71:J71) -> 270000 | H71: =F71-G71 -> 30000 | I71: =부품모델매핑!D6 -> 1 | J71: =IF(ISNUMBER(물량원가기준!F71),E71*I71,"미산출") -> 3457 | K71: =D71*H71 -> 103710000 | L71: =E71*H71 -> 103710000 | M71: =L71-K71 -> 0 | N71: =IF(AND(B71>=설정!$B$6,B71<설정!$B$23),1,0) -> 1 | O71: =IF(AND(B71>=설정!$B$6,B71<설정!$B$24),1,0) -> 0 | P71: =IF(B71>=설정!$B$6,J71*(설정!$B$18-설정!$B$13),0) -> 414840 | Q71: =L71-P71 -> 103295160 | R71: =IF(물량원가기준!D71="","",물량원가기준!D71*H71) | S71: =E71*F71 -> 1037100000 | T71: =물량원가기준!I71+IF(B71>=설정!$B$6,I71*(설정!$B$18-설정!$B$13),0) -> 75120 | U71: =IF(OR(COUNT(물량원가기준!E71:J71)<>6,COUNTIFS(물량원가기준!$A$6:$A$100,A71)<>1),0,1) -> 1
A72: =물량원가기준!A72 -> 2028-02|A-b | B72: =물량원가기준!B72 -> 46784 | C72: =물량원가기준!C72 -> A-b | D72: =물량원가기준!E72 -> 8643 | E72: =물량원가기준!F72 -> 8643 | F72: =물량원가기준!G72 -> 180000 | G72: =SUM(물량원가기준!H72:J72) -> 160000 | H72: =F72-G72 -> 20000 | I72: =부품모델매핑!D7 -> 1 | J72: =IF(ISNUMBER(물량원가기준!F72),E72*I72,"미산출") -> 8643 | K72: =D72*H72 -> 172860000 | L72: =E72*H72 -> 172860000 | M72: =L72-K72 -> 0 | N72: =IF(AND(B72>=설정!$B$6,B72<설정!$B$23),1,0) -> 1 | O72: =IF(AND(B72>=설정!$B$6,B72<설정!$B$24),1,0) -> 0 | P72: =IF(B72>=설정!$B$6,J72*(설정!$B$18-설정!$B$13),0) -> 1037160 | Q72: =L72-P72 -> 171822840 | R72: =IF(물량원가기준!D72="","",물량원가기준!D72*H72) | S72: =E72*F72 -> 1555740000 | T72: =물량원가기준!I72+IF(B72>=설정!$B$6,I72*(설정!$B$18-설정!$B$13),0) -> 95120 | U72: =IF(OR(COUNT(물량원가기준!E72:J72)<>6,COUNTIFS(물량원가기준!$A$6:$A$100,A72)<>1),0,1) -> 1
A73: =물량원가기준!A73 -> 2028-02|A-c | B73: =물량원가기준!B73 -> 46784 | C73: =물량원가기준!C73 -> A-c | D73: =물량원가기준!E73 -> 5186 | E73: =물량원가기준!F73 -> 5186 | F73: =물량원가기준!G73 -> 230000 | G73: =SUM(물량원가기준!H73:J73) -> 202000 | H73: =F73-G73 -> 28000 | I73: =부품모델매핑!D8 -> 0 | J73: =IF(ISNUMBER(물량원가기준!F73),E73*I73,"미산출") -> 0 | K73: =D73*H73 -> 145208000 | L73: =E73*H73 -> 145208000 | M73: =L73-K73 -> 0 | N73: =IF(AND(B73>=설정!$B$6,B73<설정!$B$23),1,0) -> 1 | O73: =IF(AND(B73>=설정!$B$6,B73<설정!$B$24),1,0) -> 0 | P73: =IF(B73>=설정!$B$6,J73*(설정!$B$18-설정!$B$13),0) -> 0 | Q73: =L73-P73 -> 145208000 | R73: =IF(물량원가기준!D73="","",물량원가기준!D73*H73) | S73: =E73*F73 -> 1192780000 | T73: =물량원가기준!I73+IF(B73>=설정!$B$6,I73*(설정!$B$18-설정!$B$13),0) -> 60000 | U73: =IF(OR(COUNT(물량원가기준!E73:J73)<>6,COUNTIFS(물량원가기준!$A$6:$A$100,A73)<>1),0,1) -> 1
A74: =물량원가기준!A74 -> 2028-02|A-d | B74: =물량원가기준!B74 -> 46784 | C74: =물량원가기준!C74 -> A-d | D74: =물량원가기준!E74 -> 4409 | E74: =물량원가기준!F74 -> 4409 | F74: =물량원가기준!G74 -> 210000 | G74: =SUM(물량원가기준!H74:J74) -> 185000 | H74: =F74-G74 -> 25000 | I74: =부품모델매핑!D9 -> 0 | J74: =IF(ISNUMBER(물량원가기준!F74),E74*I74,"미산출") -> 0 | K74: =D74*H74 -> 110225000 | L74: =E74*H74 -> 110225000 | M74: =L74-K74 -> 0 | N74: =IF(AND(B74>=설정!$B$6,B74<설정!$B$23),1,0) -> 1 | O74: =IF(AND(B74>=설정!$B$6,B74<설정!$B$24),1,0) -> 0 | P74: =IF(B74>=설정!$B$6,J74*(설정!$B$18-설정!$B$13),0) -> 0 | Q74: =L74-P74 -> 110225000 | R74: =IF(물량원가기준!D74="","",물량원가기준!D74*H74) | S74: =E74*F74 -> 925890000 | T74: =물량원가기준!I74+IF(B74>=설정!$B$6,I74*(설정!$B$18-설정!$B$13),0) -> 65000 | U74: =IF(OR(COUNT(물량원가기준!E74:J74)<>6,COUNTIFS(물량원가기준!$A$6:$A$100,A74)<>1),0,1) -> 1
A75: =물량원가기준!A75 -> 2028-02|A-e | B75: =물량원가기준!B75 -> 46784 | C75: =물량원가기준!C75 -> A-e | D75: =물량원가기준!E75 -> 2593 | E75: =물량원가기준!F75 -> 2593 | F75: =물량원가기준!G75 -> 150000 | G75: =SUM(물량원가기준!H75:J75) -> 132000 | H75: =F75-G75 -> 18000 | I75: =부품모델매핑!D10 -> 0 | J75: =IF(ISNUMBER(물량원가기준!F75),E75*I75,"미산출") -> 0 | K75: =D75*H75 -> 46674000 | L75: =E75*H75 -> 46674000 | M75: =L75-K75 -> 0 | N75: =IF(AND(B75>=설정!$B$6,B75<설정!$B$23),1,0) -> 1 | O75: =IF(AND(B75>=설정!$B$6,B75<설정!$B$24),1,0) -> 0 | P75: =IF(B75>=설정!$B$6,J75*(설정!$B$18-설정!$B$13),0) -> 0 | Q75: =L75-P75 -> 46674000 | R75: =IF(물량원가기준!D75="","",물량원가기준!D75*H75) | S75: =E75*F75 -> 388950000 | T75: =물량원가기준!I75+IF(B75>=설정!$B$6,I75*(설정!$B$18-설정!$B$13),0) -> 50000 | U75: =IF(OR(COUNT(물량원가기준!E75:J75)<>6,COUNTIFS(물량원가기준!$A$6:$A$100,A75)<>1),0,1) -> 1
A76: =물량원가기준!A76 -> 2028-03|A-a | B76: =물량원가기준!B76 -> 46813 | C76: =물량원가기준!C76 -> A-a | D76: =물량원가기준!E76 -> 3993 | E76: =물량원가기준!F76 -> 3993 | F76: =물량원가기준!G76 -> 300000 | G76: =SUM(물량원가기준!H76:J76) -> 270000 | H76: =F76-G76 -> 30000 | I76: =부품모델매핑!D6 -> 1 | J76: =IF(ISNUMBER(물량원가기준!F76),E76*I76,"미산출") -> 3993 | K76: =D76*H76 -> 119790000 | L76: =E76*H76 -> 119790000 | M76: =L76-K76 -> 0 | N76: =IF(AND(B76>=설정!$B$6,B76<설정!$B$23),1,0) -> 1 | O76: =IF(AND(B76>=설정!$B$6,B76<설정!$B$24),1,0) -> 0 | P76: =IF(B76>=설정!$B$6,J76*(설정!$B$18-설정!$B$13),0) -> 479160 | Q76: =L76-P76 -> 119310840 | R76: =IF(물량원가기준!D76="","",물량원가기준!D76*H76) | S76: =E76*F76 -> 1197900000 | T76: =물량원가기준!I76+IF(B76>=설정!$B$6,I76*(설정!$B$18-설정!$B$13),0) -> 75120 | U76: =IF(OR(COUNT(물량원가기준!E76:J76)<>6,COUNTIFS(물량원가기준!$A$6:$A$100,A76)<>1),0,1) -> 1
A77: =물량원가기준!A77 -> 2028-03|A-b | B77: =물량원가기준!B77 -> 46813 | C77: =물량원가기준!C77 -> A-b | D77: =물량원가기준!E77 -> 9981 | E77: =물량원가기준!F77 -> 9981 | F77: =물량원가기준!G77 -> 180000 | G77: =SUM(물량원가기준!H77:J77) -> 160000 | H77: =F77-G77 -> 20000 | I77: =부품모델매핑!D7 -> 1 | J77: =IF(ISNUMBER(물량원가기준!F77),E77*I77,"미산출") -> 9981 | K77: =D77*H77 -> 199620000 | L77: =E77*H77 -> 199620000 | M77: =L77-K77 -> 0 | N77: =IF(AND(B77>=설정!$B$6,B77<설정!$B$23),1,0) -> 1 | O77: =IF(AND(B77>=설정!$B$6,B77<설정!$B$24),1,0) -> 0 | P77: =IF(B77>=설정!$B$6,J77*(설정!$B$18-설정!$B$13),0) -> 1197720 | Q77: =L77-P77 -> 198422280 | R77: =IF(물량원가기준!D77="","",물량원가기준!D77*H77) | S77: =E77*F77 -> 1796580000 | T77: =물량원가기준!I77+IF(B77>=설정!$B$6,I77*(설정!$B$18-설정!$B$13),0) -> 95120 | U77: =IF(OR(COUNT(물량원가기준!E77:J77)<>6,COUNTIFS(물량원가기준!$A$6:$A$100,A77)<>1),0,1) -> 1
A78: =물량원가기준!A78 -> 2028-03|A-c | B78: =물량원가기준!B78 -> 46813 | C78: =물량원가기준!C78 -> A-c | D78: =물량원가기준!E78 -> 6050 | E78: =물량원가기준!F78 -> 6050 | F78: =물량원가기준!G78 -> 230000 | G78: =SUM(물량원가기준!H78:J78) -> 202000 | H78: =F78-G78 -> 28000 | I78: =부품모델매핑!D8 -> 0 | J78: =IF(ISNUMBER(물량원가기준!F78),E78*I78,"미산출") -> 0 | K78: =D78*H78 -> 169400000 | L78: =E78*H78 -> 169400000 | M78: =L78-K78 -> 0 | N78: =IF(AND(B78>=설정!$B$6,B78<설정!$B$23),1,0) -> 1 | O78: =IF(AND(B78>=설정!$B$6,B78<설정!$B$24),1,0) -> 0 | P78: =IF(B78>=설정!$B$6,J78*(설정!$B$18-설정!$B$13),0) -> 0 | Q78: =L78-P78 -> 169400000 | R78: =IF(물량원가기준!D78="","",물량원가기준!D78*H78) | S78: =E78*F78 -> 1391500000 | T78: =물량원가기준!I78+IF(B78>=설정!$B$6,I78*(설정!$B$18-설정!$B$13),0) -> 60000 | U78: =IF(OR(COUNT(물량원가기준!E78:J78)<>6,COUNTIFS(물량원가기준!$A$6:$A$100,A78)<>1),0,1) -> 1
A79: =물량원가기준!A79 -> 2028-03|A-d | B79: =물량원가기준!B79 -> 46813 | C79: =물량원가기준!C79 -> A-d | D79: =물량원가기준!E79 -> 5144 | E79: =물량원가기준!F79 -> 5144 | F79: =물량원가기준!G79 -> 210000 | G79: =SUM(물량원가기준!H79:J79) -> 185000 | H79: =F79-G79 -> 25000 | I79: =부품모델매핑!D9 -> 0 | J79: =IF(ISNUMBER(물량원가기준!F79),E79*I79,"미산출") -> 0 | K79: =D79*H79 -> 128600000 | L79: =E79*H79 -> 128600000 | M79: =L79-K79 -> 0 | N79: =IF(AND(B79>=설정!$B$6,B79<설정!$B$23),1,0) -> 1 | O79: =IF(AND(B79>=설정!$B$6,B79<설정!$B$24),1,0) -> 0 | P79: =IF(B79>=설정!$B$6,J79*(설정!$B$18-설정!$B$13),0) -> 0 | Q79: =L79-P79 -> 128600000 | R79: =IF(물량원가기준!D79="","",물량원가기준!D79*H79) | S79: =E79*F79 -> 1080240000 | T79: =물량원가기준!I79+IF(B79>=설정!$B$6,I79*(설정!$B$18-설정!$B$13),0) -> 65000 | U79: =IF(OR(COUNT(물량원가기준!E79:J79)<>6,COUNTIFS(물량원가기준!$A$6:$A$100,A79)<>1),0,1) -> 1
A80: =물량원가기준!A80 -> 2028-03|A-e | B80: =물량원가기준!B80 -> 46813 | C80: =물량원가기준!C80 -> A-e | D80: =물량원가기준!E80 -> 3025 | E80: =물량원가기준!F80 -> 3025 | F80: =물량원가기준!G80 -> 150000 | G80: =SUM(물량원가기준!H80:J80) -> 132000 | H80: =F80-G80 -> 18000 | I80: =부품모델매핑!D10 -> 0 | J80: =IF(ISNUMBER(물량원가기준!F80),E80*I80,"미산출") -> 0 | K80: =D80*H80 -> 54450000 | L80: =E80*H80 -> 54450000 | M80: =L80-K80 -> 0 | N80: =IF(AND(B80>=설정!$B$6,B80<설정!$B$23),1,0) -> 1 | O80: =IF(AND(B80>=설정!$B$6,B80<설정!$B$24),1,0) -> 0 | P80: =IF(B80>=설정!$B$6,J80*(설정!$B$18-설정!$B$13),0) -> 0 | Q80: =L80-P80 -> 54450000 | R80: =IF(물량원가기준!D80="","",물량원가기준!D80*H80) | S80: =E80*F80 -> 453750000 | T80: =물량원가기준!I80+IF(B80>=설정!$B$6,I80*(설정!$B$18-설정!$B$13),0) -> 50000 | U80: =IF(OR(COUNT(물량원가기준!E80:J80)<>6,COUNTIFS(물량원가기준!$A$6:$A$100,A80)<>1),0,1) -> 1
A81: =물량원가기준!A81 -> 2028-04|A-a | B81: =물량원가기준!B81 -> 46844 | C81: =물량원가기준!C81 -> A-a | D81: =물량원가기준!E81 -> 3764 | E81: =물량원가기준!F81 -> 3764 | F81: =물량원가기준!G81 -> 300000 | G81: =SUM(물량원가기준!H81:J81) -> 270000 | H81: =F81-G81 -> 30000 | I81: =부품모델매핑!D6 -> 1 | J81: =IF(ISNUMBER(물량원가기준!F81),E81*I81,"미산출") -> 3764 | K81: =D81*H81 -> 112920000 | L81: =E81*H81 -> 112920000 | M81: =L81-K81 -> 0 | N81: =IF(AND(B81>=설정!$B$6,B81<설정!$B$23),1,0) -> 1 | O81: =IF(AND(B81>=설정!$B$6,B81<설정!$B$24),1,0) -> 0 | P81: =IF(B81>=설정!$B$6,J81*(설정!$B$18-설정!$B$13),0) -> 451680 | Q81: =L81-P81 -> 112468320 | R81: =IF(물량원가기준!D81="","",물량원가기준!D81*H81) | S81: =E81*F81 -> 1129200000 | T81: =물량원가기준!I81+IF(B81>=설정!$B$6,I81*(설정!$B$18-설정!$B$13),0) -> 75120 | U81: =IF(OR(COUNT(물량원가기준!E81:J81)<>6,COUNTIFS(물량원가기준!$A$6:$A$100,A81)<>1),0,1) -> 1
A82: =물량원가기준!A82 -> 2028-04|A-b | B82: =물량원가기준!B82 -> 46844 | C82: =물량원가기준!C82 -> A-b | D82: =물량원가기준!E82 -> 9409 | E82: =물량원가기준!F82 -> 9409 | F82: =물량원가기준!G82 -> 180000 | G82: =SUM(물량원가기준!H82:J82) -> 160000 | H82: =F82-G82 -> 20000 | I82: =부품모델매핑!D7 -> 1 | J82: =IF(ISNUMBER(물량원가기준!F82),E82*I82,"미산출") -> 9409 | K82: =D82*H82 -> 188180000 | L82: =E82*H82 -> 188180000 | M82: =L82-K82 -> 0 | N82: =IF(AND(B82>=설정!$B$6,B82<설정!$B$23),1,0) -> 1 | O82: =IF(AND(B82>=설정!$B$6,B82<설정!$B$24),1,0) -> 0 | P82: =IF(B82>=설정!$B$6,J82*(설정!$B$18-설정!$B$13),0) -> 1129080 | Q82: =L82-P82 -> 187050920 | R82: =IF(물량원가기준!D82="","",물량원가기준!D82*H82) | S82: =E82*F82 -> 1693620000 | T82: =물량원가기준!I82+IF(B82>=설정!$B$6,I82*(설정!$B$18-설정!$B$13),0) -> 95120 | U82: =IF(OR(COUNT(물량원가기준!E82:J82)<>6,COUNTIFS(물량원가기준!$A$6:$A$100,A82)<>1),0,1) -> 1
A83: =물량원가기준!A83 -> 2028-04|A-c | B83: =물량원가기준!B83 -> 46844 | C83: =물량원가기준!C83 -> A-c | D83: =물량원가기준!E83 -> 5762 | E83: =물량원가기준!F83 -> 5762 | F83: =물량원가기준!G83 -> 230000 | G83: =SUM(물량원가기준!H83:J83) -> 202000 | H83: =F83-G83 -> 28000 | I83: =부품모델매핑!D8 -> 0 | J83: =IF(ISNUMBER(물량원가기준!F83),E83*I83,"미산출") -> 0 | K83: =D83*H83 -> 161336000 | L83: =E83*H83 -> 161336000 | M83: =L83-K83 -> 0 | N83: =IF(AND(B83>=설정!$B$6,B83<설정!$B$23),1,0) -> 1 | O83: =IF(AND(B83>=설정!$B$6,B83<설정!$B$24),1,0) -> 0 | P83: =IF(B83>=설정!$B$6,J83*(설정!$B$18-설정!$B$13),0) -> 0 | Q83: =L83-P83 -> 161336000 | R83: =IF(물량원가기준!D83="","",물량원가기준!D83*H83) | S83: =E83*F83 -> 1325260000 | T83: =물량원가기준!I83+IF(B83>=설정!$B$6,I83*(설정!$B$18-설정!$B$13),0) -> 60000 | U83: =IF(OR(COUNT(물량원가기준!E83:J83)<>6,COUNTIFS(물량원가기준!$A$6:$A$100,A83)<>1),0,1) -> 1
A84: =물량원가기준!A84 -> 2028-04|A-d | B84: =물량원가기준!B84 -> 46844 | C84: =물량원가기준!C84 -> A-d | D84: =물량원가기준!E84 -> 4899 | E84: =물량원가기준!F84 -> 4899 | F84: =물량원가기준!G84 -> 210000 | G84: =SUM(물량원가기준!H84:J84) -> 185000 | H84: =F84-G84 -> 25000 | I84: =부품모델매핑!D9 -> 0 | J84: =IF(ISNUMBER(물량원가기준!F84),E84*I84,"미산출") -> 0 | K84: =D84*H84 -> 122475000 | L84: =E84*H84 -> 122475000 | M84: =L84-K84 -> 0 | N84: =IF(AND(B84>=설정!$B$6,B84<설정!$B$23),1,0) -> 1 | O84: =IF(AND(B84>=설정!$B$6,B84<설정!$B$24),1,0) -> 0 | P84: =IF(B84>=설정!$B$6,J84*(설정!$B$18-설정!$B$13),0) -> 0 | Q84: =L84-P84 -> 122475000 | R84: =IF(물량원가기준!D84="","",물량원가기준!D84*H84) | S84: =E84*F84 -> 1028790000 | T84: =물량원가기준!I84+IF(B84>=설정!$B$6,I84*(설정!$B$18-설정!$B$13),0) -> 65000 | U84: =IF(OR(COUNT(물량원가기준!E84:J84)<>6,COUNTIFS(물량원가기준!$A$6:$A$100,A84)<>1),0,1) -> 1
A85: =물량원가기준!A85 -> 2028-04|A-e | B85: =물량원가기준!B85 -> 46844 | C85: =물량원가기준!C85 -> A-e | D85: =물량원가기준!E85 -> 2881 | E85: =물량원가기준!F85 -> 2881 | F85: =물량원가기준!G85 -> 150000 | G85: =SUM(물량원가기준!H85:J85) -> 132000 | H85: =F85-G85 -> 18000 | I85: =부품모델매핑!D10 -> 0 | J85: =IF(ISNUMBER(물량원가기준!F85),E85*I85,"미산출") -> 0 | K85: =D85*H85 -> 51858000 | L85: =E85*H85 -> 51858000 | M85: =L85-K85 -> 0 | N85: =IF(AND(B85>=설정!$B$6,B85<설정!$B$23),1,0) -> 1 | O85: =IF(AND(B85>=설정!$B$6,B85<설정!$B$24),1,0) -> 0 | P85: =IF(B85>=설정!$B$6,J85*(설정!$B$18-설정!$B$13),0) -> 0 | Q85: =L85-P85 -> 51858000 | R85: =IF(물량원가기준!D85="","",물량원가기준!D85*H85) | S85: =E85*F85 -> 432150000 | T85: =물량원가기준!I85+IF(B85>=설정!$B$6,I85*(설정!$B$18-설정!$B$13),0) -> 50000 | U85: =IF(OR(COUNT(물량원가기준!E85:J85)<>6,COUNTIFS(물량원가기준!$A$6:$A$100,A85)<>1),0,1) -> 1
A86: =물량원가기준!A86 -> 2028-05|A-a | B86: =물량원가기준!B86 -> 46874 | C86: =물량원가기준!C86 -> A-a | D86: =물량원가기준!E86 -> 3650 | E86: =물량원가기준!F86 -> 3650 | F86: =물량원가기준!G86 -> 300000 | G86: =SUM(물량원가기준!H86:J86) -> 270000 | H86: =F86-G86 -> 30000 | I86: =부품모델매핑!D6 -> 1 | J86: =IF(ISNUMBER(물량원가기준!F86),E86*I86,"미산출") -> 3650 | K86: =D86*H86 -> 109500000 | L86: =E86*H86 -> 109500000 | M86: =L86-K86 -> 0 | N86: =IF(AND(B86>=설정!$B$6,B86<설정!$B$23),1,0) -> 1 | O86: =IF(AND(B86>=설정!$B$6,B86<설정!$B$24),1,0) -> 0 | P86: =IF(B86>=설정!$B$6,J86*(설정!$B$18-설정!$B$13),0) -> 438000 | Q86: =L86-P86 -> 109062000 | R86: =IF(물량원가기준!D86="","",물량원가기준!D86*H86) | S86: =E86*F86 -> 1095000000 | T86: =물량원가기준!I86+IF(B86>=설정!$B$6,I86*(설정!$B$18-설정!$B$13),0) -> 75120 | U86: =IF(OR(COUNT(물량원가기준!E86:J86)<>6,COUNTIFS(물량원가기준!$A$6:$A$100,A86)<>1),0,1) -> 1
A87: =물량원가기준!A87 -> 2028-05|A-b | B87: =물량원가기준!B87 -> 46874 | C87: =물량원가기준!C87 -> A-b | D87: =물량원가기준!E87 -> 9126 | E87: =물량원가기준!F87 -> 9126 | F87: =물량원가기준!G87 -> 180000 | G87: =SUM(물량원가기준!H87:J87) -> 160000 | H87: =F87-G87 -> 20000 | I87: =부품모델매핑!D7 -> 1 | J87: =IF(ISNUMBER(물량원가기준!F87),E87*I87,"미산출") -> 9126 | K87: =D87*H87 -> 182520000 | L87: =E87*H87 -> 182520000 | M87: =L87-K87 -> 0 | N87: =IF(AND(B87>=설정!$B$6,B87<설정!$B$23),1,0) -> 1 | O87: =IF(AND(B87>=설정!$B$6,B87<설정!$B$24),1,0) -> 0 | P87: =IF(B87>=설정!$B$6,J87*(설정!$B$18-설정!$B$13),0) -> 1095120 | Q87: =L87-P87 -> 181424880 | R87: =IF(물량원가기준!D87="","",물량원가기준!D87*H87) | S87: =E87*F87 -> 1642680000 | T87: =물량원가기준!I87+IF(B87>=설정!$B$6,I87*(설정!$B$18-설정!$B$13),0) -> 95120 | U87: =IF(OR(COUNT(물량원가기준!E87:J87)<>6,COUNTIFS(물량원가기준!$A$6:$A$100,A87)<>1),0,1) -> 1
A88: =물량원가기준!A88 -> 2028-05|A-c | B88: =물량원가기준!B88 -> 46874 | C88: =물량원가기준!C88 -> A-c | D88: =물량원가기준!E88 -> 5646 | E88: =물량원가기준!F88 -> 5646 | F88: =물량원가기준!G88 -> 230000 | G88: =SUM(물량원가기준!H88:J88) -> 202000 | H88: =F88-G88 -> 28000 | I88: =부품모델매핑!D8 -> 0 | J88: =IF(ISNUMBER(물량원가기준!F88),E88*I88,"미산출") -> 0 | K88: =D88*H88 -> 158088000 | L88: =E88*H88 -> 158088000 | M88: =L88-K88 -> 0 | N88: =IF(AND(B88>=설정!$B$6,B88<설정!$B$23),1,0) -> 1 | O88: =IF(AND(B88>=설정!$B$6,B88<설정!$B$24),1,0) -> 0 | P88: =IF(B88>=설정!$B$6,J88*(설정!$B$18-설정!$B$13),0) -> 0 | Q88: =L88-P88 -> 158088000 | R88: =IF(물량원가기준!D88="","",물량원가기준!D88*H88) | S88: =E88*F88 -> 1298580000 | T88: =물량원가기준!I88+IF(B88>=설정!$B$6,I88*(설정!$B$18-설정!$B$13),0) -> 60000 | U88: =IF(OR(COUNT(물량원가기준!E88:J88)<>6,COUNTIFS(물량원가기준!$A$6:$A$100,A88)<>1),0,1) -> 1
A89: =물량원가기준!A89 -> 2028-05|A-d | B89: =물량원가기준!B89 -> 46874 | C89: =물량원가기준!C89 -> A-d | D89: =물량원가기준!E89 -> 4801 | E89: =물량원가기준!F89 -> 4801 | F89: =물량원가기준!G89 -> 210000 | G89: =SUM(물량원가기준!H89:J89) -> 185000 | H89: =F89-G89 -> 25000 | I89: =부품모델매핑!D9 -> 0 | J89: =IF(ISNUMBER(물량원가기준!F89),E89*I89,"미산출") -> 0 | K89: =D89*H89 -> 120025000 | L89: =E89*H89 -> 120025000 | M89: =L89-K89 -> 0 | N89: =IF(AND(B89>=설정!$B$6,B89<설정!$B$23),1,0) -> 1 | O89: =IF(AND(B89>=설정!$B$6,B89<설정!$B$24),1,0) -> 0 | P89: =IF(B89>=설정!$B$6,J89*(설정!$B$18-설정!$B$13),0) -> 0 | Q89: =L89-P89 -> 120025000 | R89: =IF(물량원가기준!D89="","",물량원가기준!D89*H89) | S89: =E89*F89 -> 1008210000 | T89: =물량원가기준!I89+IF(B89>=설정!$B$6,I89*(설정!$B$18-설정!$B$13),0) -> 65000 | U89: =IF(OR(COUNT(물량원가기준!E89:J89)<>6,COUNTIFS(물량원가기준!$A$6:$A$100,A89)<>1),0,1) -> 1
A90: =물량원가기준!A90 -> 2028-05|A-e | B90: =물량원가기준!B90 -> 46874 | C90: =물량원가기준!C90 -> A-e | D90: =물량원가기준!E90 -> 2824 | E90: =물량원가기준!F90 -> 2824 | F90: =물량원가기준!G90 -> 150000 | G90: =SUM(물량원가기준!H90:J90) -> 132000 | H90: =F90-G90 -> 18000 | I90: =부품모델매핑!D10 -> 0 | J90: =IF(ISNUMBER(물량원가기준!F90),E90*I90,"미산출") -> 0 | K90: =D90*H90 -> 50832000 | L90: =E90*H90 -> 50832000 | M90: =L90-K90 -> 0 | N90: =IF(AND(B90>=설정!$B$6,B90<설정!$B$23),1,0) -> 1 | O90: =IF(AND(B90>=설정!$B$6,B90<설정!$B$24),1,0) -> 0 | P90: =IF(B90>=설정!$B$6,J90*(설정!$B$18-설정!$B$13),0) -> 0 | Q90: =L90-P90 -> 50832000 | R90: =IF(물량원가기준!D90="","",물량원가기준!D90*H90) | S90: =E90*F90 -> 423600000 | T90: =물량원가기준!I90+IF(B90>=설정!$B$6,I90*(설정!$B$18-설정!$B$13),0) -> 50000 | U90: =IF(OR(COUNT(물량원가기준!E90:J90)<>6,COUNTIFS(물량원가기준!$A$6:$A$100,A90)<>1),0,1) -> 1
A91: =물량원가기준!A91 -> 2028-06|A-a | B91: =물량원가기준!B91 -> 46905 | C91: =물량원가기준!C91 -> A-a | D91: =물량원가기준!E91 -> 3686 | E91: =물량원가기준!F91 -> 3686 | F91: =물량원가기준!G91 -> 300000 | G91: =SUM(물량원가기준!H91:J91) -> 270000 | H91: =F91-G91 -> 30000 | I91: =부품모델매핑!D6 -> 1 | J91: =IF(ISNUMBER(물량원가기준!F91),E91*I91,"미산출") -> 3686 | K91: =D91*H91 -> 110580000 | L91: =E91*H91 -> 110580000 | M91: =L91-K91 -> 0 | N91: =IF(AND(B91>=설정!$B$6,B91<설정!$B$23),1,0) -> 1 | O91: =IF(AND(B91>=설정!$B$6,B91<설정!$B$24),1,0) -> 0 | P91: =IF(B91>=설정!$B$6,J91*(설정!$B$18-설정!$B$13),0) -> 442320 | Q91: =L91-P91 -> 110137680 | R91: =IF(물량원가기준!D91="","",물량원가기준!D91*H91) | S91: =E91*F91 -> 1105800000 | T91: =물량원가기준!I91+IF(B91>=설정!$B$6,I91*(설정!$B$18-설정!$B$13),0) -> 75120 | U91: =IF(OR(COUNT(물량원가기준!E91:J91)<>6,COUNTIFS(물량원가기준!$A$6:$A$100,A91)<>1),0,1) -> 1
A92: =물량원가기준!A92 -> 2028-06|A-b | B92: =물량원가기준!B92 -> 46905 | C92: =물량원가기준!C92 -> A-b | D92: =물량원가기준!E92 -> 9215 | E92: =물량원가기준!F92 -> 9215 | F92: =물량원가기준!G92 -> 180000 | G92: =SUM(물량원가기준!H92:J92) -> 160000 | H92: =F92-G92 -> 20000 | I92: =부품모델매핑!D7 -> 1 | J92: =IF(ISNUMBER(물량원가기준!F92),E92*I92,"미산출") -> 9215 | K92: =D92*H92 -> 184300000 | L92: =E92*H92 -> 184300000 | M92: =L92-K92 -> 0 | N92: =IF(AND(B92>=설정!$B$6,B92<설정!$B$23),1,0) -> 1 | O92: =IF(AND(B92>=설정!$B$6,B92<설정!$B$24),1,0) -> 0 | P92: =IF(B92>=설정!$B$6,J92*(설정!$B$18-설정!$B$13),0) -> 1105800 | Q92: =L92-P92 -> 183194200 | R92: =IF(물량원가기준!D92="","",물량원가기준!D92*H92) | S92: =E92*F92 -> 1658700000 | T92: =물량원가기준!I92+IF(B92>=설정!$B$6,I92*(설정!$B$18-설정!$B$13),0) -> 95120 | U92: =IF(OR(COUNT(물량원가기준!E92:J92)<>6,COUNTIFS(물량원가기준!$A$6:$A$100,A92)<>1),0,1) -> 1
A93: =물량원가기준!A93 -> 2028-06|A-c | B93: =물량원가기준!B93 -> 46905 | C93: =물량원가기준!C93 -> A-c | D93: =물량원가기준!E93 -> 5762 | E93: =물량원가기준!F93 -> 5762 | F93: =물량원가기준!G93 -> 230000 | G93: =SUM(물량원가기준!H93:J93) -> 202000 | H93: =F93-G93 -> 28000 | I93: =부품모델매핑!D8 -> 0 | J93: =IF(ISNUMBER(물량원가기준!F93),E93*I93,"미산출") -> 0 | K93: =D93*H93 -> 161336000 | L93: =E93*H93 -> 161336000 | M93: =L93-K93 -> 0 | N93: =IF(AND(B93>=설정!$B$6,B93<설정!$B$23),1,0) -> 1 | O93: =IF(AND(B93>=설정!$B$6,B93<설정!$B$24),1,0) -> 0 | P93: =IF(B93>=설정!$B$6,J93*(설정!$B$18-설정!$B$13),0) -> 0 | Q93: =L93-P93 -> 161336000 | R93: =IF(물량원가기준!D93="","",물량원가기준!D93*H93) | S93: =E93*F93 -> 1325260000 | T93: =물량원가기준!I93+IF(B93>=설정!$B$6,I93*(설정!$B$18-설정!$B$13),0) -> 60000 | U93: =IF(OR(COUNT(물량원가기준!E93:J93)<>6,COUNTIFS(물량원가기준!$A$6:$A$100,A93)<>1),0,1) -> 1
A94: =물량원가기준!A94 -> 2028-06|A-d | B94: =물량원가기준!B94 -> 46905 | C94: =물량원가기준!C94 -> A-d | D94: =물량원가기준!E94 -> 4899 | E94: =물량원가기준!F94 -> 4899 | F94: =물량원가기준!G94 -> 210000 | G94: =SUM(물량원가기준!H94:J94) -> 185000 | H94: =F94-G94 -> 25000 | I94: =부품모델매핑!D9 -> 0 | J94: =IF(ISNUMBER(물량원가기준!F94),E94*I94,"미산출") -> 0 | K94: =D94*H94 -> 122475000 | L94: =E94*H94 -> 122475000 | M94: =L94-K94 -> 0 | N94: =IF(AND(B94>=설정!$B$6,B94<설정!$B$23),1,0) -> 1 | O94: =IF(AND(B94>=설정!$B$6,B94<설정!$B$24),1,0) -> 0 | P94: =IF(B94>=설정!$B$6,J94*(설정!$B$18-설정!$B$13),0) -> 0 | Q94: =L94-P94 -> 122475000 | R94: =IF(물량원가기준!D94="","",물량원가기준!D94*H94) | S94: =E94*F94 -> 1028790000 | T94: =물량원가기준!I94+IF(B94>=설정!$B$6,I94*(설정!$B$18-설정!$B$13),0) -> 65000 | U94: =IF(OR(COUNT(물량원가기준!E94:J94)<>6,COUNTIFS(물량원가기준!$A$6:$A$100,A94)<>1),0,1) -> 1
A95: =물량원가기준!A95 -> 2028-06|A-e | B95: =물량원가기준!B95 -> 46905 | C95: =물량원가기준!C95 -> A-e | D95: =물량원가기준!E95 -> 2881 | E95: =물량원가기준!F95 -> 2881 | F95: =물량원가기준!G95 -> 150000 | G95: =SUM(물량원가기준!H95:J95) -> 132000 | H95: =F95-G95 -> 18000 | I95: =부품모델매핑!D10 -> 0 | J95: =IF(ISNUMBER(물량원가기준!F95),E95*I95,"미산출") -> 0 | K95: =D95*H95 -> 51858000 | L95: =E95*H95 -> 51858000 | M95: =L95-K95 -> 0 | N95: =IF(AND(B95>=설정!$B$6,B95<설정!$B$23),1,0) -> 1 | O95: =IF(AND(B95>=설정!$B$6,B95<설정!$B$24),1,0) -> 0 | P95: =IF(B95>=설정!$B$6,J95*(설정!$B$18-설정!$B$13),0) -> 0 | Q95: =L95-P95 -> 51858000 | R95: =IF(물량원가기준!D95="","",물량원가기준!D95*H95) | S95: =E95*F95 -> 432150000 | T95: =물량원가기준!I95+IF(B95>=설정!$B$6,I95*(설정!$B$18-설정!$B$13),0) -> 50000 | U95: =IF(OR(COUNT(물량원가기준!E95:J95)<>6,COUNTIFS(물량원가기준!$A$6:$A$100,A95)<>1),0,1) -> 1
A96: =물량원가기준!A96 -> 2028-07|A-a | B96: =물량원가기준!B96 -> 46935 | C96: =물량원가기준!C96 -> A-a | D96: =물량원가기준!E96 -> 3686 | E96: =물량원가기준!F96 -> 3686 | F96: =물량원가기준!G96 -> 300000 | G96: =SUM(물량원가기준!H96:J96) -> 270000 | H96: =F96-G96 -> 30000 | I96: =부품모델매핑!D6 -> 1 | J96: =IF(ISNUMBER(물량원가기준!F96),E96*I96,"미산출") -> 3686 | K96: =D96*H96 -> 110580000 | L96: =E96*H96 -> 110580000 | M96: =L96-K96 -> 0 | N96: =IF(AND(B96>=설정!$B$6,B96<설정!$B$23),1,0) -> 0 | O96: =IF(AND(B96>=설정!$B$6,B96<설정!$B$24),1,0) -> 0 | P96: =IF(B96>=설정!$B$6,J96*(설정!$B$18-설정!$B$13),0) -> 442320 | Q96: =L96-P96 -> 110137680 | R96: =IF(물량원가기준!D96="","",물량원가기준!D96*H96) | S96: =E96*F96 -> 1105800000 | T96: =물량원가기준!I96+IF(B96>=설정!$B$6,I96*(설정!$B$18-설정!$B$13),0) -> 75120 | U96: =IF(OR(COUNT(물량원가기준!E96:J96)<>6,COUNTIFS(물량원가기준!$A$6:$A$100,A96)<>1),0,1) -> 1
A97: =물량원가기준!A97 -> 2028-07|A-b | B97: =물량원가기준!B97 -> 46935 | C97: =물량원가기준!C97 -> A-b | D97: =물량원가기준!E97 -> 9215 | E97: =물량원가기준!F97 -> 9215 | F97: =물량원가기준!G97 -> 180000 | G97: =SUM(물량원가기준!H97:J97) -> 160000 | H97: =F97-G97 -> 20000 | I97: =부품모델매핑!D7 -> 1 | J97: =IF(ISNUMBER(물량원가기준!F97),E97*I97,"미산출") -> 9215 | K97: =D97*H97 -> 184300000 | L97: =E97*H97 -> 184300000 | M97: =L97-K97 -> 0 | N97: =IF(AND(B97>=설정!$B$6,B97<설정!$B$23),1,0) -> 0 | O97: =IF(AND(B97>=설정!$B$6,B97<설정!$B$24),1,0) -> 0 | P97: =IF(B97>=설정!$B$6,J97*(설정!$B$18-설정!$B$13),0) -> 1105800 | Q97: =L97-P97 -> 183194200 | R97: =IF(물량원가기준!D97="","",물량원가기준!D97*H97) | S97: =E97*F97 -> 1658700000 | T97: =물량원가기준!I97+IF(B97>=설정!$B$6,I97*(설정!$B$18-설정!$B$13),0) -> 95120 | U97: =IF(OR(COUNT(물량원가기준!E97:J97)<>6,COUNTIFS(물량원가기준!$A$6:$A$100,A97)<>1),0,1) -> 1
A98: =물량원가기준!A98 -> 2028-07|A-c | B98: =물량원가기준!B98 -> 46935 | C98: =물량원가기준!C98 -> A-c | D98: =물량원가기준!E98 -> 5762 | E98: =물량원가기준!F98 -> 5762 | F98: =물량원가기준!G98 -> 230000 | G98: =SUM(물량원가기준!H98:J98) -> 202000 | H98: =F98-G98 -> 28000 | I98: =부품모델매핑!D8 -> 0 | J98: =IF(ISNUMBER(물량원가기준!F98),E98*I98,"미산출") -> 0 | K98: =D98*H98 -> 161336000 | L98: =E98*H98 -> 161336000 | M98: =L98-K98 -> 0 | N98: =IF(AND(B98>=설정!$B$6,B98<설정!$B$23),1,0) -> 0 | O98: =IF(AND(B98>=설정!$B$6,B98<설정!$B$24),1,0) -> 0 | P98: =IF(B98>=설정!$B$6,J98*(설정!$B$18-설정!$B$13),0) -> 0 | Q98: =L98-P98 -> 161336000 | R98: =IF(물량원가기준!D98="","",물량원가기준!D98*H98) | S98: =E98*F98 -> 1325260000 | T98: =물량원가기준!I98+IF(B98>=설정!$B$6,I98*(설정!$B$18-설정!$B$13),0) -> 60000 | U98: =IF(OR(COUNT(물량원가기준!E98:J98)<>6,COUNTIFS(물량원가기준!$A$6:$A$100,A98)<>1),0,1) -> 1
A99: =물량원가기준!A99 -> 2028-07|A-d | B99: =물량원가기준!B99 -> 46935 | C99: =물량원가기준!C99 -> A-d | D99: =물량원가기준!E99 -> 4899 | E99: =물량원가기준!F99 -> 4899 | F99: =물량원가기준!G99 -> 210000 | G99: =SUM(물량원가기준!H99:J99) -> 185000 | H99: =F99-G99 -> 25000 | I99: =부품모델매핑!D9 -> 0 | J99: =IF(ISNUMBER(물량원가기준!F99),E99*I99,"미산출") -> 0 | K99: =D99*H99 -> 122475000 | L99: =E99*H99 -> 122475000 | M99: =L99-K99 -> 0 | N99: =IF(AND(B99>=설정!$B$6,B99<설정!$B$23),1,0) -> 0 | O99: =IF(AND(B99>=설정!$B$6,B99<설정!$B$24),1,0) -> 0 | P99: =IF(B99>=설정!$B$6,J99*(설정!$B$18-설정!$B$13),0) -> 0 | Q99: =L99-P99 -> 122475000 | R99: =IF(물량원가기준!D99="","",물량원가기준!D99*H99) | S99: =E99*F99 -> 1028790000 | T99: =물량원가기준!I99+IF(B99>=설정!$B$6,I99*(설정!$B$18-설정!$B$13),0) -> 65000 | U99: =IF(OR(COUNT(물량원가기준!E99:J99)<>6,COUNTIFS(물량원가기준!$A$6:$A$100,A99)<>1),0,1) -> 1
A100: =물량원가기준!A100 -> 2028-07|A-e | B100: =물량원가기준!B100 -> 46935 | C100: =물량원가기준!C100 -> A-e | D100: =물량원가기준!E100 -> 2881 | E100: =물량원가기준!F100 -> 2881 | F100: =물량원가기준!G100 -> 150000 | G100: =SUM(물량원가기준!H100:J100) -> 132000 | H100: =F100-G100 -> 18000 | I100: =부품모델매핑!D10 -> 0 | J100: =IF(ISNUMBER(물량원가기준!F100),E100*I100,"미산출") -> 0 | K100: =D100*H100 -> 51858000 | L100: =E100*H100 -> 51858000 | M100: =L100-K100 -> 0 | N100: =IF(AND(B100>=설정!$B$6,B100<설정!$B$23),1,0) -> 0 | O100: =IF(AND(B100>=설정!$B$6,B100<설정!$B$24),1,0) -> 0 | P100: =IF(B100>=설정!$B$6,J100*(설정!$B$18-설정!$B$13),0) -> 0 | Q100: =L100-P100 -> 51858000 | R100: =IF(물량원가기준!D100="","",물량원가기준!D100*H100) | S100: =E100*F100 -> 432150000 | T100: =물량원가기준!I100+IF(B100>=설정!$B$6,I100*(설정!$B$18-설정!$B$13),0) -> 50000 | U100: =IF(OR(COUNT(물량원가기준!E100:J100)<>6,COUNTIFS(물량원가기준!$A$6:$A$100,A100)<>1),0,1) -> 1

Sheet 물량원가기준
A1: 2027 기준 및 2028 내부가정
A3: 출처: INNONOW_SC01_통합가상데이터설계_v0.1.xlsx 손익계산·단위원가. 2027 값 보존. 수량은 당사 배정 대분이며 40%를 재적용하지 않습니다.
A5: row_key | B5: period | C5: model_id | D5: T01_qty | E5: F01_qty | F5: F02_qty | G5: 판매단가 | H5: 재료비 | I5: 기존외주비 | J5: 변동가공비 | K5: 실적수량 | L5: 기간성격 | M5: source_ref | N5: 확실성
A6: 2027-01|A-a | B6: 46388 | C6: A-a | D6: 4080 | E6: 4080 | F6: 4080 | G6: 300000 | H6: 175000 | I6: 75000 | J6: 20000 | K6: 4080 | L6: 확정실적 포함 | M6: SC01 v0.1 / F01·F02·C01 | N6: 내부전망 또는 실적
A7: 2027-01|A-b | B7: 46388 | C7: A-b | D7: 10200 | E7: 10200 | F7: 10200 | G7: 180000 | H7: 55000 | I7: 95000 | J7: 10000 | K7: 10200 | L7: 확정실적 포함 | M7: SC01 v0.1 / F01·F02·C01 | N7: 내부전망 또는 실적
A8: 2027-01|A-c | B8: 46388 | C8: A-c | D8: 6120 | E8: 6059 | F8: 6059 | G8: 230000 | H8: 125000 | I8: 60000 | J8: 17000 | K8: 6059 | L8: 확정실적 포함 | M8: SC01 v0.1 / F01·F02·C01 | N8: 내부전망 또는 실적
A9: 2027-01|A-d | B9: 46388 | C9: A-d | D9: 5100 | E9: 5151 | F9: 5151 | G9: 210000 | H9: 105000 | I9: 65000 | J9: 15000 | K9: 5151 | L9: 확정실적 포함 | M9: SC01 v0.1 / F01·F02·C01 | N9: 내부전망 또는 실적
A10: 2027-01|A-e | B10: 46388 | C10: A-e | D10: 3060 | E10: 3029 | F10: 3029 | G10: 150000 | H10: 70000 | I10: 50000 | J10: 12000 | K10: 3029 | L10: 확정실적 포함 | M10: SC01 v0.1 / F01·F02·C01 | N10: 내부전망 또는 실적
A11: 2027-02|A-a | B11: 46419 | C11: A-a | D11: 3600 | E11: 3564 | F11: 3564 | G11: 300000 | H11: 175000 | I11: 75000 | J11: 20000 | K11: 3564 | L11: 확정실적 포함 | M11: SC01 v0.1 / F01·F02·C01 | N11: 내부전망 또는 실적
A12: 2027-02|A-b | B12: 46419 | C12: A-b | D12: 9000 | E12: 8910 | F12: 8910 | G12: 180000 | H12: 55000 | I12: 95000 | J12: 10000 | K12: 8910 | L12: 확정실적 포함 | M12: SC01 v0.1 / F01·F02·C01 | N12: 내부전망 또는 실적
A13: 2027-02|A-c | B13: 46419 | C13: A-c | D13: 5400 | E13: 5346 | F13: 5346 | G13: 230000 | H13: 125000 | I13: 60000 | J13: 17000 | K13: 5346 | L13: 확정실적 포함 | M13: SC01 v0.1 / F01·F02·C01 | N13: 내부전망 또는 실적
A14: 2027-02|A-d | B14: 46419 | C14: A-d | D14: 4500 | E14: 4545 | F14: 4545 | G14: 210000 | H14: 105000 | I14: 65000 | J14: 15000 | K14: 4545 | L14: 확정실적 포함 | M14: SC01 v0.1 / F01·F02·C01 | N14: 내부전망 또는 실적
A15: 2027-02|A-e | B15: 46419 | C15: A-e | D15: 2700 | E15: 2673 | F15: 2673 | G15: 150000 | H15: 70000 | I15: 50000 | J15: 12000 | K15: 2673 | L15: 확정실적 포함 | M15: SC01 v0.1 / F01·F02·C01 | N15: 내부전망 또는 실적
A16: 2027-03|A-a | B16: 46447 | C16: A-a | D16: 4200 | E16: 4116 | F16: 4116 | G16: 300000 | H16: 175000 | I16: 75000 | J16: 20000 | K16: 4116 | L16: 확정실적 포함 | M16: SC01 v0.1 / F01·F02·C01 | N16: 내부전망 또는 실적
A17: 2027-03|A-b | B17: 46447 | C17: A-b | D17: 10500 | E17: 10290 | F17: 10290 | G17: 180000 | H17: 55000 | I17: 95000 | J17: 10000 | K17: 10290 | L17: 확정실적 포함 | M17: SC01 v0.1 / F01·F02·C01 | N17: 내부전망 또는 실적
... A35: 2027-06|A-e | B35: 46539 | C35: A-e | D35: 3000 | E35: 2970 | F35: 2970 | G35: 150000 | H35: 70000 | I35: 50000 | J35: 12000 | K35: 1336 | L35: 6/15 실적+잔여전망 | M35: SC01 v0.1 / F01·F02·C01 | N35: 내부전망 또는 실적
A36: 2027-07|A-a | B36: 46569 | C36: A-a | D36: 4000 | E36: 3800 | F36: 3800 | G36: 300000 | H36: 175000 | I36: 75000 | J36: 20000 | L36: 미래전망 | M36: SC01 v0.1 / F01·F02·C01 | N36: CP02 확인물량
A37: 2027-07|A-b | B37: 46569 | C37: A-b | D37: 10000 | E37: 9500 | F37: 8800 | G37: 180000 | H37: 55000 | I37: 95000 | J37: 10000 | L37: 미래전망 | M37: SC01 v0.1 / F01·F02·C01 | N37: CP02 확인물량
A38: 2027-07|A-c | B38: 46569 | C38: A-c | D38: 6000 | E38: 5940 | F38: 5940 | G38: 230000 | H38: 125000 | I38: 60000 | J38: 17000 | L38: 미래전망 | M38: SC01 v0.1 / F01·F02·C01 | N38: CP02 확인물량
A39: 2027-07|A-d | B39: 46569 | C39: A-d | D39: 5000 | E39: 5050 | F39: 5050 | G39: 210000 | H39: 105000 | I39: 65000 | J39: 15000 | L39: 미래전망 | M39: SC01 v0.1 / F01·F02·C01 | N39: CP02 확인물량
A40: 2027-07|A-e | B40: 46569 | C40: A-e | D40: 3000 | E40: 2970 | F40: 2970 | G40: 150000 | H40: 70000 | I40: 50000 | J40: 12000 | L40: 미래전망 | M40: SC01 v0.1 / F01·F02·C01 | N40: CP02 확인물량
A41: 2027-08|A-a | B41: 46600 | C41: A-a | D41: 3680 | E41: 3496 | F41: 3496 | G41: 300000 | H41: 175000 | I41: 75000 | J41: 20000 | L41: 미래전망 | M41: SC01 v0.1 / F01·F02·C01 | N41: CP02 확인물량
A42: 2027-08|A-b | B42: 46600 | C42: A-b | D42: 9200 | E42: 8740 | F42: 8740 | G42: 180000 | H42: 55000 | I42: 95000 | J42: 10000 | L42: 미래전망 | M42: SC01 v0.1 / F01·F02·C01 | N42: CP02 확인물량
A43: 2027-08|A-c | B43: 46600 | C43: A-c | D43: 5520 | E43: 5465 | F43: 5465 | G43: 230000 | H43: 125000 | I43: 60000 | J43: 17000 | L43: 미래전망 | M43: SC01 v0.1 / F01·F02·C01 | N43: CP02 확인물량
A44: 2027-08|A-d | B44: 46600 | C44: A-d | D44: 4600 | E44: 4646 | F44: 4646 | G44: 210000 | H44: 105000 | I44: 65000 | J44: 15000 | L44: 미래전망 | M44: SC01 v0.1 / F01·F02·C01 | N44: CP02 확인물량
A45: 2027-08|A-e | B45: 46600 | C45: A-e | D45: 2760 | E45: 2732 | F45: 2732 | G45: 150000 | H45: 70000 | I45: 50000 | J45: 12000 | L45: 미래전망 | M45: SC01 v0.1 / F01·F02·C01 | N45: CP02 확인물량
A46: 2027-09|A-a | B46: 46631 | C46: A-a | D46: 4120 | E46: 3914 | F46: 3914 | G46: 300000 | H46: 175000 | I46: 75000 | J46: 20000 | L46: 미래전망 | M46: SC01 v0.1 / F01·F02·C01 | N46: CP02 확인물량
A47: 2027-09|A-b | B47: 46631 | C47: A-b | D47: 10300 | E47: 9785 | F47: 9785 | G47: 180000 | H47: 55000 | I47: 95000 | J47: 10000 | L47: 미래전망 | M47: SC01 v0.1 / F01·F02·C01 | N47: CP02 확인물량
... A65: 2027-12|A-e | B65: 46722 | C65: A-e | D65: 2850 | E65: 2822 | F65: 2822 | G65: 150000 | H65: 70000 | I65: 50000 | J65: 12000 | L65: 미래전망 | M65: SC01 v0.1 / F01·F02·C01 | N65: 내부전망 또는 실적
A66: 2028-01|A-a | B66: 46753 | C66: A-a | E66: =ROUND(E6*설정!$B$7,0) -> 3958 | F66: =E66 -> 3958 | G66: =G6 -> 300000 | H66: =H6 -> 175000 | I66: =I6 -> 75000 | J66: =J6 -> 20000 | L66: 내부가정·미승인 | M66: EXT28-v1 / C01 유지 | N66: 고객확정 아님
A67: 2028-01|A-b | B67: 46753 | C67: A-b | E67: =ROUND(E7*설정!$B$7,0) -> 9894 | F67: =E67 -> 9894 | G67: =G7 -> 180000 | H67: =H7 -> 55000 | I67: =I7 -> 95000 | J67: =J7 -> 10000 | L67: 내부가정·미승인 | M67: EXT28-v1 / C01 유지 | N67: 고객확정 아님
A68: 2028-01|A-c | B68: 46753 | C68: A-c | E68: =ROUND(E8*설정!$B$7,0) -> 5877 | F68: =E68 -> 5877 | G68: =G8 -> 230000 | H68: =H8 -> 125000 | I68: =I8 -> 60000 | J68: =J8 -> 17000 | L68: 내부가정·미승인 | M68: EXT28-v1 / C01 유지 | N68: 고객확정 아님
A69: 2028-01|A-d | B69: 46753 | C69: A-d | E69: =ROUND(E9*설정!$B$7,0) -> 4996 | F69: =E69 -> 4996 | G69: =G9 -> 210000 | H69: =H9 -> 105000 | I69: =I9 -> 65000 | J69: =J9 -> 15000 | L69: 내부가정·미승인 | M69: EXT28-v1 / C01 유지 | N69: 고객확정 아님
A70: 2028-01|A-e | B70: 46753 | C70: A-e | E70: =ROUND(E10*설정!$B$7,0) -> 2938 | F70: =E70 -> 2938 | G70: =G10 -> 150000 | H70: =H10 -> 70000 | I70: =I10 -> 50000 | J70: =J10 -> 12000 | L70: 내부가정·미승인 | M70: EXT28-v1 / C01 유지 | N70: 고객확정 아님
A71: 2028-02|A-a | B71: 46784 | C71: A-a | E71: =ROUND(E11*설정!$B$7,0) -> 3457 | F71: =E71 -> 3457 | G71: =G11 -> 300000 | H71: =H11 -> 175000 | I71: =I11 -> 75000 | J71: =J11 -> 20000 | L71: 내부가정·미승인 | M71: EXT28-v1 / C01 유지 | N71: 고객확정 아님
A72: 2028-02|A-b | B72: 46784 | C72: A-b | E72: =ROUND(E12*설정!$B$7,0) -> 8643 | F72: =E72 -> 8643 | G72: =G12 -> 180000 | H72: =H12 -> 55000 | I72: =I12 -> 95000 | J72: =J12 -> 10000 | L72: 내부가정·미승인 | M72: EXT28-v1 / C01 유지 | N72: 고객확정 아님
A73: 2028-02|A-c | B73: 46784 | C73: A-c | E73: =ROUND(E13*설정!$B$7,0) -> 5186 | F73: =E73 -> 5186 | G73: =G13 -> 230000 | H73: =H13 -> 125000 | I73: =I13 -> 60000 | J73: =J13 -> 17000 | L73: 내부가정·미승인 | M73: EXT28-v1 / C01 유지 | N73: 고객확정 아님
A74: 2028-02|A-d | B74: 46784 | C74: A-d | E74: =ROUND(E14*설정!$B$7,0) -> 4409 | F74: =E74 -> 4409 | G74: =G14 -> 210000 | H74: =H14 -> 105000 | I74: =I14 -> 65000 | J74: =J14 -> 15000 | L74: 내부가정·미승인 | M74: EXT28-v1 / C01 유지 | N74: 고객확정 아님
A75: 2028-02|A-e | B75: 46784 | C75: A-e | E75: =ROUND(E15*설정!$B$7,0) -> 2593 | F75: =E75 -> 2593 | G75: =G15 -> 150000 | H75: =H15 -> 70000 | I75: =I15 -> 50000 | J75: =J15 -> 12000 | L75: 내부가정·미승인 | M75: EXT28-v1 / C01 유지 | N75: 고객확정 아님
A76: 2028-03|A-a | B76: 46813 | C76: A-a | E76: =ROUND(E16*설정!$B$7,0) -> 3993 | F76: =E76 -> 3993 | G76: =G16 -> 300000 | H76: =H16 -> 175000 | I76: =I16 -> 75000 | J76: =J16 -> 20000 | L76: 내부가정·미승인 | M76: EXT28-v1 / C01 유지 | N76: 고객확정 아님
A77: 2028-03|A-b | B77: 46813 | C77: A-b | E77: =ROUND(E17*설정!$B$7,0) -> 9981 | F77: =E77 -> 9981 | G77: =G17 -> 180000 | H77: =H17 -> 55000 | I77: =I17 -> 95000 | J77: =J17 -> 10000 | L77: 내부가정·미승인 | M77: EXT28-v1 / C01 유지 | N77: 고객확정 아님
... A100: 2028-07|A-e | B100: 46935 | C100: A-e | E100: =ROUND(E40*설정!$B$7,0) -> 2881 | F100: =E100 -> 2881 | G100: =G40 -> 150000 | H100: =H40 -> 70000 | I100: =I40 -> 50000 | J100: =J40 -> 12000 | L100: 내부가정·미승인 | M100: EXT28-v1 / C01 유지 | N100: 고객확정 아님

Sheet 월고정비
A1: 공장 고정비
A3: 울산 A제품 범위. 모델별 고정비 배부는 하지 않으며 공장 합계에서 한 번만 차감합니다.
A5: period | B5: fixed_cost | C5: actual_fixed | D5: source_ref
A6: 46388 | B6: 370000000 | C6: 370000000 | D6: SC01 v0.1 / 고정비
A7: 46419 | B7: 370000000 | C7: 370000000 | D7: SC01 v0.1 / 고정비
A8: 46447 | B8: 370000000 | C8: 370000000 | D8: SC01 v0.1 / 고정비
A9: 46478 | B9: 370000000 | C9: 370000000 | D9: SC01 v0.1 / 고정비
A10: 46508 | B10: 370000000 | C10: 370000000 | D10: SC01 v0.1 / 고정비
A11: 46539 | B11: 370000000 | C11: 185000000 | D11: SC01 v0.1 / 고정비
A12: 46569 | B12: 370000000 | D12: SC01 v0.1 / 고정비
A13: 46600 | B13: 370000000 | D13: SC01 v0.1 / 고정비
A14: 46631 | B14: 370000000 | D14: SC01 v0.1 / 고정비
A15: 46661 | B15: 370000000 | D15: SC01 v0.1 / 고정비
A16: 46692 | B16: 370000000 | D16: SC01 v0.1 / 고정비
A17: 46722 | B17: 370000000 | D17: SC01 v0.1 / 고정비
A18: 46753 | B18: =설정!$B$21 -> 370000000 | D18: 내부가정: 2027 기준 유지
A19: 46784 | B19: =설정!$B$21 -> 370000000 | D19: 내부가정: 2027 기준 유지
A20: 46813 | B20: =설정!$B$21 -> 370000000 | D20: 내부가정: 2027 기준 유지
A21: 46844 | B21: =설정!$B$21 -> 370000000 | D21: 내부가정: 2027 기준 유지
A22: 46874 | B22: =설정!$B$21 -> 370000000 | D22: 내부가정: 2027 기준 유지
A23: 46905 | B23: =설정!$B$21 -> 370000000 | D23: 내부가정: 2027 기준 유지
A24: 46935 | B24: =설정!$B$21 -> 370000000 | D24: 내부가정: 2027 기준 유지

Sheet 부품모델매핑
A1: 공통부품 소요량 및 외주비 구성
A3: P-COM01은 가상의 외주 공통부품입니다. a·b 각1개, c·d·e는 미사용. 기존 단가는 전체 외주비의 일부입니다.
A5: model_id | B5: part_id | C5: supplier_id | D5: 소요량 | E5: 기존부품단가 | F5: 기존외주비 | G5: 잔여외주비 | H5: 산식 및 소속
A6: A-a | B6: P-COM01 | C6: SUP-01 | D6: 1 | E6: =설정!$B$13 -> 2000 | F6: =물량원가기준!I6 -> 75000 | G6: =F6-D6*E6 -> 73000 | H6: C01 외주비 = 기존부품단가×소요량 + 잔여외주비
A7: A-b | B7: P-COM01 | C7: SUP-01 | D7: 1 | E7: =설정!$B$13 -> 2000 | F7: =물량원가기준!I7 -> 95000 | G7: =F7-D7*E7 -> 93000 | H7: C01 외주비 = 기존부품단가×소요량 + 잔여외주비
A8: A-c | B8: P-COM01 | C8: SUP-01 | D8: 0 | E8: =설정!$B$13 -> 2000 | F8: =물량원가기준!I8 -> 60000 | G8: =F8-D8*E8 -> 60000 | H8: C01 외주비 = 기존부품단가×소요량 + 잔여외주비
A9: A-d | B9: P-COM01 | C9: SUP-01 | D9: 0 | E9: =설정!$B$13 -> 2000 | F9: =물량원가기준!I9 -> 65000 | G9: =F9-D9*E9 -> 65000 | H9: C01 외주비 = 기존부품단가×소요량 + 잔여외주비
A10: A-e | B10: P-COM01 | C10: SUP-01 | D10: 0 | E10: =설정!$B$13 -> 2000 | F10: =물량원가기준!I10 -> 50000 | G10: =F10-D10*E10 -> 50000 | H10: C01 외주비 = 기존부품단가×소요량 + 잔여외주비

Sheet 단가버전
A1: 단가안과 분석 버전
A3: 동일 요청의 순차 이력입니다. 요청·협상·기안·승인안을 합산하지 않습니다. 아래는 단계 실행 시 생성할 기대 데이터입니다.
A5: price_version | B5: 종류 | C5: request_id | D5: part_id | E5: old_price | F5: new_price | G5: effective_date | H5: run_id | I5: 생성시연 | J5: 상태
A6: PV-REQ01 | B6: 요청안 | C6: REQ-2706-01 | D6: P-COM01 | E6: =설정!$B$13 -> 2000 | F6: =설정!B14 -> 2200 | G6: =설정!$B$6 -> 46569 | H6: RUN-REQ01 | I6: D01 | J6: 접수·미승인
A7: PV-OFFER01 | B7: 내부제시안 | C7: REQ-2706-01 | D7: P-COM01 | E7: =설정!$B$13 -> 2000 | F7: =설정!B15 -> 2100 | G7: =설정!$B$6 -> 46569 | H7: RUN-OFFER01 | I7: D03 | J7: 내부검토·미합의
A8: PV-NEG01 | B8: 1차협상안 | C8: REQ-2706-01 | D8: P-COM01 | E8: =설정!$B$13 -> 2000 | F8: =설정!B16 -> 2120 | G8: =설정!$B$6 -> 46569 | H8: RUN-NEG01 | I8: D04 | J8: 잠정합의·미승인
A9: PV-PROP01 | B9: 기안안 | C9: REQ-2706-01 | D9: P-COM01 | E9: =설정!$B$13 -> 2000 | F9: =설정!B17 -> 2120 | G9: =설정!$B$6 -> 46569 | H9: RUN-PROP01 | I9: D06 | J9: 승인대기
A10: PV-APP01 | B10: 승인안 | C10: REQ-2706-01 | D10: P-COM01 | E10: =설정!$B$13 -> 2000 | F10: =설정!B18 -> 2120 | G10: =설정!$B$6 -> 46569 | H10: RUN-APP01 | I10: D09 | J10: 승인완료·적용예정

Sheet 업무이력
A1: 시연 단계별 이벤트와 상태
A3: 모든 날짜·사용자 역할은 가상 시연값입니다. 처음에는 D00까지만 적재하고 단계 실행 시 후속 기록을 생성합니다. 기본 경로와 X01은 동시에 실행하지 않습니다.
A5: demo_id | B5: step_id | C5: event_at | D5: actor_role | E5: screen_id | F5: action | G5: state_after | H5: due_at | I5: evidence_id | J5: run_id | K5: 완료조건·주의 | L5: fixture_kind | M5: control_id | N5: 업무단계
A6: D00 | B6: S0 | C6: 2027-06-17 08:50:00 KST | D6: 경영관리 | E6: 공통 | F6: ISSUE-B07 확인 | G6: SC01_REVIEW_PENDING | H6: NONE | I6: NONE | J6: RUN-F02-001 | K6: 장면1 기본 완료·F02 미승인 | L6: 초기
A7: D01 | B7: S01 | C7: 2027-06-17 09:00:00 KST | D7: 구매담당 | E7: U21 | F7: REQ-2706-01 접수 | G7: RECEIVED | H7: 2027-06-18 18:00:00 KST | I7: DOC-REQ01 | J7: NONE | K7: 요청가 확인·승인값 없음 | L7: 실행 | M7: CT21 | N7: 인상 요청 접수
A8: D02 | B8: S02 | C8: 2027-06-17 10:00:00 KST | D8: 구매담당·팀장 | E8: U22 | F8: 구두보고 기록 | G8: PRE_REVIEW | H8: 2027-06-21 18:00:00 KST | I8: NOTE-REPORT01 | J8: NONE | K8: 분석 착수, 별도 전자승인 없음 | L8: 실행 | M8: CT22 | N8: 팀장 보고 및 협의
A9: D03 | B9: S03 | C9: 2027-06-18 11:00:00 KST | D9: 구매담당 | E9: U22 | F9: 요청안 분석·내부 제시안 | G9: NEGOTIATION_READY | H9: =설정!B19 -> 2027-06-21 18:00:00 KST | I9: NOTE-ANALYSIS01 | J9: RUN-REQ01/RUN-OFFER01 | K9: 12개월 증가액·가정 확인 | L9: 실행 | M9: CT23·CT24 | N9: 사전 영향분석
A10: D04 | B10: S04 | C10: 2027-06-21 15:00:00 KST | D10: 구매담당 | E10: U23 | F10: 1차 협상 기록 | G10: TENTATIVE_AGREEMENT | H10: =설정!B19 -> 2027-06-21 18:00:00 KST | I10: NOTE-NEG01 | J10: NONE | K10: 협상가 입력·미승인 | L10: 실행 | M10: CT25 | N10: 1차 협상
A11: D05 | B11: S05 | C11: 2027-06-22 10:00:00 KST | D11: 구매담당 | E11: U22 | F11: 협상안 재분석 | G11: PROPOSAL_READY | H11: 2027-06-23 18:00:00 KST | I11: NOTE-NEG01 | J11: RUN-NEG01 | K11: 최신 버전·조건 일치 확인 | L11: 실행 | M11: CT24·CT26 | N11: 협상안 영향 재분석
A12: D06 | B12: S06 | C12: 2027-06-22 11:00:00 KST | D12: 구매담당 | E12: U24 | F12: PROP01-v1 상신 | G12: TEAM_APPROVAL_PENDING | H12: 2027-06-23 18:00:00 KST | I12: DOC-PROP01 | J12: RUN-PROP01 | K12: 기안 단가2120·협상안 일치 | L12: 실행 | M12: CT26 | N12: 가격인상 보고 기안
A13: D07 | B13: S07 | C13: 2027-06-22 14:00:00 KST | D13: 구매팀장 | E13: U25 | F13: APP-T01 승인 | G13: EXEC_APPROVAL_PENDING | H13: 2027-06-23 18:00:00 KST | I13: APP-T01 | J13: RUN-PROP01 | K13: 동일 PROP01-v1 승인 | L13: 실행 | M13: CT27 | N13: 구매팀장 승인
A14: D08 | B14: S08/S09 | C14: 2027-06-23 10:00:00 KST | D14: 구매임원 | E14: U25 | F14: APP-E01 승인·대표 판정 | G14: CEO_APPROVAL_PENDING | H14: 2027-06-24 18:00:00 KST | I14: APP-E01 | J14: RUN-PROP01 | K14: 최종12개월 구매증가 ≥10백만원 | L14: 실행 | M14: CT27·CT28 / CT28 | N14: 구매임원 승인 / 대표 승인 대상 판단
A15: D09 | B15: S10 | C15: 2027-06-23 14:00:00 KST | D15: 대표 | E15: U25 | F15: APP-C01 승인 | G15: APPROVED | H15: NONE | I15: APP-C01 | J15: RUN-APP01 | K15: 승인 단가 확정·공식 F02 승인 아님 | L15: 실행 | M15: CT27·CT28 | N15: 대표 승인
A16: D10 | B16: S11 | C16: 2027-06-23 15:00:00 KST | D16: 구매담당 | E16: U26 | F16: C02-APP01 원가 등록 | G16: REGISTERED_FUTURE | H16: NONE | I16: REG-C02 | J16: RUN-APP01 | K16: 7/1 적용예정·C01 보존 | L16: 실행 | M16: CT29 | N16: 승인 조건 및 원가 등록
A17: D11 | B17: S12 | C17: 2027-06-23 16:00:00 KST | D17: 구매담당 | E17: U27 | F17: MR-2706-01 검토자료 갱신 | G17: FINANCE_PENDING | H17: 2027-06-24 18:00:00 KST | I17: HANDOFF-01 | J17: RUN-APP01 | K17: 물량·원가 별도 사건 연결 | L17: 실행 | M17: CT30 | N17: 장면 3 검토자료 연결
A18: D12 | B18: S13 | C18: 2027-06-24 10:00:00 KST | D18: 경영관리 | E18: U27 | F18: 수신 확인 | G18: HANDED_OFF | H18: 2027-06-28 18:00:00 KST | I18: ACK-01 | J18: RUN-APP01 | K18: SC02 완료·SC03 분석대기·위험 미해소 | L18: 실행 | M18: CT30 | N18: 경영관리 인수
A19: X01 | B19: S14 | C19: 2027-06-23 10:00:00 KST | D19: 구매임원 | E19: U25 | F19: 추가 협상지시 | G19: NEEDS_RENEGOTIATION | H19: 2027-06-25 18:00:00 KST | I19: INSTR-RENEG01 | J19: RUN-PROP01 | K19: D08 기본승인 대신 분기·C02 생성 금지 | L19: 별도분기 | M19: CT27·CT30 | N19: 추가 협상지시 기록

Sheet 증빙과협상
A1: 화면을 채울 가상 증빙과 협상 내용
A3: 외부 전송·실제 공문 파일이 아닌 데모 본문 데이터입니다. 담당자 검토 후 기록하는 문안이며 Agent는 승인하지 않습니다.
A5: record_id | B5: record_type | C5: request_id | D5: actor | E5: 내용 | F5: 연결·필수항목
A6: DOC-REQ01 | B6: 요청공문 | C6: REQ-2706-01 | D6: SUP-01 가상 정밀부품 | E6: 원재료 및 가공비 상승으로 P-COM01의 공급단가를 2,000원에서 2,200원으로 조정 요청. 2027-07-01 적용 희망. VAT 별도. | F6: REQ-2706-01 / P-COM01 / PV-REQ01
A7: NOTE-REPORT01 | B7: 구두보고 | C7: REQ-2706-01 | D7: 구매담당·구매팀장 | E7: 수요 감소와 원가 상승이 중첩되어 사전 손익분석 후 1차 협상 진행. 내부 제시가 2,100원으로 검토. | F7: 보고일 6/17 10:00 / 보고자·참석자·결론
A8: NOTE-ANALYSIS01 | B8: Agent 요약 초안 | C8: REQ-2706-01 | D8: 구매담당 확인 | E8: a·b에 공통 사용. 요청안은 기존 대비 10% 인상. 2028년 물량은 내부가정으로 향후12개월 금액을 추정하며 물량 감소 사건과 함께 검토 필요. | F8: RUN-REQ01 / 검토자 확인 후 채택
A9: NOTE-NEG01 | B9: 1차 협상 결과 | C9: REQ-2706-01 | D9: 구매담당·공급사 영업담당 | E9: 6/21 협상. 내부 제시 2,100원, 공급사 최종 잠정 2,120원. 적용일 7/1 유지. 내부 승인 전 잠정안임을 확인. | F9: 가격·일자·대상·참석자·회신근거 / 담당자가 협상기한 입력
A10: DOC-PROP01 | B10: 가격인상 기안 | C10: REQ-2706-01 | D10: 구매담당 | E10: 공통부품 단가 2,120원으로 인상 상신. 요청 대비 인상폭을 10%에서 6%로 축소. 품목별 연 구매액 증가를 필수 첨부하고 손익 분석은 참고자료로 연결. | F10: PROP01-v1 / PV-PROP01 / RUN-PROP01
A11: APP-T01 | B11: 팀장 승인 | C11: REQ-2706-01 | D11: ROLE-BUY-LEAD | E11: 요청사유·협상결과·기안 일치 및 물량 가정을 검토하고 승인. | F11: PROP01-v1 / 6/22 14:00
A12: APP-E01 | B12: 임원 승인 | C12: REQ-2706-01 | D12: ROLE-BUY-EXEC | E12: 공급 안정과 잔여 원가 부담을 고려해 승인. 대표 승인 및 경영관리 통합검토 필요. | F12: PROP01-v1 / 6/23 10:00
A13: APP-C01 | B13: 대표 승인 | C13: REQ-2706-01 | D13: ROLE-CEO | E13: 단가 인상안을 승인하고 통합 손익 영향과 후속 개선대책은 장면3에서 검토하도록 함. | F13: PROP01-v1 / 6/23 14:00
A14: INSTR-RENEG01 | B14: 추가 협상지시 | C14: REQ-2706-01 | D14: ROLE-BUY-EXEC | E14: 대체 공급처 견적과 인상 사유 증빙을 확보하여 추가 협상. 구매담당 배정, 협의기한 6/25 18:00. | F14: X01 전용 / 미승인·재협상대기 / 2차 상세 후속범위
A15: BG-REQ02 | B15: 배경 거래 | C15: REQ-BG02 | D15: SUP-02 가상 소재 | E15: A-c용 외주 단가 확인 건. 인상 요청 없음, 기존 계약 유지. | F15: 정상 거래 / 계산범위 제외 / 추가 위험 생성 없음
A16: BG-REQ03 | B16: 배경 거래 | C16: REQ-BG03 | D16: SUP-03 가상 가공 | E16: A-d·A-e 정기 거래 검토 완료. 가격·수량 추가 변경 없음. | F16: 정상 거래 / 계산범위 제외 / 요청건 합산 금지

Sheet 장면3인계
A1: 장면 3 인계 데이터 계약
A3: 동일 상위 검토건에 두 사건을 유지합니다. 아래는 D12 이후 기대 레코드이며 승인 전에는 provisional=true로 별도 구분합니다.
A5: field | B5: value | C5: 정의 및 처리
A6: review_id | B6: MR-2706-01 | C6: 울산 A제품 수익성 통합검토건
A7: quantity_issue_id | B7: ISSUE-B07 | C7: 장면1 기존 물량 감소 이슈 보존
A8: price_issue_id | B8: ISSUE-COST01 | C8: 장면2 가격 인상 신규 이슈
A9: quantity_run_id | B9: RUN-F02-001 | C9: 장면1 추가 물량 감소 -700대분
A10: price_run_id | B10: RUN-APP01 | C10: 선택안은 승인안 한 개만 적용
A11: price_version | B11: =설정!B20 -> PV-APP01 | C11: D09 승인 후 생성. 요청·협상안 중복 합산 금지
A12: cost_version | B12: C02-APP01 | C12: C01+공통부품 인상분. 적용일 2027-07-01
A13: qty_version | B13: F02 + EXT28-v1 | C13: F02 검토중 유지. 2028은 내부가정
A14: year_volume_impact | B14: =통합손익!I21 -> -14000000 | C14: 2027 물량 순영향·원
A15: year_cost_impact | B15: =통합손익!J21 -> -9364320 | C15: 2027 승인안 추가 원가 영향·원
A16: year_combined_profit | B16: =통합손익!K21 -> 3299986680 | C16: 2027 통합 관리손익·원
A17: year_target_gap | B17: =통합손익!N21 -> 177303320 | C17: 2027 Target 대비 부족·원
A18: next12_purchase_increase | B18: =단가안비교!I10 -> 18817440 | C18: 대표 승인과 금액 위험 판단 기준·원
A19: next12_combined_profit | B19: =통합손익!K22 -> 3173163560 | C19: 동일12개월 비교·Target 없음
A20: approval_status | B20: APPROVED | C20: 단가안 승인 상태
A21: risk_status | B21: OPEN | C21: 단가 승인·인계완료가 위험 해소 아님
A22: forecast_status | B22: REVIEW_PENDING | C22: 공식 Forecast·Target 자동 변경 없음
A23: scene_status | B23: SC02_HANDED_OFF / SC03_PENDING | C23: D12 인수 확인 이후
A24: accepted_by_at | B24: ROLE-FIN / 2027-06-24 10:00:00 KST | C24: 실사용자 계정 매핑은 구현명세에서 확정
A25: source_bundle | B25: REQ-2706-01 / PROP01-v1 / HANDOFF-01 | C25: 요청·분석·협상·승인·등록·인수 이력 모두 참조

Sheet 예외데이터
A1: 분기 및 경계 검증 데이터
A3: X02~X05 등은 기본 시드 복제 후 단독 실행합니다. 규칙 fixture는 계산 기준 검증용이며 실제 거래·손익에 합산하지 않습니다.
A5: case_id | B5: 목적 | C5: 변경 입력 | D5: 인상률 | E5: 연구매증가 | F5: 기대 결과 | G5: 처리 기준 | H5: 계산 위험 | I5: 계산 승인선
A6: X01 | B6: 추가 협상지시 | C6: D08 결정을 추가협상으로 변경 | F6: NEEDS_RENEGOTIATION / C02 없음 | G6: S14 지시 사유·담당·기한 입력. 상세 2차 협상 제외 | H6: 업무 검증 | I6: 해당 없음
A7: X02 | B7: 대표 비대상 | C7: 기안단가 2,050원으로 별도 실행 | D7: 0.025 | E7: =단가안비교!G9*50 -> 7840600 | F7: 기안액 기준 재판정 | G7: 새 협상·기안·run 생성, 기본안 덮어쓰기 금지 | H7: =IF(OR(D7>=설정!$B$9,E7>=설정!$B$11),"중요",IF(OR(D7>=설정!$B$8,E7>=설정!$B$10),"관심","정상")) -> 관심 | I7: =IF(E7>=설정!$B$12,"대표 대상","대표 비대상") -> 대표 비대상
A8: X03-A | B8: 대표 경계 직전 | C8: 규칙 단위검증용 금액 | D8: 0 | E8: 9999999 | F8: 대표 비대상 | G8: 기본 구매수량 역산에 쓰지 않는 규칙 fixture | H8: =IF(OR(D8>=설정!$B$9,E8>=설정!$B$11),"중요",IF(OR(D8>=설정!$B$8,E8>=설정!$B$10),"관심","정상")) -> 관심 | I8: =IF(E8>=설정!$B$12,"대표 대상","대표 비대상") -> 대표 비대상
A9: X03-B | B9: 대표 경계 포함 | C9: 규칙 단위검증용 금액 | D9: 0 | E9: 10000000 | F9: 대표 대상 | G9: 정확한 원 단위 비교 | H9: =IF(OR(D9>=설정!$B$9,E9>=설정!$B$11),"중요",IF(OR(D9>=설정!$B$8,E9>=설정!$B$10),"관심","정상")) -> 중요 | I9: =IF(E9>=설정!$B$12,"대표 대상","대표 비대상") -> 대표 대상
A10: X04 | B10: 적용일 변경 | C10: 설정 B6=2027-08-01 | F10: 2027-08~2028-07 재계산 | G10: 2028-07 5모델·원가·고정비 추가 제공. 재분석 전 상신 차단 | H10: 업무 검증 | I10: 해당 없음
A11: X05 | B11: 기안가 변경 | C11: 기안가=2130, 협상가=2120 | F11: 차이 사유·RUN-PROP02 필요 | G11: 이전 run·승인 재사용 금지 | H11: 업무 검증 | I11: 해당 없음
A12: X06 | B12: 협상미합의 | C12: 잠정단가 NULL | F12: NEGOTIATION_UNRESOLVED | G12: 0원으로 계산하거나 자동 상신하지 않음 | H12: 업무 검증 | I12: 해당 없음
A13: X07 | B13: 보완 또는 반려 | C13: U25 보완/반려 선택 | F13: RETURNED 또는 REJECTED | G13: 보완 시 신규기안버전·승인경로 재시작. 기한 재기산 구현명세 | H13: 업무 검증 | I13: 해당 없음
A14: X08-A | B14: 비율 관심 경계 | C14: 5% 인상·금액위험 없음 | D14: 0.05 | E14: 0 | F14: 관심 | G14: 비율만 시험 | H14: =IF(OR(D14>=설정!$B$9,E14>=설정!$B$11),"중요",IF(OR(D14>=설정!$B$8,E14>=설정!$B$10),"관심","정상")) -> 관심 | I14: =IF(E14>=설정!$B$12,"대표 대상","대표 비대상") -> 대표 비대상
A15: X08-B | B15: 비율 중요 경계 | C15: 10% 인상·금액위험 없음 | D15: 0.1 | E15: 0 | F15: 중요 | G15: 비율만 시험 | H15: =IF(OR(D15>=설정!$B$9,E15>=설정!$B$11),"중요",IF(OR(D15>=설정!$B$8,E15>=설정!$B$10),"관심","정상")) -> 중요 | I15: =IF(E15>=설정!$B$12,"대표 대상","대표 비대상") -> 대표 비대상
A16: X08-C | B16: 금액 관심 경계 | C16: 연 증가액 5백만원 | D16: 0 | E16: 5000000 | F16: 관심 | G16: 금액만 시험 | H16: =IF(OR(D16>=설정!$B$9,E16>=설정!$B$11),"중요",IF(OR(D16>=설정!$B$8,E16>=설정!$B$10),"관심","정상")) -> 관심 | I16: =IF(E16>=설정!$B$12,"대표 대상","대표 비대상") -> 대표 비대상
A17: X08-D | B17: 금액 중요 경계 | C17: 연 증가액 10백만원 | D17: 0 | E17: 10000000 | F17: 중요 | G17: 금액만 시험 | H17: =IF(OR(D17>=설정!$B$9,E17>=설정!$B$11),"중요",IF(OR(D17>=설정!$B$8,E17>=설정!$B$10),"관심","정상")) -> 중요 | I17: =IF(E17>=설정!$B$12,"대표 대상","대표 비대상") -> 대표 대상
A18: X09-A | B18: 월수량 누락 | C18: 2028-06 A-b 수량 NULL | F18: 미산출·상신 차단 | G18: 0 대분과 구분. 필수 60행과 값 유효성 검사 | H18: 업무 검증 | I18: 해당 없음
A19: X09-B | B19: Agent 실패 | C19: 요약 생성 실패 | F19: 수치 계산 유지·수동 요약 가능 | G19: Agent 완료를 승인으로 대체하지 않음 | H19: 업무 검증 | I19: 해당 없음
A20: X10 | B20: 중복 데이터 | C20: 동일 month/model 키 복제 | F20: 중복키 오류·계산 승인 차단 | G20: SUM으로 중복행 자동 합산 금지 | H20: 업무 검증 | I20: 해당 없음

Sheet 검토의견반영
A1: v0.2 후속확정 검토의견 반영
A3: 출처: INNONOW_SC02_화면구성_시연순서_v0.2.xlsx 후속확정. 아래 검토 의견은 원문을 보존했습니다.
A5: ID | B5: 항목 | C5: 검토 의견 원문 | D5: 이번 반영 위치 | E5: 구분
A6: NEXT01 | B6: 확정된 위험 비율 | C6: OK | D6: 단가안비교 E·J / 예외 X08 | E6: 반영
A7: NEXT02 | B7: 확정된 위험 금액 | C7: OK | D7: 단가안비교 I·K·M / 공급사 요청건 집계 | E7: 반영
A8: NEXT03 | B8: 연도와 시점 | C8: OK | D8: 업무이력 2027-06-17~24 가상 일정 | E8: 반영
A9: NEXT04 | B9: 공통 부품 가격 | C9: 시연 목적상 협상 이후에도 12개월 구매 증가액 >= 10백만원이 되도록 협상가 수치 설정 | D9: 설정 B16=2120 / 12개월 증가 1천만원 이상 | E9: 기준 확정·수치 가상 설정
A10: NEXT05 | B10: 12개월 데이터 확장 | C10: 28년 데이터는 내부가정으로 생성 | D10: 물량원가기준 2028-01~07 내부가정·97% | E10: 기준 확정·수치 가상 설정
A11: NEXT06 | B11: 재고와 기존 외주비 | C11: OK | D11: 부품모델매핑 잔여외주비 / 월별계산 T | E11: 반영
A12: NEXT07 | B12: 기간 표시 | C12: OK | D12: 단가안비교 F~I / 월초 적용 | E12: 반영
A13: NEXT08 | B13: 기한과 권한 | C13: OK. 외부협상 기한은 Case마다 달라질 수 있으므로 담당자가 일정을 입력하도록 함 | D13: 설정 B19 수동입력 / 업무이력 due_at | E13: 반영
A14: NEXT09 | B14: 상태별 데이터 준비 | C14: OK | D14: 업무이력 S01~14·CT21~30·U21~27·D00~12 | E14: 반영
A15: NEXT10 | B15: 장면 3 인계 계약 | C15: OK | D15: 장면3인계 상위검토건·두 사건·단일 선택안 | E15: 반영

Sheet 데이터계약
A1: 개발 적재·계산·표시 기준
A3: 본 파일은 장면1 기준을 포함한 장면2 확장 데이터입니다. 실제 업무 실행·권한·API·오류처리 명세는 다음 구현명세에서 확정합니다.
A5: entity / 항목 | B5: key / 자료형 | C5: 연결 및 처리 | D5: 화면·검증
A6: 물량원가기준 | B6: period DATE + model_id TEXT, 복합PK | C6: 95행: 2027 60행 +2028 35행. F01/F02 평면 열은 적재 시 version_id 기준 정규화 가능. T01은 2027만. | D6: U22/U27. 초기 F02 검토중 유지
A7: 2028 내부가정 | B7: EXT28-v1 / 가정계수0.97 | C7: 2027 동일월 F01에 계수 적용·정수 반올림. 2027-07의 -700을 다음해에 자동 복제하지 않음. 판매가·원가·고정비 동결. | D7: 내부가정 표시·고객공유 화면에 CP02로 표시 금지
A8: 월고정비 | B8: plant_id=ULS + period | C8: 공장별 월1행. 모델 합계에서 한번 차감. 2028 실적은 NULL. | D8: U27 공장손익
A9: 부품모델매핑 | B9: part_id + model_id | C9: P-COM01 / SUP-01 / a,b 각1. c,d,e 명시적0. C01 외주비 내 기존2천원 포함. | D9: U21/U22/U26
A10: 가격 원천 | B10: price_version + part_id | C10: 기존·요청·내부제시·협상·기안·승인 구분. 금액 KRW 정수·VAT 제외. | D10: U21~U26
A11: 적용일 | B11: effective_date DATE | C11: 기본 월초 7/1. 8/1 예외까지 데이터 지원. 월중 적용/2028-08 이후는 범위 밖·추가 데이터 요구. | D11: 불충분 기간을0으로 계산 금지
A12: 구매증가 산식 | B12: DECIMAL / KRW | C12: Σ(기안단가−기존단가)×적용기간 F02 소요량. 동일 공급사·요청건 부품 합산. 여러 품목 추가 시 상세행·매핑·집계범위 확장. | D12: 현재 기본은 공통부품1종
A13: 위험 규칙 | B13: R02-v1 | C13: 품목 인상률 최고수준과 요청건 구매 증가액 수준 중 높은 등급. 5%/10%,5백만/1천만 경계 포함. | D13: 승인권한 AUTH02-v1과 분리
A14: 승인권한 | B14: AUTH02-v1 | C14: 최종 기안 연 구매증가 ≥1천만원이면 대표 필요. 팀장·임원·대표 순서, 동일기안버전. | D14: 단가 변경 시 이전 승인 무효화 후 새 버전
A15: 손익 브리지 | B15: F01+C01 → F02+C01 → F02+C02 | C15: 장면1=(F02−F01)×기준CM. 장면2=−F02×단가차이×소요량. 상호작용은 원가단계에 포함. | D15: 요청/협상/승인안 동시합산 금지
A16: 구매액과 손익 | B16: 서로 다른 지표 | C16: 무재고·무기발주·시차0이므로 본 데모에서 증가액=CM감소 절대값. 회계상 일반 등식으로 사용하지 않음. | D16: U22는 별도 항목·기간 표시
... A25: 선행 원본 | B25: SC01 v0.1 / SC02 화면 v0.2 | C25: 2027 수량·원가·실적은 SC01 손익계산/단위원가/고정비의 값 보존. CP 원문·장면1 업무이력은 기존 파일이 원본. | D25: 원본 파일 수정 없음

Sheet 정합성검증
A1: 계산 및 원본 정합성 검증
A3: 기본안 기준 기대값과 수식을 비교합니다. 입력을 바꾸면 기본안 검증은 달라질 수 있습니다. 검증표는 계산 결과를 읽으며 계산의 입력으로 쓰지 않습니다.
A5: ID | B5: 검증항목 | C5: 기대값 | D5: 계산값 | E5: 차이 | F5: 결과
A6: V01 | B6: 2027 F01 관리손익 | C6: 3323351000 | D6: =통합손익!G21 -> 3323351000 | E6: =D6-C6 -> 0 | F6: =IF(E6=0,"일치","확인 필요") -> 일치
A7: V02 | B7: 2027 F02 관리손익 | C7: 3309351000 | D7: =통합손익!H21 -> 3309351000 | E7: =D7-C7 -> 0 | F7: =IF(E7=0,"일치","확인 필요") -> 일치
A8: V03 | B8: 장면1 물량 순영향 | C8: -14000000 | D8: =통합손익!I21 -> -14000000 | E8: =D8-C8 -> 0 | F8: =IF(E8=0,"일치","확인 필요") -> 일치
A9: V04 | B9: 2027 Target 관리손익 | C9: 3477290000 | D9: =통합손익!M21 -> 3477290000 | E9: =D9-C9 -> 0 | F9: =IF(E9=0,"일치","확인 필요") -> 일치
A10: V05 | B10: 12개월 유효 모델월 | C10: 60 | D10: =SUMPRODUCT(월별계산!N6:N100,월별계산!U6:U100) -> 60 | E10: =D10-C10 -> 0 | F10: =IF(E10=0,"일치","확인 필요") -> 일치
A11: V06 | B11: 12개월 행수 | C11: 60 | D11: =SUM(월별계산!N6:N100) -> 60 | E11: =D11-C11 -> 0 | F11: =IF(E11=0,"일치","확인 필요") -> 일치
A12: V07 | B12: 손익 브리지 오차 | C12: 0 | D12: =SUM(통합손익!O6:O22) -> 0 | E12: =D12-C12 -> 0 | F12: =IF(E12=0,"일치","확인 필요") -> 일치
A13: V08 | B13: c~e 승인원가 영향 | C13: 0 | D13: =SUM(통합손익!D28:D30) -> 0 | E13: =D13-C13 -> 0 | F13: =IF(E13=0,"일치","확인 필요") -> 일치
A14: V09 | B14: 기존부품 외주비 초과 | C14: 0 | D14: =COUNTIFS(부품모델매핑!G6:G10,"<0") -> 0 | E14: =D14-C14 -> 0 | F14: =IF(E14=0,"일치","확인 필요") -> 일치
A15: V10 | B15: 협상 후 대표 승인 대상 | C15: 1 | D15: =IF(단가안비교!I8>=설정!B12,1,0) -> 1 | E15: =D15-C15 -> 0 | F15: =IF(E15=0,"일치","확인 필요") -> 일치
A16: V11 | B16: 요청 대비 부담 감소 | C16: 1 | D16: =IF(단가안비교!N8>0,1,0) -> 1 | E16: =D16-C16 -> 0 | F16: =IF(E16=0,"일치","확인 필요") -> 일치
A17: V12 | B17: 협상 후 원가 부담 잔존 | C17: 1 | D17: =IF(단가안비교!I8>0,1,0) -> 1 | E17: =D17-C17 -> 0 | F17: =IF(E17=0,"일치","확인 필요") -> 일치
A18: V13 | B18: 기안과 협상 단가 차이 | C18: 0 | D18: =설정!B17-설정!B16 -> 0 | E18: =D18-C18 -> 0 | F18: =IF(E18=0,"일치","확인 필요") -> 일치
A19: V14 | B19: 2027 증가와 손익영향 연결 | C19: 0 | D19: =단가안비교!H10+통합손익!J21 -> 0 | E19: =D19-C19 -> 0 | F19: =IF(E19=0,"일치","확인 필요") -> 일치
A20: V15 | B20: 향후12개월 증가와 손익 연결 | C20: 0 | D20: =단가안비교!I10+통합손익!J22 -> 0 | E20: =D20-C20 -> 0 | F20: =IF(E20=0,"일치","확인 필요") -> 일치
A21: V16 | B21: 2027 실적수량 보존 | C21: 149280 | D21: =SUM(물량원가기준!K6:K65) -> 149280 | E21: =D21-C21 -> 0 | F21: =IF(E21=0,"일치","확인 필요") -> 일치
A22: V17 | B22: 전체 원천 행 유효 | C22: 95 | D22: =SUM(월별계산!U6:U100) -> 95 | E22: =D22-C22 -> 0 | F22: =IF(E22=0,"일치","확인 필요") -> 일치

Sheet SC03요약
A1: INNONOW SC03요약 v0.3
A3: 장면3 확장 · 가상 업무연도 2027 · KST · 원 단위 · 빈 금액 셀은 NULL(미산정)
A5: 항목 | B5: 값 | C5: 단위·상태 | D5: 근거·읽는 순서
A6: 데이터 묶음 | B6: SC01~SC03 v0.3 | C6: 2026-10-21 | D6: 기존 원천·수식 유지. 통합손익 하단 Q3 모델표는 통합모델손익으로 분리. SC03 시트는 기본 시연 종료 시점의 가상 레코드. 이벤트로 이전 시점 재생.
A7: 대상 | B7: ULS / A-a~A-e | C7: 가상 고객 | D7: 전사1조원 회사의 일부 공장·제품 분석. 신규 현업 설명은 합성 시연자료이며 실제 회사 사실 아님.
A8: 2027 통합 관리손익 | B8: =통합손익!K21 -> 3299986680 | C8: 원 | D8: 기존 통합손익 K21 연결
A9: 2027 목표 부족 | B9: =통합손익!N21 -> 177303320 | C9: 원 | D9: Target 유지. 기존부족과 신규사건 분리
A10: 기존 목표 부족 | B10: =통합손익!M21-통합손익!G21 -> 153939000 | C10: 원 | D10: 세부 원인 아직 미확인. AT34 분석 대상
A11: 신규 사건 영향 | B11: =통합손익!L21 -> -23364320 | C11: 원 | D11: 물량과 승인단가의 통합영향
A12: 탐색 후보 | B12: =COUNTA(SC03후보!A6:A11) -> 6 | C12: 건 | D12: SC03후보: 6개 정성적 대응 후보
A13: 상세 분석 대상으로 채택 | B13: =COUNTIF(SC03후보!F6:F11,"INCLUDE") -> 4 | C13: 건 | D13: 4개 후보를 3개 대응 분석과제에 연결. 기존 부족 원인분석 AT34는 별도
A14: 이번 분석에서 제외 | B14: =COUNTIF(SC03후보!F6:F11,"EXCLUDE_THIS_REVIEW") -> 2 | C14: 건 | D14: 전면 외주화·해외 신규 차종 확대. 사유 기록, 재검토 가능
A15: 배정 과제 | B15: =COUNTA(SC03과제!A6:A9) -> 4 | C15: 건 | D15: AT31~34. 후보 채택은 실행안 승인 아님
A16: 인수 완료 과제 | B16: =COUNTIF(SC03과제!L6:L9,"ACCEPTED") -> 4 | C16: 건 | D16: 기본 시연 종료시 4/4
A17: 인수율 | B17: =IF(B15=0,"N/A",B16/B15) -> 1 | C17: 비율 | D17: 인수 완료 / 배정 과제. 0건이면 N/A
A18: Risk / Forecast | B18: OPEN / REVIEW_PENDING | C18: 유지 | D18: 장면 완료와 분리
A19: 기본 장면 상태 | B19: SC03_COMPLETED | C19: 6/30 11:30 KST | D19: 검토결론·잔여사항 처리·과제인수·7/12 월간회의 계획 확보
A20: 조건부 수용의 의미 | B20: 통합 영향 검토 수용, 상세 분석 범위 특정 | C20: REV31 | D20: AT31 회피가능 고정비와 AT34 기존 부족의 근거를 후속 확인. 현재 손익계산 오류는 없음.
A21: 추가 의견 반영 | B21: NEXT32·NEXT33 | C21: 반영 | D21: 후보별 설명→포함/제외 판단→분석 대상·질문 특정. SC03후보·SC03회의 참조.
A22: 후속 | B22: 통합 데이터 검토 후 구현 명세 | C22: 예정 | D22: 추가 대안 비용·절감액은 미산정(NULL). 장면4에서 상세 비교·결정.

Sheet SC03기준
A1: INNONOW SC03기준 v0.3
A3: 장면3 확장 · 가상 업무연도 2027 · KST · 원 단위 · 빈 금액 셀은 NULL(미산정)
A5: record_id | B5: type | C5: value | D5: source_ref | E5: effective_at | F5: 설명
A6: BASE31 | B6: qty_version | C6: F02 + EXT28-v1 | D6: 장면3인계 | E6: 46562.417 | F6: F01 대비 물량변동 후 승인단가 적용
A7: BASE32 | B7: cost_version | C7: C02-APP01 | D7: PV-APP01 / RUN-APP01 | E7: 46569 | F7: C01 고정 기준. 요청·협상안 중복 합산 금지
A8: BASE33 | B8: fixed_version | C8: FC01 / FC28-v1 | D8: 월고정비 | E8: 46562.417 | F8: 공장합계에만 고정비 차감
A9: RUN-SC03-01 | B9: analysis_run | C9: MR-2706-01 | D9: RUN-F02-001 / RUN-APP01 | E9: 46562.625 | F9: 기존 통합 계산 재사용. 새6월 실적 입력 없음
A10: REP31-v0 | B10: report_version | C10: DRAFT | D10: RUN-SC03-01 | E10: 46562.632 | F10: 부서 확인용 초안
A11: REP31-v1 | B11: report_version | C11: FROZEN | D11: RUN-SC03-01 | E11: 46567.375 | F11: 임원 확인·확정. 수치 재계산 없음, 부서 확인과 쟁점 처리 추가
A12: MIN31-v1 | B12: minutes_version | C12: CONFIRMED | D12: MT31 / REV31 | E12: 46567.625 | F12: 경영관리 임원 확인. 분석 지시 및 제외 사유 포함
A13: USR-FIN | B13: actor | C13: 경영관리 담당 | D13: ROLE-FIN | F13: 가상 계정. 분석·취합·회의록 작성·종료
A14: USR-CFO | B14: actor | C14: 경영관리 임원 | D14: ROLE-CFO | F14: 수시회의 주재·결론·배정 확인
A15: USR-PROD | B15: actor | C15: 생산 책임자 | D15: ROLE-PROD | F15: AT31 인수; 생산 사실 확인
A16: USR-BUY | B16: actor | C16: 구매 책임자 | D16: ROLE-BUY | F16: AT32 인수; 구매 사실 확인
A17: USR-SALES | B17: actor | C17: 영업 책임자 | D17: ROLE-SALES | F17: AT33 인수; 영업 사실 확인
A18: USR-FINLEAD | B18: actor | C18: 경영관리 책임자 | D18: ROLE-FINLEAD | F18: AT34 인수; 기존 부족 분석
A19: USR-QA | B19: actor | C19: 품질 책임자 | D19: ROLE-QA | F19: 후속 과제 협조. MT31 참석자로 가정하지 않음
A20: USR-CEO | B20: actor | C20: 대표이사 | D20: ROLE-CEO | F20: 장면4 MT41 주재. 장면3 결론 승인권자 아님

Sheet SC03사실확인
A1: INNONOW SC03사실확인 v0.3
A3: 장면3 확장 · 가상 업무연도 2027 · KST · 원 단위 · 빈 금액 셀은 NULL(미산정)
A5: fact_id | B5: dept | C5: category | D5: statement | E5: evidence_ref | F5: reviewer | G5: confirmed_at | H5: state | I5: followup_ref
A6: F31 | B6: 영업 | C6: FACT | D6: b모델 7월 전망 9,500→8,800. 고객계획 변경에 따른 추가 700개 감소. | E6: ISSUE-B07 / RUN-F02-001 | F6: USR-SALES | G6: 46563.458 | H6: CONFIRMED
A7: F32 | B7: 영업 | C7: ASSUMPTION | D7: 2028 물량은 2027 동일월 F01×97%. 고객 확정 생산계획 아님. | E7: EXT28-v1 / 설정 | F7: USR-SALES | G7: 46563.462 | H7: CONFIRMED_AS_ASSUMPTION
A8: F33 | B8: 구매 | C8: FACT | D8: 공통부품 승인단가 2,120원, 7/1 적용, a·b 각1개. | E8: PV-APP01 / P-COM01 / RUN-APP01 | F8: USR-BUY | G8: 46563.625 | H8: CONFIRMED
A9: F34 | B9: 구매 | C9: ASSUMPTION | D9: 기발주·재고 및 구매·생산·납품 시차 없음. 구매 증가와 CM 감소 대응은 이 가정에 한정. | E9: 기존 데이터계약 | F9: USR-BUY | G9: 46563.628 | H9: CONFIRMED_AS_ASSUMPTION
A10: F35 | B10: 생산 | C10: FACT | D10: 일부 부품공정 공유, 최종 조립은 모델별 구분. a 수익성 우위는 단가만으로 단정할 수 없음. | E10: SC03 경영이야기 / 가상 프로세스 기준 | F10: USR-PROD | G10: 46566.417 | H10: CONFIRMED
A11: F36 | B11: 생산 | C11: UNCONFIRMED | D11: 부분 외주화 시 회피 가능한 인력·설비 비용과 잔존비용의 상세 구분은 미확인. | E11: 가상 생산 검토 메모 SYN-PROD31 | F11: USR-PROD | G11: 46566.424 | H11: FOLLOWUP_REQUIRED | I11: Q31 / AT31
A12: F37 | B12: 경영관리 | C12: UNCONFIRMED | D12: 기존 목표 부족 153,939,000원의 세부 원인 분해 근거 추가 확인 필요. | E12: 통합손익 M21−G21 | F12: USR-FINLEAD | G12: 46566.625 | H12: FOLLOWUP_REQUIRED | I12: Q32 / AT34

Sheet SC03쟁점
A1: INNONOW SC03쟁점 v0.3
A3: 장면3 확장 · 가상 업무연도 2027 · KST · 원 단위 · 빈 금액 셀은 NULL(미산정)
A5: question_id | B5: fact_ref | C5: question | D5: blocking | E5: owner | F5: due_at | G5: decision_by | H5: decided_at | I5: treatment | J5: state
A6: Q31 | B6: F36 | C6: 실제 회피 가능한 고정비와 잔존비용은 무엇인가? | D6: FALSE | E6: USR-PROD | F6: 46574.75 | G6: USR-CFO | H6: 46566.708 | I6: 현 통합손익은 고정비 불변으로 계산되어 영향 없음. AT31에서 부분 공정 조정의 경제성을 확인. | J6: OPEN_FOLLOWUP
A7: Q32 | B7: F37 | C7: 기존 부족의 원인을 신규 사건과 중복 없이 어떻게 설명할 것인가? | D7: FALSE | E7: USR-FINLEAD | F7: 46574.75 | G7: USR-CFO | H7: 46566.712 | I7: 부족 금액은 검증됨. 원인 미확인을 명시하고 AT34로 분석 지시. | J7: OPEN_FOLLOWUP

Sheet SC03회의
A1: INNONOW SC03회의 v0.3
A3: 장면3 확장 · 가상 업무연도 2027 · KST · 원 단위 · 빈 금액 셀은 NULL(미산정)
A5: record_id | B5: record_type | C5: meeting_id | D5: actor_id | E5: event_at | F5: subject | G5: content | H5: related_ref | I5: state
A6: MT31 | B6: MEETING | C6: MT31 | D6: USR-CFO | E6: 46567.417 | F6: 수시 경영검토회의 | G6: 울산 A제품 통합 손익영향 검토 및 상세 분석대상 특정. 종료 예정11:00. | H6: MR-2706-01 / REP31-v1 | I6: HELD
A7: ATT31-1 | B7: ATTENDANCE | C7: MT31 | D7: USR-CFO | E7: 46567.417 | F7: 참석 | G7: 가상 참석 기록 | H7: REP31-v1 | I7: PRESENT
A8: ATT31-2 | B8: ATTENDANCE | C8: MT31 | D8: USR-FIN | E8: 46567.417 | F8: 참석 | G8: 가상 참석 기록 | H8: REP31-v1 | I8: PRESENT
A9: ATT31-3 | B9: ATTENDANCE | C9: MT31 | D9: USR-PROD | E9: 46567.417 | F9: 참석 | G9: 가상 참석 기록 | H9: REP31-v1 | I9: PRESENT
A10: ATT31-4 | B10: ATTENDANCE | C10: MT31 | D10: USR-BUY | E10: 46567.417 | F10: 참석 | G10: 가상 참석 기록 | H10: REP31-v1 | I10: PRESENT
A11: ATT31-5 | B11: ATTENDANCE | C11: MT31 | D11: USR-SALES | E11: 46567.417 | F11: 참석 | G11: 가상 참석 기록 | H11: REP31-v1 | I11: PRESENT
A12: ATT31-6 | B12: ATTENDANCE | C12: MT31 | D12: USR-FINLEAD | E12: 46567.417 | F12: 참석 | G12: 가상 참석 기록 | H12: REP31-v1 | I12: PRESENT
A13: QA31 | B13: QUESTION | C13: MT31 | D13: USR-CFO | E13: 46567.424 | F13: 사건 영향과 전체 부족 구분 | G13: 두 사건을 해소하면 목표 달성이 가능한가? | H13: RUN-SC03-01 | I13: ANSWERED
A14: QA32 | B14: ANSWER | C14: MT31 | D14: USR-FIN | E14: 46567.425 | F14: 기존 부족 별도 | G14: 신규 악화 23,364,320원 외 기존 부족 153,939,000원이 남습니다. 원인 분해는 추가 분석하겠습니다. | H14: QA31 / Q32 | I14: RECORDED
A15: QA33 | B15: EXPLANATION | C15: MT31 | D15: USR-PROD | E15: 46567.432 | F15: 외주 범위 구분 | G15: 부분 공정 조정은 검토 가능. 최종 조립 전면 외주화는 단기간 전환·품질 검증 조건이 준비되지 않았다는 가상 설명. | H15: C31 / C35 / SYN-PROD31 | I15: RECORDED
A16: QA34 | B16: EXPLANATION | C16: MT31 | D16: USR-SALES | E16: 46567.438 | F16: 물량 확보 범위 | G16: 기존 고객·기존 승인모델의 추가 배분 가능성부터 확인. 해외 신규 차종은 인증·수주 일정이 미확인이라는 가상 설명. | H16: C34 / C36 / SYN-SALES31 | I16: RECORDED
A17: REV31 | B17: REVIEW_DECISION | C17: MT31 | D17: USR-CFO | E17: 46567.451 | F17: 조건부 수용 및 분석 범위 특정 | G17: 통합영향을 수용한다. C31~34는 상세 분석하고 C35·36은 이번 월간회의 상세 분석에서 제외한다. Q31·32는 7/6까지 AT31·34로 확인한다. 실행안 선택은 7/12 대표 주재회의로 남긴다. | H17: Q31 / Q32 / AT31~34 | I17: CONDITIONAL_ACCEPT
... A19: MT41 | B19: MEETING_PLAN | C19: MT41 | D19: USR-CEO | E19: 46580.417 | F19: 월간 경영회의 | G19: 7/6 분석 제출, 7/8 경영관리 취합 후 상세 대안을 비교·결정한다. 현재는 계획만 등록. | H19: HANDOFF31 | I19: PLANNED

Sheet SC03후보
A1: INNONOW SC03후보 v0.3
A3: 장면3 확장 · 가상 업무연도 2027 · KST · 원 단위 · 빈 금액 셀은 NULL(미산정)
A5: candidate_id | B5: dept | C5: candidate | D5: expected_mechanism | E5: constraints | F5: decision | G5: decision_reason | H5: task_id | I5: evidence_ref | J5: decided_by | K5: decided_at | L5: effect_2027 | M5: effect_12m
A6: C31 | B6: 생산 | C6: 부분 공정의 생산·외주 구성 조정 | D6: 고정비 회피 가능성과 외주 추가비를 비교 | E6: 잔존비용·전환비용·품질·납기 확인 필요 | F6: INCLUDE | G6: 부분 공정 대안의 경제성을 검증할 수 있으므로 상세 분석 | H6: AT31 | I6: QA33 | J6: USR-CFO | K6: 46567.451
A7: C32 | B7: 구매 | C7: 구매조건 개선·긴급구매 축소 | D7: 조달 단가·긴급비용 부담 완화 가능성 | E7: 기존 계약조건·발주 패턴 자료 확인 필요 | F7: INCLUDE | G7: 실제 조정 가능한 구매조건과 긴급구매 원인부터 확인 | H7: AT32 | I7: F33 | J7: USR-CFO | K7: 46567.451
A8: C33 | B8: 구매 | C8: 기존 승인 대체 공급처 활용 가능성 | D8: 공급 안정성과 원가 대안 확인 | E8: 승인 범위·가용 능력·품질검증·전환비 확인 필요 | F8: INCLUDE | G8: 기존 승인 범위 안의 후보부터 검증; 확보된 공급처로 단정하지 않음 | H8: AT32 | I8: F33 | J8: USR-CFO | K8: 46567.451
A9: C34 | B9: 영업 | C9: 기존 고객·기존 승인모델 물량 재배분 | D9: 유휴 여력 활용과 공헌이익 기여 가능성 | E9: 고객 배분 의사·생산능력·납기·추가 변동비 확인 필요 | F9: INCLUDE | G9: 신규 수주 확정 없이 실현 가능성과 적용 시점 검증 | H9: AT33 | I9: QA34 | J9: USR-CFO | K9: 46567.451
A10: C35 | B10: 생산 | C10: 최종 조립 전면 외주화 | D10: 대규모 고정비 변동비화 가능성 탐색 | E10: 단기 전환·품질 검증조건 미준비라는 가상 설명 | F10: EXCLUDE_THIS_REVIEW | G10: 7/12 보고를 위한 검증 가능한 범위를 벗어나 제외. 전환조건 확보 후 재검토 | I10: QA33 | J10: USR-CFO | K10: 46567.451
A11: C36 | B11: 영업 | C11: 해외 신규 차종 신규 수주 확대 | D11: 국내 감소를 해외 매출로 보완할 가능성 | E11: 인증·수주 일정 미확인이라는 가상 설명 | F11: EXCLUDE_THIS_REVIEW | G11: 이번 단기 대응 분석에서는 제외. 중장기 영업전략 검토 후보로 보존 | I11: QA34 | J11: USR-CFO | K11: 46567.451

Sheet SC03과제
A1: INNONOW SC03과제 v0.3
A3: 장면3 확장 · 가상 업무연도 2027 · KST · 원 단위 · 빈 금액 셀은 NULL(미산정)
A5: task_id | B5: candidate_refs | C5: title | D5: owner_id | E5: collaborators | F5: analysis_question | G5: deliverable | H5: dependency | I5: assigned_at | J5: due_at | K5: accepted_at | L5: state | M5: basis_ref | N5: effect_2027 | O5: effect_12m
A6: AT31 | B6: C31 | C6: 생산·외주 구성 분석 | D6: USR-PROD | E6: USR-BUY;USR-FIN;USR-QA | F6: 부분 공정별 회피가능·잔존 고정비, 추가외주·전환비·품질·납기·실행시점은? | G6: 원가구조·제약·실행시점 비교자료 | H6: Q31 | I6: 46567.632 | J6: 46574.75 | K6: 46568.375 | L6: ACCEPTED | M6: REP31-v1 / BASE31~33
A7: AT32 | B7: C32;C33 | C7: 구매조건·대체공급처 분석 | D7: USR-BUY | E7: USR-PROD;USR-QA;USR-FIN | F7: 구매조건·긴급구매 축소와 기존 승인 대체공급처의 가능성·비용·제약은? | G7: 구매 후보별 조건·검증자료·적용시점 | H7: AT31과 외주비 효과 중복 조정 | I7: 46567.632 | J7: 46574.75 | K7: 46568.396 | L7: ACCEPTED | M7: REP31-v1 / BASE31~33
A8: AT33 | B8: C34 | C8: 물량·제품 구성 분석 | D8: USR-SALES | E8: USR-PROD;USR-FIN | F8: 기존 고객·승인모델 추가 배분 가능량·시점·제약·공헌이익은? | G8: 물량 근거·가능시점·CM 산정조건 | H8: 생산 여력 확인 필요 | I8: 46567.632 | J8: 46574.75 | K8: 46568.417 | L8: ACCEPTED | M8: REP31-v1 / BASE31~33
A9: AT34 | C9: 기존 목표 부족 원인 분석 | D9: USR-FINLEAD | E9: USR-SALES;USR-BUY;USR-PROD | F9: 기존 부족의 원인 근거와 미확인을 신규 사건과 중복 없이 설명할 수 있는가? | G9: 기존 부족 원인표·근거·추가 질문 | H9: Q32 | I9: 46567.632 | J9: 46574.75 | K9: 46568.458 | L9: ACCEPTED | M9: REP31-v1 / BASE31~33

Sheet SC03이벤트
A1: INNONOW SC03이벤트 v0.3
A3: 장면3 확장 · 가상 업무연도 2027 · KST · 원 단위 · 빈 금액 셀은 NULL(미산정)
A5: event_id | B5: scenario_id | C5: event_at_KST | D5: actor_id | E5: screen_id | F5: step_id | G5: action | H5: object_ref | I5: state_after | J5: evidence_ref | K5: demo_id
A6: EV31-01 | B6: BASE | C6: 46562.42 | D6: USR-FIN | E6: U31 | F6: S31 | G6: 검토 착수 | H6: MR-2706-01 | I6: ANALYSIS_IN_PROGRESS | J6: 장면3인계 | K6: D31
A7: EV31-02 | B7: BASE | C7: 46562.625 | D7: USR-FIN | E7: U32 | F7: S32~33 | G7: 통합분석 저장 | H7: RUN-SC03-01 | I7: CALCULATED | J7: RUN-F02-001;RUN-APP01 | K7: D32
A8: EV31-03 | B8: BASE | C8: 46562.667 | D8: USR-FIN | E8: U33 | F8: S34~36 | G8: 부서 확인 요청 | H8: REP31-v0 | I8: CONFIRMATION_PENDING | J8: USR-SALES;USR-BUY;USR-PROD | K8: D34
A9: EV31-04 | B9: BASE | C9: 46563.462 | D9: USR-SALES | E9: U33 | F9: S34~36 | G9: 부서 회신 | H9: F31;F32 | I9: RESPONDED | J9: REP31-v0 | K9: D35
A10: EV31-05 | B10: BASE | C10: 46563.628 | D10: USR-BUY | E10: U33 | F10: S34~36 | G10: 부서 회신 | H10: F33;F34 | I10: RESPONDED | J10: REP31-v0 | K10: D35
A11: EV31-06 | B11: BASE | C11: 46566.424 | D11: USR-PROD | E11: U33 | F11: S34~36 | G11: 부서 회신 | H11: F35;F36 | I11: RESPONDED | J11: REP31-v0 | K11: D35
A12: EV31-07 | B12: BASE | C12: 46566.625 | D12: USR-FINLEAD | E12: U33 | F12: S37 | G12: 기존 부족 쟁점 등록 | H12: F37 | I12: FOLLOWUP_REQUIRED | J12: Q32 | K12: D36
A13: EV31-08 | B13: BASE | C13: 46566.712 | D13: USR-CFO | E13: U33 | F13: S37 | G13: 비차단 쟁점 처리 확정 | H13: Q31;Q32 | I13: OPEN_FOLLOWUP | J13: AT31;AT34 | K13: D36
A14: EV31-09 | B14: BASE | C14: 46567.375 | D14: USR-CFO | E14: U34 | F14: S38 | G14: 자료 확인·확정 | H14: REP31-v1 | I14: FROZEN | J14: REP31-v0 | K14: D36
A15: EV31-10 | B15: BASE | C15: 46567.378 | D15: USR-FIN | E15: U34 | F15: S38 | G15: 내부 자료 배포 | H15: MT31 | I15: MEETING_READY | J15: REP31-v1 | K15: D36
A16: EV31-11 | B16: BASE | C16: 46567.417 | D16: USR-FIN | E16: U35 | F16: S39 | G16: 통합영향 보고 | H16: MT31 | I16: IN_REVIEW | J16: REP31-v1 | K16: D37
A17: EV31-12 | B17: BASE | C17: 46567.451 | D17: USR-CFO | E17: U35 | F17: S40~41 | G17: 후보 포함·제외 및 분석 범위 특정 | H17: REV31 | I17: CONDITIONAL_ACCEPT | J17: C31;C32;C33;C34;C35;C36 | K17: D38
... A27: EV31-22 | B27: BASE | C27: 46568.479 | D27: USR-FIN | E27: U37 | F27: S44 | G27: 장면 종료 | H27: MR-2706-01 | I27: SC03_COMPLETED | J27: HANDOFF31 | K27: D41

Sheet SC03인계
A1: INNONOW SC03인계 v0.3
A3: 장면3 확장 · 가상 업무연도 2027 · KST · 원 단위 · 빈 금액 셀은 NULL(미산정)
A5: field | B5: value | C5: source_ref | D5: 처리 기준
A6: handoff_id | B6: HANDOFF31 | C6: EV31-22 | D6: 2027-06-30 11:30 기준
A7: review_id | B7: MR-2706-01 | C7: 장면3인계 | D7: 기존 검토건 유지
A8: report_version | B8: REP31-v1 | C8: RUN-SC03-01 | D8: 고정 보고본. 최신 전망과 자동 치환 금지
A9: minutes_version | B9: MIN31-v1 | C9: MT31 / REV31 | D9: 조건부 수용·포함/제외 사유 및 분석 지시
A10: accepted_tasks | B10: AT31;AT32;AT33;AT34 | C10: SC03과제 | D10: 전건 인수, 아직 상세분석 미제출
A11: open_questions | B11: Q31;Q32 | C11: SC03쟁점 | D11: 7/6 18시까지 후속 확인
A12: excluded_candidates | B12: C35;C36 | C12: SC03후보 | D12: 이번 상세 분석 제외. 중장기 재검토 가능
A13: next_meeting | B13: MT41 / 2027-07-12 10:00 KST | C13: SC03회의 | D13: 대표 주재 월간회의
A14: analysis_due | B14: 46574.75 | C14: SC03과제 | D14: 제출기한
A15: consolidation_due | B15: 46576.75 | C15: MT41 | D15: 경영관리 취합기한
A16: risk_status | B16: OPEN | C16: 장면3인계 | D16: 회의 검토/과제 인수로 해소되지 않음
A17: forecast_status | B17: REVIEW_PENDING | C17: 장면3인계 | D17: 공식 전망 승인 별도
A18: target_status | B18: UNCHANGED | C18: 기존 Target | D18: 자동 변경 금지
A19: comparison_rule | B19: 잔여2027 / 향후12개월 구분 | C19: BASE31~33 | D19: 일회성/반복·시작일·중복효과·가정·제약 명시
A20: as_of | B20: 46568.479 | C20: EV31-22 | D20: 미래 제출·효과검증 완료 데이터 없음

Sheet SC03예외
A1: INNONOW SC03예외 v0.3
A3: 장면3 확장 · 가상 업무연도 2027 · KST · 원 단위 · 빈 금액 셀은 NULL(미산정)
A5: scenario_id | B5: checkpoint | C5: object_ref | D5: field | E5: override_value | F5: action_sequence | G5: expected_state | H5: 보존·검수
A6: E31 | B6: EV31-03 이후 | C6: F33 | D6: state | E6: DISPUTED | F6: 구매 적용조건 이견→차단→보완→새 보고버전·재확인 | G6: BLOCKED → CONFIRMED | H6: BASE 복제. 실제 승인값 2120은 유지; 자료의 잘못된 적용월을 정정
A7: E32 | B7: EV31-17 이후 | C7: AT31 | D7: dependency | E7: 자료 의존관계 누락 | F7: 6/29 16시 반려→17시 Q31·구매 협조 보완→6/30 9시 재인수 | G7: RETURNED → ASSIGNED → ACCEPTED | H7: 분기 이벤트 ID E32-01~03; BASE의 인수 이력 덮어쓰기 금지
A8: E33 | B8: EV31-02 이전 | C8: RUN-SC03-01 | D8: fixed_cost_multiplier | E8: 2 | F8: 고정비 중복 입력 복제 계산→검증 실패→정정 | G8: CALCULATION_BLOCKED | H8: 정합성검증 실패 결과 기록. 조건부 수용으로 우회 불가
A9: E34 | B9: EV31-10 이후 | C9: REP31-v1 | D9: new_report_version | E9: REP31-v2-E34 | F9: 새 전망 입력요청→별도 계산→변경 설명→임원 재확인 | G9: REVISION_PENDING | H9: 기존 v1 유지. 신규 재무값은 기본 데이터에 포함하지 않음
A10: E35 | B10: EV31-17 이후 | C10: AT31 | D10: accept_actor | E10: USR-SALES | F10: 타부서 인수 시도→거부 | G10: FORBIDDEN | H10: AT31 상태 변화 없음
A11: E35-M | B11: EV31-13 이후 | C11: AT31 | D11: owner_id | F11: 필수 책임자 NULL로 배정 확정 시도 | G11: VALIDATION_FAILED | H11: 미배정이며 완료율 분모에는 확정 배정만 사용
A12: E36 | B12: EV31-11 이후 | C12: AG31 | D12: generation_status | E12: FAILED | F12: Agent 실패→수동 기록 | G12: MANUAL_ENTRY_AVAILABLE | H12: 원 계산값 유지; 실패를 0원으로 처리 금지
A13: E37 | B13: EV31-22 이후 | C13: AT31 | D13: as_of | E13: 46574.751 | F13: 미제출 상태에서 기한경과 조회 | G13: OVERDUE | H13: 장면3 완료 유지, 과제지연 알림만 생성. 후속 준비 분기

Sheet SC03데이터계약
A1: INNONOW SC03데이터계약 v0.3
A3: 장면3 확장 · 가상 업무연도 2027 · KST · 원 단위 · 빈 금액 셀은 NULL(미산정)
A5: entity_or_field | B5: key_type | C5: relation_or_rule | D5: 화면·시연 | E5: 근거·출처
A6: SC03기준 | B6: record_id TEXT PK | C6: 분석 RUN은 기존 물량·단가 RUN 두 개 참조. 보고는 RUN, 회의는 보고 버전 참조. | D6: U31·32·34 | E6: 기존 통합데이터 v0.2
A7: SC03사실확인 | B7: fact_id TEXT PK | C7: category FACT/ASSUMPTION/UNCONFIRMED. 담당자·시각·증빙·후속질문 추적. 동일 실행에 연결. | D7: U33 / D35 | E7: 새 합성 레코드
A8: SC03쟁점 | B8: question_id TEXT PK | C8: blocking BOOLEAN; owner FK actor, due_at TIMESTAMP. 열린 비차단 쟁점은 종료 후에도 유지. | D8: U33·35·37 | E8: 업무설계 v0.2
A9: SC03회의 | B9: record_id PK / meeting_id FK | C9: 회의·참석·질의·답변·결론·회의록·후속회의 계획을 record_type으로 구분. | D9: U34·35 | E9: 화면구성 v0.2 NEXT33
A10: SC03후보 | B10: candidate_id TEXT PK | C10: INCLUDE는 상세분석 대상. 실행 승인 아님. 제외 후보 task_id NULL. 채택 4후보→AT31~33, AT34는 원인분석. | D10: U35·36 | E10: NEXT32: 일부 후보 제외 반영
A11: SC03과제 | B11: task_id TEXT PK | C11: 후보 N:M. 현재 세미콜론 refs는 적재 시 관계 테이블로 분리. AT34 후보 없음은 정상. owner 단일 FK. | D11: U36·37 | E11: 기존4개 과제 유지, 분석 범위 특정
A12: effect_2027 / effect_12m | B12: DECIMAL NULL | C12: 빈 셀은 미산정. 0원 확정과 구분. 미설정 Target도 NULL 유지. | D12: U35·36 | E12: 상세 비교·효과 산정은 장면4 준비
A13: SC03이벤트 | B13: scenario_id + event_id PK | C13: BASE는 기본 흐름. event_at 순서·ID로 재생, 해당 시각 이후 인수/결론 노출 금지. 과제/후보/회의 시트는 종료시점 완성 레코드. | D13: D30~41 | E13: 시연 상태 복원 기준
A14: SC03예외 | B14: scenario_id TEXT PK | C14: BASE 체크포인트 복제 후 override 적용. 신규 시나리오별 이벤트 분리. E34 신규 수치는 후속 구현 fixture로 생성. | D14: E31~37 | E14: 오류·반려·권한 검증 입력
A15: 시각·달력 | B15: KST / CAL-DEMO01 | C15: Excel 날짜는 KST 벽시계 값. API 적재 시 +09:00. 평일09~18, 주말 제외, 휴일없음·점심공제없음의 가상9시간 영업일. | D15: 기한·소요시간 | E15: 기존 가상 영업일 원칙 유지
A16: 소요시간 | B16: 완료−착수 | C16: 장면3 착수6/24 10:05~6/30 11:30. 실제 경과 및 영업시간 별도. 비교기준 없으므로 개선율 NULL. | D16: M40 | E16: SC03영업시간 계산
... A20: 제외 후보의 제약 | B20: SYN-PROD31 / SYN-SALES31 | C20: 회의 QA33·QA34의 합성 설명을 근거로 한 시연용 판단. 실제 공급사·고객 확인자료로 오인하지 않음. | D20: C35·C36 | E20: 추가 가상 설정, 검토 가능한 초안

Sheet SC03영업시간
A1: INNONOW SC03영업시간 v0.3
A3: 장면3 확장 · 가상 업무연도 2027 · KST · 원 단위 · 빈 금액 셀은 NULL(미산정)
A5: date_KST | B5: workday | C5: open_at | D5: close_at | E5: scene_start | F5: scene_end | G5: elapsed_business_hours
A6: 46562 | B6: 1 | C6: 46562.375 | D6: 46562.75 | E6: 46562.42 | F6: 46568.479 | G6: =IF(B6=1,MAX(0,MIN(D6,F6)-MAX(C6,E6))*24,0) -> 7.9166667
A7: 46563 | B7: 1 | C7: 46563.375 | D7: 46563.75 | E7: 46562.42 | F7: 46568.479 | G7: =IF(B7=1,MAX(0,MIN(D7,F7)-MAX(C7,E7))*24,0) -> 9
A8: 46564 | B8: 0 | C8: 46564.375 | D8: 46564.75 | E8: 46562.42 | F8: 46568.479 | G8: =IF(B8=1,MAX(0,MIN(D8,F8)-MAX(C8,E8))*24,0) -> 0
A9: 46565 | B9: 0 | C9: 46565.375 | D9: 46565.75 | E9: 46562.42 | F9: 46568.479 | G9: =IF(B9=1,MAX(0,MIN(D9,F9)-MAX(C9,E9))*24,0) -> 0
A10: 46566 | B10: 1 | C10: 46566.375 | D10: 46566.75 | E10: 46562.42 | F10: 46568.479 | G10: =IF(B10=1,MAX(0,MIN(D10,F10)-MAX(C10,E10))*24,0) -> 9
A11: 46567 | B11: 1 | C11: 46567.375 | D11: 46567.75 | E11: 46562.42 | F11: 46568.479 | G11: =IF(B11=1,MAX(0,MIN(D11,F11)-MAX(C11,E11))*24,0) -> 9
A12: 46568 | B12: 1 | C12: 46568.375 | D12: 46568.75 | E12: 46562.42 | F12: 46568.479 | G12: =IF(B12=1,MAX(0,MIN(D12,F12)-MAX(C12,E12))*24,0) -> 2.5
A13: 46569 | B13: 1 | C13: 46569.375 | D13: 46569.75 | E13: 46562.42 | F13: 46568.479 | G13: =IF(B13=1,MAX(0,MIN(D13,F13)-MAX(C13,E13))*24,0) -> 0
A14: 46570 | B14: 1 | C14: 46570.375 | D14: 46570.75 | E14: 46562.42 | F14: 46568.479 | G14: =IF(B14=1,MAX(0,MIN(D14,F14)-MAX(C14,E14))*24,0) -> 0
A15: 46571 | B15: 0 | C15: 46571.375 | D15: 46571.75 | E15: 46562.42 | F15: 46568.479 | G15: =IF(B15=1,MAX(0,MIN(D15,F15)-MAX(C15,E15))*24,0) -> 0
A16: 46572 | B16: 0 | C16: 46572.375 | D16: 46572.75 | E16: 46562.42 | F16: 46568.479 | G16: =IF(B16=1,MAX(0,MIN(D16,F16)-MAX(C16,E16))*24,0) -> 0
A17: 46573 | B17: 1 | C17: 46573.375 | D17: 46573.75 | E17: 46562.42 | F17: 46568.479 | G17: =IF(B17=1,MAX(0,MIN(D17,F17)-MAX(C17,E17))*24,0) -> 0
... A24: 46580 | B24: 1 | C24: 46580.375 | D24: 46580.75 | E24: 46562.42 | F24: 46568.479 | G24: =IF(B24=1,MAX(0,MIN(D24,F24)-MAX(C24,E24))*24,0) -> 0

Sheet SC03검증
A1: INNONOW SC03검증 v0.3
A3: 장면3 확장 · 가상 업무연도 2027 · KST · 원 단위 · 빈 금액 셀은 NULL(미산정)
A5: check_id | B5: 검증항목 | C5: expected | D5: actual | E5: result
A6: V31 | B6: 기존2027 통합손익 | C6: 3299986680 | D6: =통합손익!K21 -> 3299986680 | E6: =IF(ABS(D6-C6)<0.00001,"일치","확인 필요") -> 일치
A7: V32 | B7: 기존 목표부족 | C7: 177303320 | D7: =통합손익!N21 -> 177303320 | E7: =IF(ABS(D7-C7)<0.00001,"일치","확인 필요") -> 일치
A8: V33 | B8: 후보수 | C8: 6 | D8: =SC03요약!B12 -> 6 | E8: =IF(ABS(D8-C8)<0.00001,"일치","확인 필요") -> 일치
A9: V34 | B9: 상세분석 포함후보 | C9: 4 | D9: =SC03요약!B13 -> 4 | E9: =IF(ABS(D9-C9)<0.00001,"일치","확인 필요") -> 일치
A10: V35 | B10: 이번분석 제외후보 | C10: 2 | D10: =SC03요약!B14 -> 2 | E10: =IF(ABS(D10-C10)<0.00001,"일치","확인 필요") -> 일치
A11: V36 | B11: 배정과제 | C11: 4 | D11: =SC03요약!B15 -> 4 | E11: =IF(ABS(D11-C11)<0.00001,"일치","확인 필요") -> 일치
A12: V37 | B12: 인수율 | C12: 1 | D12: =SC03요약!B17 -> 1 | E12: =IF(ABS(D12-C12)<0.00001,"일치","확인 필요") -> 일치
A13: V38 | B13: 잔여 질문수 | C13: 2 | D13: =COUNTA(SC03쟁점!A6:A7) -> 2 | E13: =IF(ABS(D13-C13)<0.00001,"일치","확인 필요") -> 일치
A14: V39 | B14: 기존부족 + 신규악화 − 전체부족 | C14: 0 | D14: =SC03요약!B10-SC03요약!B11-SC03요약!B9 -> 0 | E14: =IF(ABS(D14-C14)<0.00001,"일치","확인 필요") -> 일치
A15: V40 | B15: 영업시간 | C15: 37.416667 | D15: =SUM(SC03영업시간!G6:G24) -> 37.416667 | E15: =IF(ABS(D15-C15)<0.00001,"일치","확인 필요") -> 일치
A16: V41 | B16: 경과시간 | C16: 145.41667 | D16: =(SC03영업시간!F6-SC03영업시간!E6)*24 -> 145.41667 | E16: =IF(ABS(D16-C16)<0.00001,"일치","확인 필요") -> 일치

Sheet 통합모델손익
A1: INNONOW 통합모델손익 v0.3
A3: 장면3 확장 · 가상 업무연도 2027 · KST · 원 단위 · 빈 금액 셀은 NULL(미산정)
A5: 2027 Q3 모델 | B5: F01 공헌이익 | C5: 물량영향 | D5: 원가영향 | E5: 통합 공헌이익 | F5: 고정비 처리
A6: A-a | B6: =SUMIFS(월별계산!$K$6:$K$100,월별계산!$C$6:$C$100,A6,월별계산!$B$6:$B$100,">="&DATE(2027,7,1),월별계산!$B$6:$B$100,"<"&DATE(2027,10,1)) -> 336300000 | C6: =SUMIFS(월별계산!$M$6:$M$100,월별계산!$C$6:$C$100,A6,월별계산!$B$6:$B$100,">="&DATE(2027,7,1),월별계산!$B$6:$B$100,"<"&DATE(2027,10,1)) -> 0 | D6: =-SUMIFS(월별계산!$P$6:$P$100,월별계산!$C$6:$C$100,A6,월별계산!$B$6:$B$100,">="&DATE(2027,7,1),월별계산!$B$6:$B$100,"<"&DATE(2027,10,1)) -> -1345200 | E6: =SUMIFS(월별계산!$Q$6:$Q$100,월별계산!$C$6:$C$100,A6,월별계산!$B$6:$B$100,">="&DATE(2027,7,1),월별계산!$B$6:$B$100,"<"&DATE(2027,10,1)) -> 334954800 | F6: 공장 합계에서만 차감
A7: A-b | B7: =SUMIFS(월별계산!$K$6:$K$100,월별계산!$C$6:$C$100,A7,월별계산!$B$6:$B$100,">="&DATE(2027,7,1),월별계산!$B$6:$B$100,"<"&DATE(2027,10,1)) -> 560500000 | C7: =SUMIFS(월별계산!$M$6:$M$100,월별계산!$C$6:$C$100,A7,월별계산!$B$6:$B$100,">="&DATE(2027,7,1),월별계산!$B$6:$B$100,"<"&DATE(2027,10,1)) -> -14000000 | D7: =-SUMIFS(월별계산!$P$6:$P$100,월별계산!$C$6:$C$100,A7,월별계산!$B$6:$B$100,">="&DATE(2027,7,1),월별계산!$B$6:$B$100,"<"&DATE(2027,10,1)) -> -3279000 | E7: =SUMIFS(월별계산!$Q$6:$Q$100,월별계산!$C$6:$C$100,A7,월별계산!$B$6:$B$100,">="&DATE(2027,7,1),월별계산!$B$6:$B$100,"<"&DATE(2027,10,1)) -> 543221000 | F7: 공장 합계에서만 차감
A8: A-c | B8: =SUMIFS(월별계산!$K$6:$K$100,월별계산!$C$6:$C$100,A8,월별계산!$B$6:$B$100,">="&DATE(2027,7,1),월별계산!$B$6:$B$100,"<"&DATE(2027,10,1)) -> 490644000 | C8: =SUMIFS(월별계산!$M$6:$M$100,월별계산!$C$6:$C$100,A8,월별계산!$B$6:$B$100,">="&DATE(2027,7,1),월별계산!$B$6:$B$100,"<"&DATE(2027,10,1)) -> 0 | D8: =-SUMIFS(월별계산!$P$6:$P$100,월별계산!$C$6:$C$100,A8,월별계산!$B$6:$B$100,">="&DATE(2027,7,1),월별계산!$B$6:$B$100,"<"&DATE(2027,10,1)) -> 0 | E8: =SUMIFS(월별계산!$Q$6:$Q$100,월별계산!$C$6:$C$100,A8,월별계산!$B$6:$B$100,">="&DATE(2027,7,1),월별계산!$B$6:$B$100,"<"&DATE(2027,10,1)) -> 490644000 | F8: 공장 합계에서만 차감
A9: A-d | B9: =SUMIFS(월별계산!$K$6:$K$100,월별계산!$C$6:$C$100,A9,월별계산!$B$6:$B$100,">="&DATE(2027,7,1),월별계산!$B$6:$B$100,"<"&DATE(2027,10,1)) -> 372450000 | C9: =SUMIFS(월별계산!$M$6:$M$100,월별계산!$C$6:$C$100,A9,월별계산!$B$6:$B$100,">="&DATE(2027,7,1),월별계산!$B$6:$B$100,"<"&DATE(2027,10,1)) -> 0 | D9: =-SUMIFS(월별계산!$P$6:$P$100,월별계산!$C$6:$C$100,A9,월별계산!$B$6:$B$100,">="&DATE(2027,7,1),월별계산!$B$6:$B$100,"<"&DATE(2027,10,1)) -> 0 | E9: =SUMIFS(월별계산!$Q$6:$Q$100,월별계산!$C$6:$C$100,A9,월별계산!$B$6:$B$100,">="&DATE(2027,7,1),월별계산!$B$6:$B$100,"<"&DATE(2027,10,1)) -> 372450000 | F9: 공장 합계에서만 차감
A10: A-e | B10: =SUMIFS(월별계산!$K$6:$K$100,월별계산!$C$6:$C$100,A10,월별계산!$B$6:$B$100,">="&DATE(2027,7,1),월별계산!$B$6:$B$100,"<"&DATE(2027,10,1)) -> 157698000 | C10: =SUMIFS(월별계산!$M$6:$M$100,월별계산!$C$6:$C$100,A10,월별계산!$B$6:$B$100,">="&DATE(2027,7,1),월별계산!$B$6:$B$100,"<"&DATE(2027,10,1)) -> 0 | D10: =-SUMIFS(월별계산!$P$6:$P$100,월별계산!$C$6:$C$100,A10,월별계산!$B$6:$B$100,">="&DATE(2027,7,1),월별계산!$B$6:$B$100,"<"&DATE(2027,10,1)) -> 0 | E10: =SUMIFS(월별계산!$Q$6:$Q$100,월별계산!$C$6:$C$100,A10,월별계산!$B$6:$B$100,">="&DATE(2027,7,1),월별계산!$B$6:$B$100,"<"&DATE(2027,10,1)) -> 157698000 | F10: 공장 합계에서만 차감

Sheet 검토요약_v02
A1: INNONOW 통합 가상 데이터 확장 v0.2
A3: 장면 1·2 연결 / 기존사업 A제품·울산공장 / 전 항목 가상 데이터 / 기본안은 2027-07-01 적용
A5: 구분 | B5: 핵심 항목 | C5: 값·결과 | D5: 설명
A6: 검토 | B6: 공통부품 기존 → 요청 → 협상 | C6: 2,000 → 2,200 → 2,120원 | D6: 이번 가상값 제안. 기존단가 대비 요청10%, 협상6%. a·b 각1개 사용.
A7: 구매 | B7: 당해연도 잔여 구매 증가 | C7: =단가안비교!H8 -> 9364320 | D7: 협상안 / 2027-07~12 / 원
A8: 구매 | B8: 향후12개월 구매 증가 | C8: =단가안비교!I8 -> 18817440 | D8: 협상안 / 2027-07~2028-06 / 원
A9: 협상 | B9: 요청 대비 12개월 부담 감소 | C9: =단가안비교!N8 -> 12544960 | D9: 원. 가격 인상 부담은 남아 있으며 위험 해소로 보지 않음.
A10: 판단 | B10: 종합위험 / 대표 승인 | C10: =단가안비교!L9&" / "&단가안비교!M9 -> 중요 / 대표 대상 | D10: 비율 위험은 관심, 구매 증가액 위험은 중요. 결재 기준은 별도 적용.
A11: 손익 | B11: 2027 물량 감소 순영향 | C11: =통합손익!I21 -> -14000000 | D11: 장면1 F01→F02 차이 / 원
A12: 손익 | B12: 2027 단가 인상 추가 영향 | C12: =통합손익!J21 -> -9364320 | D12: 장면2 F02 수량 × 승인단가 인상 / 원
A13: 손익 | B13: 2027 통합 관리손익 | C13: =통합손익!K21 -> 3299986680 | D13: 고정비 차감 후 공장 범위 / 원
A14: 손익 | B14: 2027 Target 대비 부족 | C14: =통합손익!N21 -> 177303320 | D14: Target은 변경하지 않음 / 원
A15: 가정 | B15: 2028 내부가정 | C15: 동일월 F01의 97% | D15: 2028-01~07 제공. 판매단가·원가·월고정비는 유지. 실제 고객계획 아님.
A16: 시연 | B16: 단계별 적재 | C16: D00 초기, 이후 실행 시 생성 | D16: 향후 승인·협상 기록은 기대 fixture이며 시작 화면에 미리 노출하지 않음.
A17: 시연 | B17: 외부 협상기한 | C17: 담당자가 건별 입력 | D17: 가상 기본 기한 2027-06-21 18:00. 내부 SLA와 구분.
A18: 개발 | B18: 인계 범위 | C18: 단가·물량·원가·손익·증빙·상태·예외 | D18: U21~27, S01~14, CT21~30, D00~12 연결. 권한/API 상세는 다음 구현명세.
A19: 확인 | B19: 검토 권장 위치 | C19: 설정 / 단가안비교 / 통합손익 | D19: 가상 가격·2028 감소가정·기본 업무일정의 자연스러움을 우선 검토.
A20: 한계 | B20: 구매 증가와 CM 감소의 동일성 | C20: 시차0·재고0 단순화 | D20: 일반 회계 등식이 아님. 두 지표는 별도 보관. 향후12개월 Target은 미설정.

Sheet SC04비교
A1: INNONOW SC04비교 v0.4
A3: 원 단위. 보고본 REP41-v1 → 회의 판단본 DEC41-v2. 기준 관리손익에 더하는 순증분이며 실제 실적이 아닙니다.
A5: 대안ID | B5: 대응안 | C5: 보고효과 | D5: 판단효과 | E5: 회의조정 | F5: 정상연효과 | G5: 우선순위 | H5: 대표결정 | I5: 책임임원 | J5: 시점·리스크·조건
A6: ALT41 | B6: 부분 공정·외주 조정 | C6: =SUMIFS(SC04월효과!$O$6:$O$41,SC04월효과!$B$6:$B$41,"REP41-v1",SC04월효과!$C$6:$C$41,A6) -> 86000000 | D6: =SUMIFS(SC04월효과!$O$6:$O$41,SC04월효과!$B$6:$B$41,"DEC41-v2",SC04월효과!$C$6:$C$41,A6) -> 86000000 | E6: =D6-C6 -> 0 | F6: =SC04가정!T6 -> 216000000 | G6: 2 | H6: APPROVED | I6: EX-PROD | J6: 8월 월3,000대분 적용. 7/7 시범품질·공급능력 검토 완료 가정. 전환·협력사 리스크는 후속 추적.
A7: ALT42 | B7: 구매조건·긴급구매 개선 | C7: =SUMIFS(SC04월효과!$O$6:$O$41,SC04월효과!$B$6:$B$41,"REP41-v1",SC04월효과!$C$6:$C$41,A7) -> 45000000 | D7: =SUMIFS(SC04월효과!$O$6:$O$41,SC04월효과!$B$6:$B$41,"DEC41-v2",SC04월효과!$C$6:$C$41,A7) -> 35600000 | E7: =D7-C7 -> -9400000 | F7: =SC04가정!T7 -> 112800000 | G7: 1 | H7: CONDITIONAL | I7: EX-BUY | J7: 8월에서 9월로 효과 시작 조정. 생산·구매 협조 조건 CON41 완료 전 실행 착수 제한.
A8: ALT43 | B8: 기존 승인 대체 공급업체 | C8: =SUMIFS(SC04월효과!$O$6:$O$41,SC04월효과!$B$6:$B$41,"REP41-v1",SC04월효과!$C$6:$C$41,A8) -> 6200000 | D8: =SUMIFS(SC04월효과!$O$6:$O$41,SC04월효과!$B$6:$B$41,"DEC41-v2",SC04월효과!$C$6:$C$41,A8) -> 6200000 | E8: =D8-C8 -> 0 | F8: =SC04가정!T8 -> 28800000 | G8: 3 | H8: APPROVED | I8: EX-BUY | J8: 10월 적용. 기존 승인 품목 범위·월 6,000개 공급능력·물류 검토 완료 가정.
A9: TOTAL | B9: 3개 실행안 | C9: =SUM(C6:C8) -> 137200000 | D9: =SUM(D6:D8) -> 127800000 | E9: =SUM(E6:E8) -> -9400000 | F9: =SUM(F6:F8) -> 357600000 | H9: 2개 승인·1개 조건부 | I9: USR-CFO | J9: 정상연효과는 일회성 비용 제외. 예산과 개선효과를 혼용하지 않음.
A10: EXCL44 | B10: 고객·모델 물량 배분 | H10: EXCLUDED | I10: EX-SALES | J10: AT33 검토 결과: 고객 생산계획 배정 변경 근거 부족. 실행과제 미생성.

Sheet SC04월손익
A1: INNONOW SC04월손익 v0.4
A3: 공장 관리손익. 본사비·금융비·세금 제외. Target·기준 전망 유지. 조건부 제외전망은 ALT42 순효과 전체를 제외하는 비교이며 별도 승인안이 아닙니다.
A5: 기간 | B5: Target | C5: SC03기준손익 | D5: 보고순효과 | E5: 판단순효과 | F5: 보고후전망 | G5: 판단후전망 | H5: 잔여부족 | I5: 조건부제외전망 | J5: 조건부제외부족
A6: 46388 | B6: =통합손익!M6 -> 310340000 | C6: =통합손익!K6 -> 309349000 | D6: =SUMIFS(SC04월효과!$O$6:$O$41,SC04월효과!$B$6:$B$41,"REP41-v1",SC04월효과!$D$6:$D$41,A6) -> 0 | E6: =SUMIFS(SC04월효과!$O$6:$O$41,SC04월효과!$B$6:$B$41,"DEC41-v2",SC04월효과!$D$6:$D$41,A6) -> 0 | F6: =C6+D6 -> 309349000 | G6: =C6+E6 -> 309349000 | H6: =B6-G6 -> 991000 | I6: =G6-SUMIFS(SC04월효과!$O$6:$O$41,SC04월효과!$B$6:$B$41,"DEC41-v2",SC04월효과!$D$6:$D$41,A6,SC04월효과!$C$6:$C$41,"ALT42") -> 309349000 | J6: =B6-I6 -> 991000
A7: 46419 | B7: =통합손익!M7 -> 230300000 | C7: =통합손익!K7 -> 226547000 | D7: =SUMIFS(SC04월효과!$O$6:$O$41,SC04월효과!$B$6:$B$41,"REP41-v1",SC04월효과!$D$6:$D$41,A7) -> 0 | E7: =SUMIFS(SC04월효과!$O$6:$O$41,SC04월효과!$B$6:$B$41,"DEC41-v2",SC04월효과!$D$6:$D$41,A7) -> 0 | F7: =C7+D7 -> 226547000 | G7: =C7+E7 -> 226547000 | H7: =B7-G7 -> 3753000 | I7: =G7-SUMIFS(SC04월효과!$O$6:$O$41,SC04월효과!$B$6:$B$41,"DEC41-v2",SC04월효과!$D$6:$D$41,A7,SC04월효과!$C$6:$C$41,"ALT42") -> 226547000 | J7: =B7-I7 -> 3753000
A8: 46447 | B8: =통합손익!M8 -> 330350000 | C8: =통합손익!K8 -> 322633000 | D8: =SUMIFS(SC04월효과!$O$6:$O$41,SC04월효과!$B$6:$B$41,"REP41-v1",SC04월효과!$D$6:$D$41,A8) -> 0 | E8: =SUMIFS(SC04월효과!$O$6:$O$41,SC04월효과!$B$6:$B$41,"DEC41-v2",SC04월효과!$D$6:$D$41,A8) -> 0 | F8: =C8+D8 -> 322633000 | G8: =C8+E8 -> 322633000 | H8: =B8-G8 -> 7717000 | I8: =G8-SUMIFS(SC04월효과!$O$6:$O$41,SC04월효과!$B$6:$B$41,"DEC41-v2",SC04월효과!$D$6:$D$41,A8,SC04월효과!$C$6:$C$41,"ALT42") -> 322633000 | J8: =B8-I8 -> 7717000
A9: 46478 | B9: =통합손익!M9 -> 297000000 | C9: =통합손익!K9 -> 286430000 | D9: =SUMIFS(SC04월효과!$O$6:$O$41,SC04월효과!$B$6:$B$41,"REP41-v1",SC04월효과!$D$6:$D$41,A9) -> 0 | E9: =SUMIFS(SC04월효과!$O$6:$O$41,SC04월효과!$B$6:$B$41,"DEC41-v2",SC04월효과!$D$6:$D$41,A9) -> 0 | F9: =C9+D9 -> 286430000 | G9: =C9+E9 -> 286430000 | H9: =B9-G9 -> 10570000 | I9: =G9-SUMIFS(SC04월효과!$O$6:$O$41,SC04월효과!$B$6:$B$41,"DEC41-v2",SC04월효과!$D$6:$D$41,A9,SC04월효과!$C$6:$C$41,"ALT42") -> 286430000 | J9: =B9-I9 -> 10570000
A10: 46508 | B10: =통합손익!M10 -> 283660000 | C10: =통합손익!K10 -> 270161000 | D10: =SUMIFS(SC04월효과!$O$6:$O$41,SC04월효과!$B$6:$B$41,"REP41-v1",SC04월효과!$D$6:$D$41,A10) -> 0 | E10: =SUMIFS(SC04월효과!$O$6:$O$41,SC04월효과!$B$6:$B$41,"DEC41-v2",SC04월효과!$D$6:$D$41,A10) -> 0 | F10: =C10+D10 -> 270161000 | G10: =C10+E10 -> 270161000 | H10: =B10-G10 -> 13499000 | I10: =G10-SUMIFS(SC04월효과!$O$6:$O$41,SC04월효과!$B$6:$B$41,"DEC41-v2",SC04월효과!$D$6:$D$41,A10,SC04월효과!$C$6:$C$41,"ALT42") -> 270161000 | J10: =B10-I10 -> 13499000
A11: 46539 | B11: =통합손익!M11 -> 297000000 | C11: =통합손익!K11 -> 280030000 | D11: =SUMIFS(SC04월효과!$O$6:$O$41,SC04월효과!$B$6:$B$41,"REP41-v1",SC04월효과!$D$6:$D$41,A11) -> 0 | E11: =SUMIFS(SC04월효과!$O$6:$O$41,SC04월효과!$B$6:$B$41,"DEC41-v2",SC04월효과!$D$6:$D$41,A11) -> 0 | F11: =C11+D11 -> 280030000 | G11: =C11+E11 -> 280030000 | H11: =B11-G11 -> 16970000 | I11: =G11-SUMIFS(SC04월효과!$O$6:$O$41,SC04월효과!$B$6:$B$41,"DEC41-v2",SC04월효과!$D$6:$D$41,A11,SC04월효과!$C$6:$C$41,"ALT42") -> 280030000 | J11: =B11-I11 -> 16970000
A12: 46569 | B12: =통합손익!M12 -> 297000000 | C12: =통합손익!K12 -> 264518000 | D12: =SUMIFS(SC04월효과!$O$6:$O$41,SC04월효과!$B$6:$B$41,"REP41-v1",SC04월효과!$D$6:$D$41,A12) -> -4000000 | E12: =SUMIFS(SC04월효과!$O$6:$O$41,SC04월효과!$B$6:$B$41,"DEC41-v2",SC04월효과!$D$6:$D$41,A12) -> -4000000 | F12: =C12+D12 -> 260518000 | G12: =C12+E12 -> 260518000 | H12: =B12-G12 -> 36482000 | I12: =G12-SUMIFS(SC04월효과!$O$6:$O$41,SC04월효과!$B$6:$B$41,"DEC41-v2",SC04월효과!$D$6:$D$41,A12,SC04월효과!$C$6:$C$41,"ALT42") -> 260518000 | J12: =B12-I12 -> 36482000
A13: 46600 | B13: =통합손익!M13 -> 243640000 | C13: =통합손익!K13 -> 226557680 | D13: =SUMIFS(SC04월효과!$O$6:$O$41,SC04월효과!$B$6:$B$41,"REP41-v1",SC04월효과!$D$6:$D$41,A13) -> 25400000 | E13: =SUMIFS(SC04월효과!$O$6:$O$41,SC04월효과!$B$6:$B$41,"DEC41-v2",SC04월효과!$D$6:$D$41,A13) -> 16000000 | F13: =C13+D13 -> 251957680 | G13: =C13+E13 -> 242557680 | H13: =B13-G13 -> 1082320 | I13: =G13-SUMIFS(SC04월효과!$O$6:$O$41,SC04월효과!$B$6:$B$41,"DEC41-v2",SC04월효과!$D$6:$D$41,A13,SC04월효과!$C$6:$C$41,"ALT42") -> 244557680 | J13: =B13-I13 -> -917680
A14: 46631 | B14: =통합손익!M14 -> 317010000 | C14: =통합손익!K14 -> 297892120 | D14: =SUMIFS(SC04월효과!$O$6:$O$41,SC04월효과!$B$6:$B$41,"REP41-v1",SC04월효과!$D$6:$D$41,A14) -> 26400000 | E14: =SUMIFS(SC04월효과!$O$6:$O$41,SC04월효과!$B$6:$B$41,"DEC41-v2",SC04월효과!$D$6:$D$41,A14) -> 26400000 | F14: =C14+D14 -> 324292120 | G14: =C14+E14 -> 324292120 | H14: =B14-G14 -> -7282120 | I14: =G14-SUMIFS(SC04월효과!$O$6:$O$41,SC04월효과!$B$6:$B$41,"DEC41-v2",SC04월효과!$D$6:$D$41,A14,SC04월효과!$C$6:$C$41,"ALT42") -> 314892120 | J14: =B14-I14 -> 2117880
A15: 46661 | B15: =통합손익!M15 -> 310340000 | C15: =통합손익!K15 -> 291401080 | D15: =SUMIFS(SC04월효과!$O$6:$O$41,SC04월효과!$B$6:$B$41,"REP41-v1",SC04월효과!$D$6:$D$41,A15) -> 29800000 | E15: =SUMIFS(SC04월효과!$O$6:$O$41,SC04월효과!$B$6:$B$41,"DEC41-v2",SC04월효과!$D$6:$D$41,A15) -> 29800000 | F15: =C15+D15 -> 321201080 | G15: =C15+E15 -> 321201080 | H15: =B15-G15 -> -10861080 | I15: =G15-SUMIFS(SC04월효과!$O$6:$O$41,SC04월효과!$B$6:$B$41,"DEC41-v2",SC04월효과!$D$6:$D$41,A15,SC04월효과!$C$6:$C$41,"ALT42") -> 311801080 | J15: =B15-I15 -> -1461080
A16: 46692 | B16: =통합손익!M16 -> 297000000 | C16: =통합손익!K16 -> 278434000 | D16: =SUMIFS(SC04월효과!$O$6:$O$41,SC04월효과!$B$6:$B$41,"REP41-v1",SC04월효과!$D$6:$D$41,A16) -> 29800000 | E16: =SUMIFS(SC04월효과!$O$6:$O$41,SC04월효과!$B$6:$B$41,"DEC41-v2",SC04월효과!$D$6:$D$41,A16) -> 29800000 | F16: =C16+D16 -> 308234000 | G16: =C16+E16 -> 308234000 | H16: =B16-G16 -> -11234000 | I16: =G16-SUMIFS(SC04월효과!$O$6:$O$41,SC04월효과!$B$6:$B$41,"DEC41-v2",SC04월효과!$D$6:$D$41,A16,SC04월효과!$C$6:$C$41,"ALT42") -> 298834000 | J16: =B16-I16 -> -1834000
A17: 46722 | B17: =통합손익!M17 -> 263650000 | C17: =통합손익!K17 -> 246033800 | D17: =SUMIFS(SC04월효과!$O$6:$O$41,SC04월효과!$B$6:$B$41,"REP41-v1",SC04월효과!$D$6:$D$41,A17) -> 29800000 | E17: =SUMIFS(SC04월효과!$O$6:$O$41,SC04월효과!$B$6:$B$41,"DEC41-v2",SC04월효과!$D$6:$D$41,A17) -> 29800000 | F17: =C17+D17 -> 275833800 | G17: =C17+E17 -> 275833800 | H17: =B17-G17 -> -12183800 | I17: =G17-SUMIFS(SC04월효과!$O$6:$O$41,SC04월효과!$B$6:$B$41,"DEC41-v2",SC04월효과!$D$6:$D$41,A17,SC04월효과!$C$6:$C$41,"ALT42") -> 266433800 | J17: =B17-I17 -> -2783800
A18: 2027 연간 | B18: =SUM(B6:B17) -> 3477290000 | C18: =SUM(C6:C17) -> 3299986680 | D18: =SUM(D6:D17) -> 137200000 | E18: =SUM(E6:E17) -> 127800000 | F18: =SUM(F6:F17) -> 3437186680 | G18: =SUM(G6:G17) -> 3427786680 | H18: =SUM(H6:H17) -> 49503320 | I18: =SUM(I6:I17) -> 3392186680 | J18: =SUM(J6:J17) -> 85103320
A19: 2027 Q3 | B19: =SUM(B12:B14) -> 857650000 | C19: =SUM(C12:C14) -> 788967800 | D19: =SUM(D12:D14) -> 47800000 | E19: =SUM(E12:E14) -> 38400000 | F19: =SUM(F12:F14) -> 836767800 | G19: =SUM(G12:G14) -> 827367800 | H19: =SUM(H12:H14) -> 30282200 | I19: =SUM(I12:I14) -> 819967800 | J19: =SUM(J12:J14) -> 37682200
A20: 2027 Q4 | B20: =SUM(B15:B17) -> 870990000 | C20: =SUM(C15:C17) -> 815868880 | D20: =SUM(D15:D17) -> 89400000 | E20: =SUM(E15:E17) -> 89400000 | F20: =SUM(F15:F17) -> 905268880 | G20: =SUM(G15:G17) -> 905268880 | H20: =SUM(H15:H17) -> -34278880 | I20: =SUM(I15:I17) -> 877068880 | J20: =SUM(J15:J17) -> -6078880
A21: 2027 잔여7~12월 | B21: =SUM(B12:B17) -> 1728640000 | C21: =SUM(C12:C17) -> 1604836680 | D21: =SUM(D12:D17) -> 137200000 | E21: =SUM(E12:E17) -> 127800000 | F21: =SUM(F12:F17) -> 1742036680 | G21: =SUM(G12:G17) -> 1732636680 | H21: =SUM(H12:H17) -> -3996680 | I21: =SUM(I12:I17) -> 1697036680 | J21: =SUM(J12:J17) -> 31603320

Sheet SC04가정
A1: INNONOW SC04가정 v0.4
A3: 2026-10-23 검토 반영: ALT41 대상량·회피단가, ALT42 긴급비용 가상 가정 수정. 원 단위·VAT 제외. 정상연효과는 12개월 참고값.
A5: 대안ID | B5: 대안명 | C5: 분석과제 | D5: 모델 | E5: 비용대상 | F5: 보고 시작 | G5: 판단 시작 | H5: 월 대상량 | I5: 회피단가 | J5: 추가단가 | K5: 물류단가 | L5: 긴급 전 | M5: 긴급 후 | N5: 건당비용 | O5: 월지원비 | P5: 일회성비 | Q5: 일회성월 | R5: 전용예산 | S5: 정상월효과 | T5: 정상연효과 | U5: 초안중복할인단가
A6: ALT41 | B6: 부분 공정·외주 조정 | C6: AT31 | D6: A-a | E6: PR-A01 | F6: 46600 | G6: 46600 | H6: 3000 | I6: 15000 | J6: 8000 | K6: 1000 | L6: 0 | M6: 0 | N6: 0 | O6: 0 | P6: 4000000 | Q6: 46569 | R6: 8000000 | S6: =H6*(I6-J6-K6)-O6 -> 18000000 | T6: =S6*12 -> 216000000
A7: ALT42 | B7: 구매조건·긴급구매 개선 | C7: AT32 | D7: A-b | E7: URG-B01 | F7: 46600 | G7: 46631 | H7: 0 | I7: 0 | J7: 0 | K7: 0 | L7: 12 | M7: 4 | N7: 1200000 | O7: 200000 | P7: 2000000 | Q7: 46600 | R7: 6000000 | S7: =(L7-M7)*N7-O7 -> 9400000 | T7: =S7*12 -> 112800000 | U7: 100
A8: ALT43 | B8: 기존 승인 대체 공급업체 | C8: AT32 | D8: A-b | E8: P-MAT02 | F8: 46661 | G8: 46661 | H8: 6000 | I8: 5000 | J8: 4500 | K8: 100 | L8: 0 | M8: 0 | N8: 0 | O8: 0 | P8: 1000000 | Q8: 46631 | R8: 4000000 | S8: =H8*(I8-J8-K8)-O8 -> 2400000 | T8: =S8*12 -> 28800000

Sheet SC04월효과
A1: INNONOW SC04월효과 v0.4
A3: 보고본과 회의 판단본은 같은 계산 구조의 버전별 이력. 합산할 때 반드시 버전 필터. ALT42 단가할인 초안은 ALT43에 포함되어 전액 중복 제거.
A5: row_id | B5: 판단버전 | C5: 대안ID | D5: 월 | E5: 적용시작 | F5: 적용여부 | G5: 대상량 | H5: 회피액 | I5: 추가거래비 | J5: 추가물류비 | K5: 운영지원비 | L5: 일회성비 | M5: 초안할인 | N5: 중복제거 | O5: 최종순효과 | P5: 고정비절감 | Q5: 효과상태 | R5: 근거ID
A6: REP41-v1|ALT41|2027-07 | B6: REP41-v1 | C6: ALT41 | D6: 46569 | E6: =SC04가정!F6 -> 46600 | F6: =IF(D6>=E6,1,0) -> 0 | G6: =F6*SC04가정!H6 -> 0 | H6: =G6*SC04가정!I6 -> 0 | I6: =G6*SC04가정!J6 -> 0 | J6: =G6*SC04가정!K6 -> 0 | K6: =F6*SC04가정!O6 -> 0 | L6: =IF(D6=SC04가정!Q6,SC04가정!P6,0) -> 4000000 | M6: =0 -> 0 | N6: =M6 -> 0 | O6: =H6-I6-J6-K6-L6+M6-N6 -> -4000000 | P6: 0 | Q6: 보고 예상 | R6: EVDC41
A7: REP41-v1|ALT41|2027-08 | B7: REP41-v1 | C7: ALT41 | D7: 46600 | E7: =SC04가정!F6 -> 46600 | F7: =IF(D7>=E7,1,0) -> 1 | G7: =F7*SC04가정!H6 -> 3000 | H7: =G7*SC04가정!I6 -> 45000000 | I7: =G7*SC04가정!J6 -> 24000000 | J7: =G7*SC04가정!K6 -> 3000000 | K7: =F7*SC04가정!O6 -> 0 | L7: =IF(D7=SC04가정!Q6,SC04가정!P6,0) -> 0 | M7: =0 -> 0 | N7: =M7 -> 0 | O7: =H7-I7-J7-K7-L7+M7-N7 -> 18000000 | P7: 0 | Q7: 보고 예상 | R7: EVDC41
A8: REP41-v1|ALT41|2027-09 | B8: REP41-v1 | C8: ALT41 | D8: 46631 | E8: =SC04가정!F6 -> 46600 | F8: =IF(D8>=E8,1,0) -> 1 | G8: =F8*SC04가정!H6 -> 3000 | H8: =G8*SC04가정!I6 -> 45000000 | I8: =G8*SC04가정!J6 -> 24000000 | J8: =G8*SC04가정!K6 -> 3000000 | K8: =F8*SC04가정!O6 -> 0 | L8: =IF(D8=SC04가정!Q6,SC04가정!P6,0) -> 0 | M8: =0 -> 0 | N8: =M8 -> 0 | O8: =H8-I8-J8-K8-L8+M8-N8 -> 18000000 | P8: 0 | Q8: 보고 예상 | R8: EVDC41
A9: REP41-v1|ALT41|2027-10 | B9: REP41-v1 | C9: ALT41 | D9: 46661 | E9: =SC04가정!F6 -> 46600 | F9: =IF(D9>=E9,1,0) -> 1 | G9: =F9*SC04가정!H6 -> 3000 | H9: =G9*SC04가정!I6 -> 45000000 | I9: =G9*SC04가정!J6 -> 24000000 | J9: =G9*SC04가정!K6 -> 3000000 | K9: =F9*SC04가정!O6 -> 0 | L9: =IF(D9=SC04가정!Q6,SC04가정!P6,0) -> 0 | M9: =0 -> 0 | N9: =M9 -> 0 | O9: =H9-I9-J9-K9-L9+M9-N9 -> 18000000 | P9: 0 | Q9: 보고 예상 | R9: EVDC41
A10: REP41-v1|ALT41|2027-11 | B10: REP41-v1 | C10: ALT41 | D10: 46692 | E10: =SC04가정!F6 -> 46600 | F10: =IF(D10>=E10,1,0) -> 1 | G10: =F10*SC04가정!H6 -> 3000 | H10: =G10*SC04가정!I6 -> 45000000 | I10: =G10*SC04가정!J6 -> 24000000 | J10: =G10*SC04가정!K6 -> 3000000 | K10: =F10*SC04가정!O6 -> 0 | L10: =IF(D10=SC04가정!Q6,SC04가정!P6,0) -> 0 | M10: =0 -> 0 | N10: =M10 -> 0 | O10: =H10-I10-J10-K10-L10+M10-N10 -> 18000000 | P10: 0 | Q10: 보고 예상 | R10: EVDC41
A11: REP41-v1|ALT41|2027-12 | B11: REP41-v1 | C11: ALT41 | D11: 46722 | E11: =SC04가정!F6 -> 46600 | F11: =IF(D11>=E11,1,0) -> 1 | G11: =F11*SC04가정!H6 -> 3000 | H11: =G11*SC04가정!I6 -> 45000000 | I11: =G11*SC04가정!J6 -> 24000000 | J11: =G11*SC04가정!K6 -> 3000000 | K11: =F11*SC04가정!O6 -> 0 | L11: =IF(D11=SC04가정!Q6,SC04가정!P6,0) -> 0 | M11: =0 -> 0 | N11: =M11 -> 0 | O11: =H11-I11-J11-K11-L11+M11-N11 -> 18000000 | P11: 0 | Q11: 보고 예상 | R11: EVDC41
A12: REP41-v1|ALT42|2027-07 | B12: REP41-v1 | C12: ALT42 | D12: 46569 | E12: =SC04가정!F7 -> 46600 | F12: =IF(D12>=E12,1,0) -> 0 | G12: =F12*SC04가정!H7 -> 0 | H12: =F12*(SC04가정!L7-SC04가정!M7)*SC04가정!N7 -> 0 | I12: =G12*SC04가정!J7 -> 0 | J12: =G12*SC04가정!K7 -> 0 | K12: =F12*SC04가정!O7 -> 0 | L12: =IF(D12=SC04가정!Q7,SC04가정!P7,0) -> 0 | M12: =IF(D12>=SC04가정!G8,SC04가정!H8*SC04가정!U7,0) -> 0 | N12: =M12 -> 0 | O12: =H12-I12-J12-K12-L12+M12-N12 -> 0 | P12: 0 | Q12: 보고 예상 | R12: EVDC42
A13: REP41-v1|ALT42|2027-08 | B13: REP41-v1 | C13: ALT42 | D13: 46600 | E13: =SC04가정!F7 -> 46600 | F13: =IF(D13>=E13,1,0) -> 1 | G13: =F13*SC04가정!H7 -> 0 | H13: =F13*(SC04가정!L7-SC04가정!M7)*SC04가정!N7 -> 9600000 | I13: =G13*SC04가정!J7 -> 0 | J13: =G13*SC04가정!K7 -> 0 | K13: =F13*SC04가정!O7 -> 200000 | L13: =IF(D13=SC04가정!Q7,SC04가정!P7,0) -> 2000000 | M13: =IF(D13>=SC04가정!G8,SC04가정!H8*SC04가정!U7,0) -> 0 | N13: =M13 -> 0 | O13: =H13-I13-J13-K13-L13+M13-N13 -> 7400000 | P13: 0 | Q13: 보고 예상 | R13: EVDC42
A14: REP41-v1|ALT42|2027-09 | B14: REP41-v1 | C14: ALT42 | D14: 46631 | E14: =SC04가정!F7 -> 46600 | F14: =IF(D14>=E14,1,0) -> 1 | G14: =F14*SC04가정!H7 -> 0 | H14: =F14*(SC04가정!L7-SC04가정!M7)*SC04가정!N7 -> 9600000 | I14: =G14*SC04가정!J7 -> 0 | J14: =G14*SC04가정!K7 -> 0 | K14: =F14*SC04가정!O7 -> 200000 | L14: =IF(D14=SC04가정!Q7,SC04가정!P7,0) -> 0 | M14: =IF(D14>=SC04가정!G8,SC04가정!H8*SC04가정!U7,0) -> 0 | N14: =M14 -> 0 | O14: =H14-I14-J14-K14-L14+M14-N14 -> 9400000 | P14: 0 | Q14: 보고 예상 | R14: EVDC42
A15: REP41-v1|ALT42|2027-10 | B15: REP41-v1 | C15: ALT42 | D15: 46661 | E15: =SC04가정!F7 -> 46600 | F15: =IF(D15>=E15,1,0) -> 1 | G15: =F15*SC04가정!H7 -> 0 | H15: =F15*(SC04가정!L7-SC04가정!M7)*SC04가정!N7 -> 9600000 | I15: =G15*SC04가정!J7 -> 0 | J15: =G15*SC04가정!K7 -> 0 | K15: =F15*SC04가정!O7 -> 200000 | L15: =IF(D15=SC04가정!Q7,SC04가정!P7,0) -> 0 | M15: =IF(D15>=SC04가정!G8,SC04가정!H8*SC04가정!U7,0) -> 600000 | N15: =M15 -> 600000 | O15: =H15-I15-J15-K15-L15+M15-N15 -> 9400000 | P15: 0 | Q15: 보고 예상 | R15: EVDC42
A16: REP41-v1|ALT42|2027-11 | B16: REP41-v1 | C16: ALT42 | D16: 46692 | E16: =SC04가정!F7 -> 46600 | F16: =IF(D16>=E16,1,0) -> 1 | G16: =F16*SC04가정!H7 -> 0 | H16: =F16*(SC04가정!L7-SC04가정!M7)*SC04가정!N7 -> 9600000 | I16: =G16*SC04가정!J7 -> 0 | J16: =G16*SC04가정!K7 -> 0 | K16: =F16*SC04가정!O7 -> 200000 | L16: =IF(D16=SC04가정!Q7,SC04가정!P7,0) -> 0 | M16: =IF(D16>=SC04가정!G8,SC04가정!H8*SC04가정!U7,0) -> 600000 | N16: =M16 -> 600000 | O16: =H16-I16-J16-K16-L16+M16-N16 -> 9400000 | P16: 0 | Q16: 보고 예상 | R16: EVDC42
A17: REP41-v1|ALT42|2027-12 | B17: REP41-v1 | C17: ALT42 | D17: 46722 | E17: =SC04가정!F7 -> 46600 | F17: =IF(D17>=E17,1,0) -> 1 | G17: =F17*SC04가정!H7 -> 0 | H17: =F17*(SC04가정!L7-SC04가정!M7)*SC04가정!N7 -> 9600000 | I17: =G17*SC04가정!J7 -> 0 | J17: =G17*SC04가정!K7 -> 0 | K17: =F17*SC04가정!O7 -> 200000 | L17: =IF(D17=SC04가정!Q7,SC04가정!P7,0) -> 0 | M17: =IF(D17>=SC04가정!G8,SC04가정!H8*SC04가정!U7,0) -> 600000 | N17: =M17 -> 600000 | O17: =H17-I17-J17-K17-L17+M17-N17 -> 9400000 | P17: 0 | Q17: 보고 예상 | R17: EVDC42
A18: REP41-v1|ALT43|2027-07 | B18: REP41-v1 | C18: ALT43 | D18: 46569 | E18: =SC04가정!F8 -> 46661 | F18: =IF(D18>=E18,1,0) -> 0 | G18: =F18*SC04가정!H8 -> 0 | H18: =G18*SC04가정!I8 -> 0 | I18: =G18*SC04가정!J8 -> 0 | J18: =G18*SC04가정!K8 -> 0 | K18: =F18*SC04가정!O8 -> 0 | L18: =IF(D18=SC04가정!Q8,SC04가정!P8,0) -> 0 | M18: =0 -> 0 | N18: =M18 -> 0 | O18: =H18-I18-J18-K18-L18+M18-N18 -> 0 | P18: 0 | Q18: 보고 예상 | R18: EVDC43
A19: REP41-v1|ALT43|2027-08 | B19: REP41-v1 | C19: ALT43 | D19: 46600 | E19: =SC04가정!F8 -> 46661 | F19: =IF(D19>=E19,1,0) -> 0 | G19: =F19*SC04가정!H8 -> 0 | H19: =G19*SC04가정!I8 -> 0 | I19: =G19*SC04가정!J8 -> 0 | J19: =G19*SC04가정!K8 -> 0 | K19: =F19*SC04가정!O8 -> 0 | L19: =IF(D19=SC04가정!Q8,SC04가정!P8,0) -> 0 | M19: =0 -> 0 | N19: =M19 -> 0 | O19: =H19-I19-J19-K19-L19+M19-N19 -> 0 | P19: 0 | Q19: 보고 예상 | R19: EVDC43
A20: REP41-v1|ALT43|2027-09 | B20: REP41-v1 | C20: ALT43 | D20: 46631 | E20: =SC04가정!F8 -> 46661 | F20: =IF(D20>=E20,1,0) -> 0 | G20: =F20*SC04가정!H8 -> 0 | H20: =G20*SC04가정!I8 -> 0 | I20: =G20*SC04가정!J8 -> 0 | J20: =G20*SC04가정!K8 -> 0 | K20: =F20*SC04가정!O8 -> 0 | L20: =IF(D20=SC04가정!Q8,SC04가정!P8,0) -> 1000000 | M20: =0 -> 0 | N20: =M20 -> 0 | O20: =H20-I20-J20-K20-L20+M20-N20 -> -1000000 | P20: 0 | Q20: 보고 예상 | R20: EVDC43
A21: REP41-v1|ALT43|2027-10 | B21: REP41-v1 | C21: ALT43 | D21: 46661 | E21: =SC04가정!F8 -> 46661 | F21: =IF(D21>=E21,1,0) -> 1 | G21: =F21*SC04가정!H8 -> 6000 | H21: =G21*SC04가정!I8 -> 30000000 | I21: =G21*SC04가정!J8 -> 27000000 | J21: =G21*SC04가정!K8 -> 600000 | K21: =F21*SC04가정!O8 -> 0 | L21: =IF(D21=SC04가정!Q8,SC04가정!P8,0) -> 0 | M21: =0 -> 0 | N21: =M21 -> 0 | O21: =H21-I21-J21-K21-L21+M21-N21 -> 2400000 | P21: 0 | Q21: 보고 예상 | R21: EVDC43
A22: REP41-v1|ALT43|2027-11 | B22: REP41-v1 | C22: ALT43 | D22: 46692 | E22: =SC04가정!F8 -> 46661 | F22: =IF(D22>=E22,1,0) -> 1 | G22: =F22*SC04가정!H8 -> 6000 | H22: =G22*SC04가정!I8 -> 30000000 | I22: =G22*SC04가정!J8 -> 27000000 | J22: =G22*SC04가정!K8 -> 600000 | K22: =F22*SC04가정!O8 -> 0 | L22: =IF(D22=SC04가정!Q8,SC04가정!P8,0) -> 0 | M22: =0 -> 0 | N22: =M22 -> 0 | O22: =H22-I22-J22-K22-L22+M22-N22 -> 2400000 | P22: 0 | Q22: 보고 예상 | R22: EVDC43
A23: REP41-v1|ALT43|2027-12 | B23: REP41-v1 | C23: ALT43 | D23: 46722 | E23: =SC04가정!F8 -> 46661 | F23: =IF(D23>=E23,1,0) -> 1 | G23: =F23*SC04가정!H8 -> 6000 | H23: =G23*SC04가정!I8 -> 30000000 | I23: =G23*SC04가정!J8 -> 27000000 | J23: =G23*SC04가정!K8 -> 600000 | K23: =F23*SC04가정!O8 -> 0 | L23: =IF(D23=SC04가정!Q8,SC04가정!P8,0) -> 0 | M23: =0 -> 0 | N23: =M23 -> 0 | O23: =H23-I23-J23-K23-L23+M23-N23 -> 2400000 | P23: 0 | Q23: 보고 예상 | R23: EVDC43
A24: DEC41-v2|ALT41|2027-07 | B24: DEC41-v2 | C24: ALT41 | D24: 46569 | E24: =SC04가정!G6 -> 46600 | F24: =IF(D24>=E24,1,0) -> 0 | G24: =F24*SC04가정!H6 -> 0 | H24: =G24*SC04가정!I6 -> 0 | I24: =G24*SC04가정!J6 -> 0 | J24: =G24*SC04가정!K6 -> 0 | K24: =F24*SC04가정!O6 -> 0 | L24: =IF(D24=SC04가정!Q6,SC04가정!P6,0) -> 4000000 | M24: =0 -> 0 | N24: =M24 -> 0 | O24: =H24-I24-J24-K24-L24+M24-N24 -> -4000000 | P24: 0 | Q24: 실행승인 예상 | R24: EVDC41
A25: DEC41-v2|ALT41|2027-08 | B25: DEC41-v2 | C25: ALT41 | D25: 46600 | E25: =SC04가정!G6 -> 46600 | F25: =IF(D25>=E25,1,0) -> 1 | G25: =F25*SC04가정!H6 -> 3000 | H25: =G25*SC04가정!I6 -> 45000000 | I25: =G25*SC04가정!J6 -> 24000000 | J25: =G25*SC04가정!K6 -> 3000000 | K25: =F25*SC04가정!O6 -> 0 | L25: =IF(D25=SC04가정!Q6,SC04가정!P6,0) -> 0 | M25: =0 -> 0 | N25: =M25 -> 0 | O25: =H25-I25-J25-K25-L25+M25-N25 -> 18000000 | P25: 0 | Q25: 실행승인 예상 | R25: EVDC41
A26: DEC41-v2|ALT41|2027-09 | B26: DEC41-v2 | C26: ALT41 | D26: 46631 | E26: =SC04가정!G6 -> 46600 | F26: =IF(D26>=E26,1,0) -> 1 | G26: =F26*SC04가정!H6 -> 3000 | H26: =G26*SC04가정!I6 -> 45000000 | I26: =G26*SC04가정!J6 -> 24000000 | J26: =G26*SC04가정!K6 -> 3000000 | K26: =F26*SC04가정!O6 -> 0 | L26: =IF(D26=SC04가정!Q6,SC04가정!P6,0) -> 0 | M26: =0 -> 0 | N26: =M26 -> 0 | O26: =H26-I26-J26-K26-L26+M26-N26 -> 18000000 | P26: 0 | Q26: 실행승인 예상 | R26: EVDC41
A27: DEC41-v2|ALT41|2027-10 | B27: DEC41-v2 | C27: ALT41 | D27: 46661 | E27: =SC04가정!G6 -> 46600 | F27: =IF(D27>=E27,1,0) -> 1 | G27: =F27*SC04가정!H6 -> 3000 | H27: =G27*SC04가정!I6 -> 45000000 | I27: =G27*SC04가정!J6 -> 24000000 | J27: =G27*SC04가정!K6 -> 3000000 | K27: =F27*SC04가정!O6 -> 0 | L27: =IF(D27=SC04가정!Q6,SC04가정!P6,0) -> 0 | M27: =0 -> 0 | N27: =M27 -> 0 | O27: =H27-I27-J27-K27-L27+M27-N27 -> 18000000 | P27: 0 | Q27: 실행승인 예상 | R27: EVDC41
A28: DEC41-v2|ALT41|2027-11 | B28: DEC41-v2 | C28: ALT41 | D28: 46692 | E28: =SC04가정!G6 -> 46600 | F28: =IF(D28>=E28,1,0) -> 1 | G28: =F28*SC04가정!H6 -> 3000 | H28: =G28*SC04가정!I6 -> 45000000 | I28: =G28*SC04가정!J6 -> 24000000 | J28: =G28*SC04가정!K6 -> 3000000 | K28: =F28*SC04가정!O6 -> 0 | L28: =IF(D28=SC04가정!Q6,SC04가정!P6,0) -> 0 | M28: =0 -> 0 | N28: =M28 -> 0 | O28: =H28-I28-J28-K28-L28+M28-N28 -> 18000000 | P28: 0 | Q28: 실행승인 예상 | R28: EVDC41
A29: DEC41-v2|ALT41|2027-12 | B29: DEC41-v2 | C29: ALT41 | D29: 46722 | E29: =SC04가정!G6 -> 46600 | F29: =IF(D29>=E29,1,0) -> 1 | G29: =F29*SC04가정!H6 -> 3000 | H29: =G29*SC04가정!I6 -> 45000000 | I29: =G29*SC04가정!J6 -> 24000000 | J29: =G29*SC04가정!K6 -> 3000000 | K29: =F29*SC04가정!O6 -> 0 | L29: =IF(D29=SC04가정!Q6,SC04가정!P6,0) -> 0 | M29: =0 -> 0 | N29: =M29 -> 0 | O29: =H29-I29-J29-K29-L29+M29-N29 -> 18000000 | P29: 0 | Q29: 실행승인 예상 | R29: EVDC41
A30: DEC41-v2|ALT42|2027-07 | B30: DEC41-v2 | C30: ALT42 | D30: 46569 | E30: =SC04가정!G7 -> 46631 | F30: =IF(D30>=E30,1,0) -> 0 | G30: =F30*SC04가정!H7 -> 0 | H30: =F30*(SC04가정!L7-SC04가정!M7)*SC04가정!N7 -> 0 | I30: =G30*SC04가정!J7 -> 0 | J30: =G30*SC04가정!K7 -> 0 | K30: =F30*SC04가정!O7 -> 0 | L30: =IF(D30=SC04가정!Q7,SC04가정!P7,0) -> 0 | M30: =IF(D30>=SC04가정!G8,SC04가정!H8*SC04가정!U7,0) -> 0 | N30: =M30 -> 0 | O30: =H30-I30-J30-K30-L30+M30-N30 -> 0 | P30: 0 | Q30: 조건부 예상 | R30: EVDC42
A31: DEC41-v2|ALT42|2027-08 | B31: DEC41-v2 | C31: ALT42 | D31: 46600 | E31: =SC04가정!G7 -> 46631 | F31: =IF(D31>=E31,1,0) -> 0 | G31: =F31*SC04가정!H7 -> 0 | H31: =F31*(SC04가정!L7-SC04가정!M7)*SC04가정!N7 -> 0 | I31: =G31*SC04가정!J7 -> 0 | J31: =G31*SC04가정!K7 -> 0 | K31: =F31*SC04가정!O7 -> 0 | L31: =IF(D31=SC04가정!Q7,SC04가정!P7,0) -> 2000000 | M31: =IF(D31>=SC04가정!G8,SC04가정!H8*SC04가정!U7,0) -> 0 | N31: =M31 -> 0 | O31: =H31-I31-J31-K31-L31+M31-N31 -> -2000000 | P31: 0 | Q31: 조건부 예상 | R31: EVDC42
A32: DEC41-v2|ALT42|2027-09 | B32: DEC41-v2 | C32: ALT42 | D32: 46631 | E32: =SC04가정!G7 -> 46631 | F32: =IF(D32>=E32,1,0) -> 1 | G32: =F32*SC04가정!H7 -> 0 | H32: =F32*(SC04가정!L7-SC04가정!M7)*SC04가정!N7 -> 9600000 | I32: =G32*SC04가정!J7 -> 0 | J32: =G32*SC04가정!K7 -> 0 | K32: =F32*SC04가정!O7 -> 200000 | L32: =IF(D32=SC04가정!Q7,SC04가정!P7,0) -> 0 | M32: =IF(D32>=SC04가정!G8,SC04가정!H8*SC04가정!U7,0) -> 0 | N32: =M32 -> 0 | O32: =H32-I32-J32-K32-L32+M32-N32 -> 9400000 | P32: 0 | Q32: 조건부 예상 | R32: EVDC42
A33: DEC41-v2|ALT42|2027-10 | B33: DEC41-v2 | C33: ALT42 | D33: 46661 | E33: =SC04가정!G7 -> 46631 | F33: =IF(D33>=E33,1,0) -> 1 | G33: =F33*SC04가정!H7 -> 0 | H33: =F33*(SC04가정!L7-SC04가정!M7)*SC04가정!N7 -> 9600000 | I33: =G33*SC04가정!J7 -> 0 | J33: =G33*SC04가정!K7 -> 0 | K33: =F33*SC04가정!O7 -> 200000 | L33: =IF(D33=SC04가정!Q7,SC04가정!P7,0) -> 0 | M33: =IF(D33>=SC04가정!G8,SC04가정!H8*SC04가정!U7,0) -> 600000 | N33: =M33 -> 600000 | O33: =H33-I33-J33-K33-L33+M33-N33 -> 9400000 | P33: 0 | Q33: 조건부 예상 | R33: EVDC42
A34: DEC41-v2|ALT42|2027-11 | B34: DEC41-v2 | C34: ALT42 | D34: 46692 | E34: =SC04가정!G7 -> 46631 | F34: =IF(D34>=E34,1,0) -> 1 | G34: =F34*SC04가정!H7 -> 0 | H34: =F34*(SC04가정!L7-SC04가정!M7)*SC04가정!N7 -> 9600000 | I34: =G34*SC04가정!J7 -> 0 | J34: =G34*SC04가정!K7 -> 0 | K34: =F34*SC04가정!O7 -> 200000 | L34: =IF(D34=SC04가정!Q7,SC04가정!P7,0) -> 0 | M34: =IF(D34>=SC04가정!G8,SC04가정!H8*SC04가정!U7,0) -> 600000 | N34: =M34 -> 600000 | O34: =H34-I34-J34-K34-L34+M34-N34 -> 9400000 | P34: 0 | Q34: 조건부 예상 | R34: EVDC42
A35: DEC41-v2|ALT42|2027-12 | B35: DEC41-v2 | C35: ALT42 | D35: 46722 | E35: =SC04가정!G7 -> 46631 | F35: =IF(D35>=E35,1,0) -> 1 | G35: =F35*SC04가정!H7 -> 0 | H35: =F35*(SC04가정!L7-SC04가정!M7)*SC04가정!N7 -> 9600000 | I35: =G35*SC04가정!J7 -> 0 | J35: =G35*SC04가정!K7 -> 0 | K35: =F35*SC04가정!O7 -> 200000 | L35: =IF(D35=SC04가정!Q7,SC04가정!P7,0) -> 0 | M35: =IF(D35>=SC04가정!G8,SC04가정!H8*SC04가정!U7,0) -> 600000 | N35: =M35 -> 600000 | O35: =H35-I35-J35-K35-L35+M35-N35 -> 9400000 | P35: 0 | Q35: 조건부 예상 | R35: EVDC42
A36: DEC41-v2|ALT43|2027-07 | B36: DEC41-v2 | C36: ALT43 | D36: 46569 | E36: =SC04가정!G8 -> 46661 | F36: =IF(D36>=E36,1,0) -> 0 | G36: =F36*SC04가정!H8 -> 0 | H36: =G36*SC04가정!I8 -> 0 | I36: =G36*SC04가정!J8 -> 0 | J36: =G36*SC04가정!K8 -> 0 | K36: =F36*SC04가정!O8 -> 0 | L36: =IF(D36=SC04가정!Q8,SC04가정!P8,0) -> 0 | M36: =0 -> 0 | N36: =M36 -> 0 | O36: =H36-I36-J36-K36-L36+M36-N36 -> 0 | P36: 0 | Q36: 실행승인 예상 | R36: EVDC43
A37: DEC41-v2|ALT43|2027-08 | B37: DEC41-v2 | C37: ALT43 | D37: 46600 | E37: =SC04가정!G8 -> 46661 | F37: =IF(D37>=E37,1,0) -> 0 | G37: =F37*SC04가정!H8 -> 0 | H37: =G37*SC04가정!I8 -> 0 | I37: =G37*SC04가정!J8 -> 0 | J37: =G37*SC04가정!K8 -> 0 | K37: =F37*SC04가정!O8 -> 0 | L37: =IF(D37=SC04가정!Q8,SC04가정!P8,0) -> 0 | M37: =0 -> 0 | N37: =M37 -> 0 | O37: =H37-I37-J37-K37-L37+M37-N37 -> 0 | P37: 0 | Q37: 실행승인 예상 | R37: EVDC43
A38: DEC41-v2|ALT43|2027-09 | B38: DEC41-v2 | C38: ALT43 | D38: 46631 | E38: =SC04가정!G8 -> 46661 | F38: =IF(D38>=E38,1,0) -> 0 | G38: =F38*SC04가정!H8 -> 0 | H38: =G38*SC04가정!I8 -> 0 | I38: =G38*SC04가정!J8 -> 0 | J38: =G38*SC04가정!K8 -> 0 | K38: =F38*SC04가정!O8 -> 0 | L38: =IF(D38=SC04가정!Q8,SC04가정!P8,0) -> 1000000 | M38: =0 -> 0 | N38: =M38 -> 0 | O38: =H38-I38-J38-K38-L38+M38-N38 -> -1000000 | P38: 0 | Q38: 실행승인 예상 | R38: EVDC43
A39: DEC41-v2|ALT43|2027-10 | B39: DEC41-v2 | C39: ALT43 | D39: 46661 | E39: =SC04가정!G8 -> 46661 | F39: =IF(D39>=E39,1,0) -> 1 | G39: =F39*SC04가정!H8 -> 6000 | H39: =G39*SC04가정!I8 -> 30000000 | I39: =G39*SC04가정!J8 -> 27000000 | J39: =G39*SC04가정!K8 -> 600000 | K39: =F39*SC04가정!O8 -> 0 | L39: =IF(D39=SC04가정!Q8,SC04가정!P8,0) -> 0 | M39: =0 -> 0 | N39: =M39 -> 0 | O39: =H39-I39-J39-K39-L39+M39-N39 -> 2400000 | P39: 0 | Q39: 실행승인 예상 | R39: EVDC43
A40: DEC41-v2|ALT43|2027-11 | B40: DEC41-v2 | C40: ALT43 | D40: 46692 | E40: =SC04가정!G8 -> 46661 | F40: =IF(D40>=E40,1,0) -> 1 | G40: =F40*SC04가정!H8 -> 6000 | H40: =G40*SC04가정!I8 -> 30000000 | I40: =G40*SC04가정!J8 -> 27000000 | J40: =G40*SC04가정!K8 -> 600000 | K40: =F40*SC04가정!O8 -> 0 | L40: =IF(D40=SC04가정!Q8,SC04가정!P8,0) -> 0 | M40: =0 -> 0 | N40: =M40 -> 0 | O40: =H40-I40-J40-K40-L40+M40-N40 -> 2400000 | P40: 0 | Q40: 실행승인 예상 | R40: EVDC43
A41: DEC41-v2|ALT43|2027-12 | B41: DEC41-v2 | C41: ALT43 | D41: 46722 | E41: =SC04가정!G8 -> 46661 | F41: =IF(D41>=E41,1,0) -> 1 | G41: =F41*SC04가정!H8 -> 6000 | H41: =G41*SC04가정!I8 -> 30000000 | I41: =G41*SC04가정!J8 -> 27000000 | J41: =G41*SC04가정!K8 -> 600000 | K41: =F41*SC04가정!O8 -> 0 | L41: =IF(D41=SC04가정!Q8,SC04가정!P8,0) -> 0 | M41: =0 -> 0 | N41: =M41 -> 0 | O41: =H41-I41-J41-K41-L41+M41-N41 -> 2400000 | P41: 0 | Q41: 실행승인 예상 | R41: EVDC43

Sheet SC04근거
A1: INNONOW SC04근거 v0.4
A3: 신규 근거는 모두 가상 시연 자료. 승인·검토기록은 실제 수행 사실이 아닌 기본 시연 기대 레코드입니다.
A5: 근거ID | B5: 대상 | C5: 가상 근거·내역 | D5: 참조 | E5: 해석·제약
A6: EVDC41 | B6: ALT41 / PR-A01 | C6: A-a 부분 공정. 변동가공비 20,000원 중 회피 가능한 15,000원/대분. 월 3,000대분을 외주 8,000원+물류 1,000원으로 대체. | D6: SC04가정 6행 | E6: 기존 변동가공비에서 차감 후 외주·물류 추가. 기존 고정비 불변. 내부 임금 고정분을 회피비에 포함하지 않음.
A7: EVDC42 | B7: ALT42 / URG-B01 | C7: A-b 변동가공비 내 긴급 운송·발주 할증: 월 12건×120만원. 목표 4건, 월 협조 운영비 20만원. 월 순효과 940만원. | D7: SC04가정 7행 | E7: 기준 월 변동가공비보다 작은 내역. 추가 손실을 기준 손익에 다시 더하지 않음.
A8: EVDC43 | B8: ALT43 / P-MAT02 | C8: A-b 재료비 55,000원 중 구매 부품 5,000원/개. 기존 승인 SUP-M02를 활용해 4,500원, 추가물류 100원. 월 6,000개. | D8: SC04가정 8행 | E8: P-COM01과 다른 품목. 장면2 승인단가 2,120원을 변경하지 않음.
A9: EVDC44 | B9: 중복 효과 | C9: ALT42 구매조건 초안의 P-MAT02 100원/개 할인은 ALT43의 500원 가격차에 포함. 10~12월 월6,000개 구간을 ALT42에서 제거. | D9: SC04월효과 M:N | E9: 중복액 월60만원, 3개월180만원. 보고본·판단본 모두 제거 완료. 초기 중복 초안은 분기 재현용.
A10: EVDC45 | B10: 잔존 고정비 | C10: 월 공장 고정비 370백만원 유지. 기존 감가상각비 120백만원, 기타 고정비 250백만원으로 설명용 세분 가정. | D10: 월고정비 / FC01 | E10: 회피 고정비 0. 기존 설비 투자·감가상각비는 대안 절감·추가지출에 포함하지 않음. 신규 설비투자 없음.
A11: EVDC46 | B11: 품질·공급능력 | C11: 7/7 가상 검토: PR-A01 시범품질·월3,000대분 능력 확인. SUP-M02 P-MAT02 월6,000개 확인. A-a 8~12월 최소 전망3,496대 이내. | D11: ALT41 / ALT43 | E11: 실제 회사 인증·검사 사실 아님. 예비 검토 완료와 후속 실제 전환·모니터링을 구분.
A12: EVDC47 | B12: 생산·구매 협조 | C12: 가상 6월 긴급조달 사례 12건 중 생산계획 변경공유 지연 6건, 공급사 일정 조정 4건, 돌발품질 2건. 공동 공유·협의로 8건 감축 가정. | D12: CON41 / QA412 | E12: 과거 예시 원장. 미래 월12건 가정의 설명 근거일 뿐 6월 실적 재작성 아님. 감축 달성은 미확정.
A13: EVDC48 | B13: AT33 검토 | C13: 7/6 영업 확인: 현재 고객 생산배정 범위에서 추가 물량 조정 요청을 뒷받침할 근거 없음. | D13: RES43 / C34 | E13: 이번 실행안 제외. 시장 가능성을 영구 부정하지 않음.
A14: EVDC49 | B14: 기존 목표 부족 | C14: T01과 F01 모델별 수량 차이×C01 단위CM으로 원인을 설명. 가격·원가·고정비 차이를 새로 만들지 않음. | D14: SC04분석결과 하단 | E14: 제품별 배정량·구성 차이의 산술 설명. 시장 수요 원인까지 확정하지 않음.

Sheet SC04분석결과
A1: INNONOW SC04분석결과 v0.4
A3: 원 SC03 기록은 6/30 시점으로 보존. 이 시트는 7월 후속 분석 결과이며 결과·쟁점 상태는 해당 이벤트 이후 유효.
A5: 결과ID | B5: 원 분석과제 | C5: 보고대상 | D5: 작성자 | E5: 확인자 | F5: 제출시각_KST | G5: 결론 | H5: 근거 | I5: 쟁점처리
A6: RES41 | B6: AT31 | C6: ALT41 | D6: USR-PROD | E6: EX-PROD | F6: 46574.583 | G6: 회피 고정비 없음. 변동가공비 대체에 의한 순효과 검토. | H6: EVDC41;EVDC45;EVDC46 | I6: Q31 근거 확인 완료. 위험 해소를 의미하지 않음.
A7: RES42 | B7: AT32 | C7: ALT42;ALT43 | D7: USR-BUY | E7: EX-BUY | F7: 46574.625 | G7: 구매조건 중복 할인 제거. 긴급구매 및 승인 대체 공급업체를 별도 대안으로 분석. | H7: EVDC42;EVDC43;EVDC44 | I7: 7/7 보완, 7/8 통합본. 생産
A8: RES43 | B8: AT33 | C8: C34 | D8: USR-SALES | E8: EX-SALES | F8: 46574.667 | G8: 현재 근거 부족으로 우선 실행안 제외. | H8: EVDC48 | I8: 분석과제 검토 종결, 실행과제 미생성
A9: RES44 | B9: AT34 | C9: 기존 부족분 | D9: USR-FINLEAD | E9: USR-CFO | F9: 46574.708 | G9: T01 대비 F01 수량·구성 차이로 기존 부족 설명. | H9: EVDC49 | I9: Q32 산술 근거 확인 완료. 추가 과제 발굴 지시 DIR41로 연결.
A12: 모델 | B12: T01 연간량 | C12: F01 연간량 | D12: C01 단위CM | E12: 기존 부족 기여 | F12: 근거
A13: A-a | B13: =SUMIFS(물량원가기준!$D$6:$D$100,물량원가기준!$C$6:$C$100,A13,물량원가기준!$B$6:$B$100,">="&DATE(2027,1,1),물량원가기준!$B$6:$B$100,"<"&DATE(2028,1,1)) -> 47480 | C13: =SUMIFS(물량원가기준!$E$6:$E$100,물량원가기준!$C$6:$C$100,A13,물량원가기준!$B$6:$B$100,">="&DATE(2027,1,1),물량원가기준!$B$6:$B$100,"<"&DATE(2028,1,1)) -> 45699 | D13: =물량원가기준!G6-SUM(물량원가기준!H6:J6) -> 30000 | E13: =(B13-C13)*D13 -> 53430000 | F13: T01·F01·C01. 수량·구성의 산술 기여
A14: A-b | B14: =SUMIFS(물량원가기준!$D$6:$D$100,물량원가기준!$C$6:$C$100,A14,물량원가기준!$B$6:$B$100,">="&DATE(2027,1,1),물량원가기준!$B$6:$B$100,"<"&DATE(2028,1,1)) -> 118700 | C14: =SUMIFS(물량원가기준!$E$6:$E$100,물량원가기준!$C$6:$C$100,A14,물량원가기준!$B$6:$B$100,">="&DATE(2027,1,1),물량원가기준!$B$6:$B$100,"<"&DATE(2028,1,1)) -> 114248 | D14: =물량원가기준!G7-SUM(물량원가기준!H7:J7) -> 20000 | E14: =(B14-C14)*D14 -> 89040000 | F14: T01·F01·C01. 수량·구성의 산술 기여
A15: A-c | B15: =SUMIFS(물량원가기준!$D$6:$D$100,물량원가기준!$C$6:$C$100,A15,물량원가기준!$B$6:$B$100,">="&DATE(2027,1,1),물량원가기준!$B$6:$B$100,"<"&DATE(2028,1,1)) -> 71220 | C15: =SUMIFS(물량원가기준!$E$6:$E$100,물량원가기준!$C$6:$C$100,A15,물량원가기준!$B$6:$B$100,">="&DATE(2027,1,1),물량원가기준!$B$6:$B$100,"<"&DATE(2028,1,1)) -> 70508 | D15: =물량원가기준!G8-SUM(물량원가기준!H8:J8) -> 28000 | E15: =(B15-C15)*D15 -> 19936000 | F15: T01·F01·C01. 수량·구성의 산술 기여
A16: A-d | B16: =SUMIFS(물량원가기준!$D$6:$D$100,물량원가기준!$C$6:$C$100,A16,물량원가기준!$B$6:$B$100,">="&DATE(2027,1,1),물량원가기준!$B$6:$B$100,"<"&DATE(2028,1,1)) -> 59350 | C16: =SUMIFS(물량원가기준!$E$6:$E$100,물량원가기준!$C$6:$C$100,A16,물량원가기준!$B$6:$B$100,">="&DATE(2027,1,1),물량원가기준!$B$6:$B$100,"<"&DATE(2028,1,1)) -> 59945 | D16: =물량원가기준!G9-SUM(물량원가기준!H9:J9) -> 25000 | E16: =(B16-C16)*D16 -> -14875000 | F16: T01·F01·C01. 수량·구성의 산술 기여
A17: A-e | B17: =SUMIFS(물량원가기준!$D$6:$D$100,물량원가기준!$C$6:$C$100,A17,물량원가기준!$B$6:$B$100,">="&DATE(2027,1,1),물량원가기준!$B$6:$B$100,"<"&DATE(2028,1,1)) -> 35610 | C17: =SUMIFS(물량원가기준!$E$6:$E$100,물량원가기준!$C$6:$C$100,A17,물량원가기준!$B$6:$B$100,">="&DATE(2027,1,1),물량원가기준!$B$6:$B$100,"<"&DATE(2028,1,1)) -> 35254 | D17: =물량원가기준!G10-SUM(물량원가기준!H10:J10) -> 18000 | E17: =(B17-C17)*D17 -> 6408000 | F17: T01·F01·C01. 수량·구성의 산술 기여
A18: 합계 | E18: =SUM(E13:E17) -> 153939000

Sheet SC04예산과제
A1: INNONOW SC04예산과제 v0.4
A3: 예산 한도는 전환·검증·교육 등 일회성 실행 준비비용 범위. 반복 거래·운영비는 기존 운영예산·품의로 별도 통제. 초기 실제 집행·약정은 0, 예상효과와 구분.
A5: 과제ID | B5: 대안ID | C5: 책임임원 | D5: 실무담당 | E5: 승인한도 | F5: 미약정예정 | G5: 기약정미집행 | H5: 집행완료 | I5: 한도여력 | J5: 계획제출_KST | K5: 과제완료_KST | L5: 승인결정 | M5: 인수상태 | N5: 인수시각_KST | O5: 승인버전 | P5: 배정버전
A6: ACT41 | B6: ALT41 | C6: EX-PROD | D6: USR-PROD | E6: 8000000 | F6: 4000000 | G6: 0 | H6: 0 | I6: =E6-SUM(F6:H6) -> 4000000 | J6: 46584.75 | K6: 46630.75 | L6: APPROVED | M6: ACCEPTED | N6: 46581.375 | O6: APR41-v1 | P6: 1
A7: ACT42 | B7: ALT42 | C7: EX-BUY | D7: USR-BUY | E7: 6000000 | F7: 2000000 | G7: 0 | H7: 0 | I7: =E7-SUM(F7:H7) -> 4000000 | J7: 46584.75 | K7: 46660.75 | L7: CONDITIONAL | M7: ACCEPTED | N7: 46581.385 | O7: APR41-v1 | P7: 1
A8: ACT43 | B8: ALT43 | C8: EX-BUY | D8: USR-BUY | E8: 4000000 | F8: 1000000 | G8: 0 | H8: 0 | I8: =E8-SUM(F8:H8) -> 3000000 | J8: 46584.75 | K8: 46689.75 | L8: APPROVED | M8: ACCEPTED | N8: 46581.389 | O8: APR41-v1 | P8: 1
A9: TOTAL | B9: 총괄 | C9: USR-CFO | E9: 18000000 | F9: =SUM(F6:F8) -> 7000000 | G9: =SUM(G6:G8) -> 0 | H9: =SUM(H6:H8) -> 0 | I9: =E9-SUM(F9:H9) -> 11000000 | L9: APPROVED | M9: ACCEPTED | N9: 46581.396 | O9: APR41-v1 | P9: 1

Sheet SC04조건지시
A1: INNONOW SC04조건지시 v0.4
A3: 품질·납기 조건은 전문 부서 검토 후 담당 임원, 예산 조건은 경영관리 예산 임원 확인. 기본 CON41은 생산·구매 협조 조건.
A5: 기록ID | B5: 유형 | C5: 관련과제 | D5: 내용 | E5: 책임 | F5: 협조 | G5: 충족확인자 | H5: 기한_KST | I5: 상태 | J5: 인수시각_KST | K5: 예상효과 | L5: 실행제한
A6: CON41 | B6: 선행조건 | C6: ACT42 | D6: 생산계획 변경정보 공유·구매 대응 협의 기준 마련 및 양 부서 확인 | E6: EX-BUY | F6: EX-PROD | G6: EX-BUY | H6: 46619.75 | I6: OPEN | J6: 46581.385 | L6: 조건 충족 전 긴급구매 개선안 실행 착수 제한. 계획 수립·인수 가능.
A7: SUP41 | B7: 지원지시 | C7: ACT42 | D7: 생산 임원이 변경정보 제공 책임과 담당 창구를 지정하고 구매와 공동 기준 합의 | E7: EX-PROD | F7: USR-PROD;USR-BUY | G7: USR-CFO | H7: 46619.75 | I7: ACCEPTED | J7: 46581.382 | L7: CON41 충족 근거로 연결. 세부 일정은 장면5.
A8: DIR41 | B8: 추가발굴 | C8: MR-2706-01 | D8: 잔여 목표 부족분 추가 개선과제 발굴. 과제별 근거·효과·기한을 후속 경영검토에 보고 | E8: USR-CFO | F8: EX-PROD;EX-BUY;EX-SALES | G8: USR-CEO | H8: 46608.417 | I8: ACCEPTED | J8: 46581.396 | L8: 미산정 효과를 현재 개선액에 포함하지 않음.

Sheet SC04회의
A1: INNONOW SC04회의 v0.4
A3: 가상 회의 문안. 보고→질의→재계산→결정→승인서 확정. 승인서의 금액은 기본 fixture이며 가정 변경 시 새 버전으로 재작성.
A5: 기록ID | B5: 유형 | C5: 시각_KST | D5: 발언·결정자 | E5: 관련대상 | F5: 본문 | G5: 근거·버전
A6: MT41 | B6: 월간회의 | C6: 46580.417 | D6: USR-CEO | E6: MR-2706-01 | F6: 수익성 개선 대응안 검토 및 실행 승인 | G6: REP41-v1
A7: QA411 | B7: 대표질문 | C7: 46580.427 | D7: USR-CEO | E7: ALT42 | F7: 긴급구매를 줄이면 납기는 지킬 수 있습니까? 구매부서만 노력하면 되는 일입니까? | G7: EVDC47
A8: QA412 | B8: 구매답변 | C8: 46580.429 | D8: EX-BUY | E8: ALT42 | F8: 생산 변경정보가 늦으면 긴급발주가 불가피합니다. 생산과 공유·협의 기준이 필요합니다. | G8: EVDC47
A9: QA413 | B9: 생산답변 | C9: 46580.431 | D9: EX-PROD | E9: ALT42 | F9: 고객 변경 자체를 없애기는 어렵습니다. 변경정보 공유와 구매 대응 협의 기준을 함께 마련하겠습니다. | G9: CON41;SUP41
A10: QA414 | B10: 지원·수정지시 | C10: 46580.434 | D10: USR-CEO | E10: ALT42 | F10: 생산·구매 공동 기준을 8/20까지 마련하고, 적용 준비기간을 반영해 효과 시작을 9월로 검토하십시오. | G10: CON41;DEC41-v2
A11: CONF41 | B11: 재계산확인 | C11: 46580.441 | D11: USR-CFO | E11: DEC41-v2 | F11: 담당 임원과 적용 시점을 확인. 원 보고본을 보존하고 수정 판단본의 효과·부족분으로 승인 요청. | G11: ALT42;SC04비교
A12: REV41 | B12: 회의결정 | C12: 46580.448 | D12: USR-CEO | E12: ALT41;ALT42;ALT43 | F12: 부분 공정·대체공급업체 안 승인, 긴급구매 안 조건부 승인. 추가 과제 발굴 지시. | G12: DEC41-v2;DIR41
A13: APR41-v1 | B13: 승인서확정 | C13: 46580.625 | D13: USR-CEO | E13: ACT41;ACT42;ACT43 | F13: 전체 책임은 경영관리 임원, 개별 책임은 담당 임원. 총괄 18백만원/과제8·6·4백만원 한도. 두 기한과 CON41·SUP41·DIR41 승인. | G13: DEC41-v2;MIN41-v1
A14: POL41 | B14: 위임조항 | C14: 46580.625 | D14: USR-CEO | E14: APR41-v1 | F14: 한도 내 품의는 담당 현업 임원·예산 임원. 과제 간 전용은 무보고 불허, 총괄한도 내 변경 보고 후 전체 책임 임원 승인. 총괄한도 초과는 대표 별도 승인. | G14: SC04예산과제
A15: MIN41-v1 | B15: 회의록확정 | C15: 46580.625 | D15: USR-CEO | E15: MT41 | F15: 질의·답변, 효과시점 조정, 예산·책임·조건·기한, 추가 발굴 및 인계 기준 확인. | G15: QA411~414;REV41;APR41-v1

Sheet SC04이벤트
A1: INNONOW SC04이벤트 v0.4
A3: 초기 2027/7/1 08:59에는 장면3 인계만 적재. 결과·결정·과제인수는 이벤트 시각 이후 표시. 기본값은 종료시점 기대 상태.
A5: event_id | B5: scenario | C5: event_at_KST | D5: actor | E5: screen | F5: action | G5: object_ref | H5: state_after | I5: demo_id
A6: EV41-01 | B6: BASE | C6: 46569.375 | D6: USR-FIN | E6: U401 | F6: 착수 | G6: HANDOFF31 | H6: PREPARING | I6: D401
A7: EV41-02 | B7: BASE | C7: 46574.583 | D7: EX-PROD | E7: U401 | F7: 분석결과 제출·확인 | G7: RES41 | H7: SUBMITTED | I7: D402
A8: EV41-03 | B8: BASE | C8: 46574.625 | D8: EX-BUY | E8: U401 | F8: 분석결과 제출·확인 | G8: RES42 | H8: SUBMITTED | I8: D402
A9: EV41-04 | B9: BASE | C9: 46574.667 | D9: EX-SALES | E9: U401 | F9: 분석결과 제출·확인 | G9: RES43 | H9: SUBMITTED | I9: D402
A10: EV41-05 | B10: BASE | C10: 46574.708 | D10: USR-CFO | E10: U401 | F10: 분석결과 제출·확인 | G10: RES44 | H10: SUBMITTED | I10: D402
A11: EV41-06 | B11: BASE | C11: 46575.625 | D11: USR-FIN | E11: U402 | F11: 비용·중복 보완 및 검증 | G11: EVDC41~46 | H11: VERIFIED | I11: D403~404
A12: EV41-07 | B12: BASE | C12: 46576.667 | D12: USR-CFO | E12: U403 | F12: 공동 추천 확인 | G12: ALT41~43 | H12: RECOMMENDED | I12: D405
A13: EV41-08 | B13: BASE | C13: 46576.708 | D13: USR-CFO | E13: U404 | F13: 보고본 확정·배포 | G13: REP41-v1 | H13: FROZEN | I13: D406
A14: EV41-09 | B14: BASE | C14: 46580.417 | D14: USR-CFO | E14: U404 | F14: 월간회의 보고 | G14: MT41 | H14: IN_REVIEW | I14: D406
A15: EV41-10 | B15: BASE | C15: 46580.427 | D15: USR-CEO | E15: U405 | F15: 질의·답변·지원지시 | G15: QA411 | H15: IN_REVIEW | I15: D407
A16: EV41-11 | B16: BASE | C16: 46580.429 | D16: EX-BUY | E16: U405 | F16: 질의·답변·지원지시 | G16: QA412 | H16: IN_REVIEW | I16: D408
A17: EV41-12 | B17: BASE | C17: 46580.431 | D17: EX-PROD | E17: U405 | F17: 질의·답변·지원지시 | G17: QA413 | H17: IN_REVIEW | I17: D408
... A28: EV41-23 | B28: BASE | C28: 46581.417 | D28: USR-FIN | E28: U408 | F28: 장면5 인계·장면4 완료 | G28: HANDOFF41 | H28: SC04_COMPLETED | I28: D413

Sheet SC04인계
A1: INNONOW SC04인계 v0.4
A3: 이 인계는 대표 승인과 과제 인수까지의 결과입니다. 장면5 상세 계획과 실제 효과 검증은 후속 수행합니다.
A5: field | B5: value | C5: 근거 | D5: 처리
A6: handoff_id | B6: HANDOFF41 | C6: EV41-23 | D6: 장면5 상세 실행계획 수립 입력
A7: review_id | B7: MR-2706-01 | C7: HANDOFF31 | D7: 기존 검토건 유지
A8: approval | B8: APR41-v1 | C8: MT41 / MIN41-v1 | D8: 대표 포괄 승인
A9: basis_report | B9: DEC41-v2 | C9: REP41-v1 대비 재계산 | D9: 원 보고와 회의 판단본 보존
A10: actions | B10: ACT41;ACT42;ACT43 | C10: SC04예산과제 | D10: 전체 및 개별 인수 완료
A11: open_condition | B11: CON41 | C11: SC04조건지시 | D11: OPEN 유지. 계획수립 가능, 해당 실행 착수 제한
A12: support | B12: SUP41 | C12: EX-PROD | D12: 책임·기한·인수 연결
A13: additional_work | B13: DIR41 | C13: USR-CFO | D13: 8/9 10시 후속 검토. 예상효과 NULL
A14: plan_due | B14: 2027-07-16 18:00 KST | C14: 승인서 | D14: 과제별 완료기한과 별도
A15: scene_status | B15: SC04_COMPLETED | C15: EV41-23 | D15: 장면5 계획 대기
A16: risk_status | B16: OPEN | C16: 장면3 상태 유지 | D16: 실행과 실제 효과 확인 전 해소 처리 금지
... A19: as_of | B19: 2027-07-13 10:00 KST | C19: EV41-23 | D19: 이후 계획·집행·조건완료 기록 없음

Sheet SC04예외
A1: INNONOW SC04예외 v0.4
A3: 모든 분기는 BASE 복제에서 단독 재현. 금액 NULL은 미산정·비해당으로 보존. 예외 결과를 기본 손익에 합산하지 않습니다.
A5: case_id | B5: 기준시점 | C5: 변경 입력 | D5: 예상결과 | E5: 수치 기대값 | F5: 기본안 보존
A6: E401 | B6: U402 검증 전 | C6: ALT41 기존 감가상각비 120백만원/월을 회피로 추가 | D6: 회피 불가 비용으로 검증 차단. 제거·확인 후 복귀. | F6: 별도 초안. 기준 고정비 삭제 금지
A7: E402 | B7: U402 검증 전 | C7: ALT42 중복제거 N열의 10~12월 값을 0으로 가정 | D7: 3개월 중복 180만원 검출. 보고 확정 차단. | E7: 1800000 | F7: 기본 N=M 유지
A8: E403 | B8: U405 | C8: EVDC46의 SUP-M02 능력 확인을 미확인으로 변경 | D8: ALT43 보류·실행과제 미생성. 승인 범위 효과는 ALT41+ALT42. | E8: =SUM(SC04비교!D6:D7) -> 121600000 | F8: DEC41-v2 기본을 덮어쓰지 않음
A9: E404 | B9: U406 | C9: ACT42 계획제출기한 또는 총괄 한도 NULL | D9: 필수값 누락으로 승인서 확정 불가. | F9: NULL을 0 또는 임의 날짜로 대체 금지
A10: E405 | B10: EV41-21 직전 | C10: ACT43 미인수 또는 타인 인수 시도 | D10: 기본 실행과제 2/3 인수. 장면4 종료 제한. | E10: 2 | F10: 전체 책임자 인수도 별도 확인
A11: E406 | B11: EV41-23 | C11: CON41 OPEN 상태 유지 | D11: 과제 인수·장면4 완료 가능. ACT42 실행 착수 제한. | F11: 기본 시나리오의 정상 조건 상태
A12: E407-A | B12: 정책 조회 | C12: ACT41 배분 1백만원을 ACT42로 전용 제안 | D12: 변경보고·경영관리 임원 승인 필요. 총괄18백만원 유지. | E12: 18000000 | F12: 규칙 설명용, 실제 전용 이벤트 없음
A13: E407-B | B13: 정책 조회 | C13: 총괄 필요액 19백만원 | D13: 대표 별도 보고·승인 필요. | E13: 19000000 | F13: 기본 승인한도18백만원 유지
A14: E408 | B14: 초안 생성 | C14: Agent 장애 | D14: 원자료·계산 유지, 수동 작성 후 사람 검토. | F14: 승인·인수 권한 불변

Sheet SC04계약
A1: INNONOW SC04계약 v0.4
A3: 데이터 계약은 개발 인계를 위한 업무 기준입니다. API·권한·오류·상세 저장 명세는 다음 구현명세에서 확정합니다.
A5: 항목 | B5: 정의·키 | C5: 적재·계산 기준 | D5: 화면·근거
A6: 근거·버전 | B6: SC01~SC03 v0.3 + SC04 화면 v0.2 | C6: 원 30개 시트 중 검토요약은 v0.4로 갱신, 기존 검토요약은 검토요약_v02에 보존. 기타 원천·계산은 동일 의미 유지. | D6: 검토요약 / 모든 원 시트
A7: 화폐·기간 | B7: KRW / 가상 2027 / VAT 제외 | C7: Target 및 기준 Forecast 유지. 2027 연간·Q3·Q4·7~12월을 구분. 정상 연간 효과는 정액12개월 참고, 기존 향후12개월 전망을 갱신하지 않음. | D7: U402~404
A8: 시간 | B8: 신규 Excel 일시 = KST 벽시계 | C8: 신규 일시를 UTC로 해석해 9시간 이동하지 않음. 기존 파일 ISO의 Z 표현은 기존 계약의 KST 표시 규칙 준수. API에서는 +09:00 명시. | D8: SC04이벤트
A9: 비용 포함 | B9: ALT41 a가공 / ALT42 b가공 / ALT43 b재료 | C9: 원 단위원가의 하위 내역으로 새로 설명한 가상 비용. 기준 손익에 다시 더하지 않음. 증분만 반영. | D9: SC04근거
A10: 버전 합산 | B10: REP41-v1 / DEC41-v2 | C10: SC04월효과 row_id 고유. 버전별 조회 필수. 두 버전의 효과를 합산하지 않음. | D10: U404~405
A11: 공헌이익·고정비 | B11: 대안 증분의 모델 배부 | C11: ALT41 A-a, ALT42·43 A-b. c~e 영향0. 일회성비 포함 대안 관리손익 증분으로 표시하며 원 모델 공헌이익과 혼용하지 않음. 고정비는 공장합계에서 기존대로1회. | D11: U403~404
A12: 행위자 | B12: EX-PROD 생산 임원 / EX-BUY 구매 임원 / EX-SALES 영업 임원 | C12: 원 USR-PROD·BUY·SALES는 실무·분석 책임 역할 유지. 신규 임원은 결과 확인·실행책임 인수. USR-CFO가 전체 책임 및 예산 임원 겸임 가정. | D12: U401~408
A13: 관계 | B13: AT31→ALT41→ACT41 / AT32→ALT42·43→ACT42·43 | C13: AT33은 검토 후 제외, AT34는 원인분석과 DIR41. 다중 참조는 구현 시 연결 테이블로 분리. | D13: SC04분석결과
A14: 예산 | B14: 총괄18백만원 / 배분8·6·4백만원 | C14: 일회성 준비비용만 대상. 약정미집행·집행완료·미약정예정은 서로 중복 없는 구간. 여력=한도−세 구간 합계. 반복비용은 기존 운영예산에서 통제. | D14: U406~408
A15: 전용·초과 | B15: 무보고 전용 불허 | C15: 총괄한도 내 전용은 변경보고 후 전체 책임 임원 승인. 범위를 넘는 총괄 한도 초과는 대표 별도 승인. 전용 승인 후 실행 품의도 정상 절차 준수. | D15: POL41
A16: 종료 조건 | B16: 최신 승인·전체인수·개별인수·추가지시 | C16: 승인서, 조건 책임·확인자·기한, 지원·발굴 지시 인수, 장면5 인계자료 필요. CON41 이행 완료와 상세 계획 완성은 장면4 종료요건 아님. | D16: HANDOFF41
... A19: 가상 근거 출처 | B19: 사용자 승인 화면 v0.2, 기존 데이터 v0.3 | C19: 2026-10-23 사용자 요청으로 ALT41 대상량·회피단가 및 ALT42 건당비용 수정. 신규 값은 가상 설계이며 실제 기업 수치가 아님. | D19: 전체

Sheet SC04검증
A1: INNONOW SC04검증 v0.4
A3: 기본 가상안의 기대값 검증. 입력 변경 시 기대값과의 차이는 새 설계안 검토 대상으로 표시. 검증 결과는 계산 입력으로 사용하지 않음.
A5: 검증ID | B5: 항목 | C5: 기대값 | D5: 계산값 | E5: 차이 | F5: 결과
A6: CK401 | B6: 기준연간손익 | C6: 3299986680 | D6: =통합손익!K21 -> 3299986680 | E6: =D6-C6 -> 0 | F6: =IF(E6=0,"PASS","CHECK") -> PASS
A7: CK402 | B7: 기존부족 원인합계 | C7: 153939000 | D7: =SC04분석결과!E18 -> 153939000 | E7: =D7-C7 -> 0 | F7: =IF(E7=0,"PASS","CHECK") -> PASS
A8: CK403 | B8: 보고효과 | C8: 137200000 | D8: =SC04비교!C9 -> 137200000 | E8: =D8-C8 -> 0 | F8: =IF(E8=0,"PASS","CHECK") -> PASS
A9: CK404 | B9: 판단효과 | C9: 127800000 | D9: =SC04비교!D9 -> 127800000 | E9: =D9-C9 -> 0 | F9: =IF(E9=0,"PASS","CHECK") -> PASS
A10: CK405 | B10: 시점조정 | C10: -9400000 | D10: =SC04비교!E9 -> -9400000 | E10: =D10-C10 -> 0 | F10: =IF(E10=0,"PASS","CHECK") -> PASS
A11: CK406 | B11: 잔여부족 | C11: 49503320 | D11: =SC04월손익!H18 -> 49503320 | E11: =D11-C11 -> 0 | F11: =IF(E11=0,"PASS","CHECK") -> PASS
A12: CK407 | B12: 조건부제외부족 | C12: 85103320 | D12: =SC04월손익!J18 -> 85103320 | E12: =D12-C12 -> 0 | F12: =IF(E12=0,"PASS","CHECK") -> PASS
A13: CK408 | B13: 정상연간반복효과 | C13: 357600000 | D13: =SC04비교!F9 -> 357600000 | E13: =D13-C13 -> 0 | F13: =IF(E13=0,"PASS","CHECK") -> PASS
A14: CK409 | B14: 배분-총괄 | C14: 0 | D14: =SUM(SC04예산과제!E6:E8)-SC04예산과제!E9 -> 0 | E14: =D14-C14 -> 0 | F14: =IF(E14=0,"PASS","CHECK") -> PASS
A15: CK410 | B15: 예산여력 | C15: 11000000 | D15: =SC04예산과제!I9 -> 11000000 | E15: =D15-C15 -> 0 | F15: =IF(E15=0,"PASS","CHECK") -> PASS
A16: CK411 | B16: 판단 중복제거 | C16: 1800000 | D16: =SUMIFS(SC04월효과!N6:N41,SC04월효과!B6:B41,"DEC41-v2") -> 1800000 | E16: =D16-C16 -> 0 | F16: =IF(E16=0,"PASS","CHECK") -> PASS
A17: CK412 | B17: 고정비절감 | C17: 0 | D17: =SUM(SC04월효과!P6:P41) -> 0 | E17: =D17-C17 -> 0 | F17: =IF(E17=0,"PASS","CHECK") -> PASS
A18: CK413 | B18: 인수완료 | C18: 3 | D18: =COUNTIFS(SC04예산과제!M6:M8,"ACCEPTED") -> 3 | E18: =D18-C18 -> 0 | F18: =IF(E18=0,"PASS","CHECK") -> PASS
A19: CK414 | B19: 원 a~e 모델 보존 | C19: 0 | D19: =SUM(통합모델손익!E6:E10)-1898967800 -> 0 | E19: =D19-C19 -> 0 | F19: =IF(E19=0,"PASS","CHECK") -> PASS
A20: CK415 | B20: 손익 브리지 | C20: 0 | D20: =SC04월손익!G18-통합손익!K21-SC04비교!D9 -> 0 | E20: =D20-C20 -> 0 | F20: =IF(E20=0,"PASS","CHECK") -> PASS

Sheet SC05요약
A1: INNONOW SC05요약 v0.5
A3: SC01~SC05 v0.5. 기존 45개 Sheet는 보존. SC05요약부터 읽으십시오. 가상 업무연도 2027, 금액 원, VAT 제외.
A5: 항목 | B5: 값 | C5: 단위·상태 | D5: 설명
A6: 데이터 묶음 | B6: SC01~SC05 v0.5 | C6: 2026-10-24 | D6: 기존45개 Sheet 보존, SC05 확장 Sheet 추가. SC05요약·초기지표·월손익을 먼저 검토
A7: 가상 마감 기준 | B7: 46660 | C7: DATE | D7: 9월 실적 마감 후10/6 월간 Rolling 승인
A8: 9월 긴급구매 | B8: =SC05초기지표!C7 -> 5 | C8: 건 | D8: 기존 전망4건보다1건 많아 초기 실적은 다소 미달
A9: 9월 긴급 추가비 | B9: =SC05초기지표!C9 -> 6000000 | C9: 원 | D9: 운송·할증 비용. 60건 중5건
A10: 9월 추정 순개선 | B10: =SC05초기지표!C12 -> 8200000 | C10: 원 | D10: 기준14.4백만원−실제6백만원−지원0.2백만원
A11: 장면4 승인 예상효과 | B11: =SC04월손익!E18 -> 127800000 | C11: 원/당해연도 | D11: 127.8백만원 비교 기준 보존
A12: 마감기간 과제순효과 | B12: =SC05월손익!G19 -> 37200000 | C12: 원/1~9월 | D12: 37.2백만원. 일회성 비용·9월 지원비 포함
A13: 잔여기간 예상효과 | B13: =SC05월손익!G20 -> 91800000 | C13: 원/10~12월 | D13: 91.8백만원. ACT42 긴급건4·3·3 임원 확인 가정
A14: 갱신 연간 과제효과 | B14: =SC05월손익!G18 -> 129000000 | C14: 원/연간 | D14: 129백만원. 실적과 미실현 전망을 구분
A15: 갱신 공식 관리손익 | B15: =SC05월손익!H18 -> 3428986680 | C15: 원/연간 | D15: 10/6 대표 승인 후 공식본 FC51로 게시
A16: 변경하지 않는 Target | B16: =SC05월손익!C18 -> 3477290000 | C16: 원/연간 | D16: 울산 A제품 공장 관리손익 기준
A17: 남는 목표 부족 | B17: =SC05월손익!K18 -> 48303320 | C17: 원/연간 | D17: 48.30332백만원. Risk OPEN 유지
A18: 일회성 예산 잔여 | B18: =SC05예산!E9 -> 11000000 | C18: 원 | D18: 총18백만원 중7백만원 집행. 별도 운영비와 구분
A19: Agent 기여 | B19: 제안·수정·판단 분리 | C19: 참고 의견 반영 | D19: SC05Agent 8건. 누가 무엇을 제안·수정·확인했는지 표시
A20: U503 처리 | B20: 조건·품의·착수 통합 | C20: 참고 의견 반영 | D20: CON41·SUP41·REQ51·OP51·START51 연결. 별도 화면 분할 없음
A21: 검토 포인트 | B21: 초기 실적·Q4 가정·공식 전환 | C21: 가상 제안 | D21: 9월5건, Q4 4·3·3건, FC50 중간 공식본 및 FC51 갱신 흐름 검토

Sheet SC05설정
A1: INNONOW SC05설정 v0.5
A3: 사용자 확정 원칙을 바탕으로 구체 수치·일정을 제안. 노란 셀은 신규 가상 입력. 날짜 값의 화면 표시는 아래 자료형을 따른다.
A5: key | B5: value | C5: 단위·자료형 | D5: 정의·가상 가정
A6: actual_cutoff | B6: 46660 | C6: DATE | D6: 9월까지 가상 마감 실적. 10~12월 잔여 전망
A7: rolling_date | B7: 46666 | C7: DATE | D7: 대표 공식 Forecast 승인일
A8: as_of | B8: 46666.646 | C8: DATETIME_KST | D8: 기본안 종료 기대 상태. 초기 적재는 7/13 10시
A9: share_minutes | B9: 60 | C9: 분 | D9: 고객 변경 접수 후 생산 공유 허용시간
A10: confirm_minutes | B10: 120 | C10: 분 | D10: 생산 공유 후 구매 확인 허용시간
A11: clock_basis | B11: 달력 경과분 | C11: 규칙 | D11: 샘플은 모두 평일 업무시간 내. 야간은 당직 대행 즉시 접수하는 가상 규칙
A12: urgent_base_count | B12: 12 | C12: 건/월 | D12: 장면4 기준의 물량 정규화 비교 가정. 과거 실제 건수로 표기 금지
A13: urgent_unit_cost | B13: 1200000 | C13: 원/건 | D13: 긴급 운송 90만원 + 할증 30만원. 기존 변동비 내 포함
A14: monthly_support | B14: 200000 | C14: 원/월 | D14: 운영 적용 9월 이후. 일회성 예산과 별도 운영비
A15: oct_urgent_forecast | B15: 4 | C15: 건 | D15: 10월 전망. 기존 4건 유지
A16: nov_urgent_forecast | B16: 3 | C16: 건 | D16: 11월 개선 전망. 협조·대행 정착을 가정하며 미달 위험 유지
A17: dec_urgent_forecast | B17: 3 | C17: 건 | D17: 12월 개선 전망. 월별 확인 필요
A18: procurement_unit | B18: 주문 ID 단위 | C18: 집계 | D18: 분할 납품은 같은 주문 ID로 합산. 취소 건 제외
A19: profit_scope | B19: 울산 A제품 공장 관리손익 | C19: 범위 | D19: 5개 모델 합산 공헌이익−공장 고정비. 전사·본사·금융·세금 제외
A20: prior_official | B20: FC50 | C20: 버전 | D20: 9/6 승인된 가상 중간 월간 전망. SC04 검토안을 공식본으로 소급 전환하지 않음
A21: current_run | B21: RUN51 | C21: 산정본 | D21: 9월 마감+잔여 10~12월 전망. FC51-D→FC51 승인
A22: target_policy | B22: UNCHANGED | C22: 상태 | D22: 기존 Target 유지
